Workbook

Sheet Unternehmen
A1: Firma_ID | B1: Unternehmen | C1: Finanzwert (0/1) | D1: Branche (vorlaeufig) | E1: KPI1_Definition (Umsatzgroesse) | F1: KPI2_Definition (op. Ergebnisgroesse) | G1: Anmerkung
A2: ADS | B2: adidas AG | C2: 0 | D2: Konsumgueter | E2: Umsatzwachstum | F2: Operative Marge / Betriebsergebnis
A3: ALV | B3: Allianz SE | C3: 1 | D3: Versicherungen | E3: Umsatz | F3: Operatives Ergebnis | G3: Konzernumsatz-Prognose nur qualitativ -> KPI1 fehlend
A4: BAS | B4: BASF SE | C4: 0 | D4: Chemie | E4: Umsatzwachstum | F4: EBIT/EBITDA*
A5: BAYN | B5: Bayer AG | C5: 0 | D5: Pharma & Healthcare | E5: Umsatzerlöse | F5: EBITDA
A6: BEI | B6: Beiersdorf AG | C6: 0 | D6: Konsumgueter | E6: Umsatzentwicklung | F6: EBIT-Umsatzrendite | G6: Alle Geschäftsberichte zum Download unter https://www.beiersdorf.de/investor-relations/finanzberichte/finanzberichte-und-praesentationen
A7: BMW | B7: BMW AG | C7: 0 | D7: Automobile | E7: nicht prognostiziert | F7: EBIT-Marge | G7: Nur Segment Automobile betrachtet, Segment Motorräder außen vor gelassen (im vergleich ist das Segment winzig). Umsatzprognose wird nicht durchgeführt, da BMW intern nicht über Umsatz steuert und DRS 20 verlangt Prognosen nur für die intern verwendeten bedeutsamsten Leistungsindikatoren.
A8: CON | B8: Continental AG | C8: 0 | D8: Automobile | E8: Umsatz | F8: EBIT-Marge
A9: 1COV | B9: Covestro AG | C9: 0 | D9: Chemie | E9: nicht prognostiziert | F9: EBITDA | G9: Umsatz als KPI fehlt
A10: DAI | B10: Daimler AG | C10: 0 | D10: Automobile | E10: Umsatz | F10: Bereinigte Umsatzrendite MB Cars & Vans | G10: 12/2021 Spin-off Daimler Truck; ab GB 2021 Mercedes-Benz-Group; ab 2022 ggf. Segment Cars separat.
A11: DBK | B11: Deutsche Bank AG | C11: 1 | D11: Banken | E11: Erträge Konzern | F11: Eigenkapitalrendite nach Steuern | G11: KPI2: Jahresprognose nur im GB 2019 für 2020 und GB 2021 für 2022, übrige Jahre nur Mittelfristziele -> fehlend
A12: DB1 | B12: Deutsche Boerse AG | C12: 1 | D12: Finanzdienstleister | E12: Nettoerlöse | F12: EBITDA
A13: DPW | B13: Deutsche Post AG | C13: 0 | D13: Transport & Logistik | E13: nicht prognostiziert | F13: Konzern-EBIT | G13: KPI1 nicht prognostiziert, alle Jahre fehlend
A14: DTE | B14: Deutsche Telekom AG | C14: 0 | D14: Telekommunikation | E14: Umsatz | F14: Bereinigte EBITDA AL
A15: EOAN | B15: E.ON SE | C15: 0 | D15: Versorger | E15: nicht prognostiziert | F15: EBIT/EBITDA | G15: KPI1 nicht prognostiziert, alle Jahre fehlend KPI2: Für 2020 und 2021 EBIT; für 2022, 2023 und 2024 EBITDA
A16: FRE | B16: Fresenius SE & Co. KGaA | C16: 0 | D16: Pharma & Healthcare | E16: Umsatz | F16: Konzernergebnis/EBIT | G16: KPI2: Konzernergebnis für 2020 bis 2022, ab 2023 EBIT
A17: FME | B17: Fresenius Medical Care AG & Co. KGaA | C17: 0 | D17: Pharma & Healthcare | E17: Umsatzerlöse | F17: Operatives Ergebnis
A18: HEI | B18: HeidelbergCement AG | C18: 0 | D18: Bau | E18: Umsatz | F18: Ergebnis des laufenden Geschäftsbetriebs (RCO)
A19: HEN3 | B19: Henkel AG & Co. KGaA | C19: 0 | D19: Konsumgueter | E19: Organisches Umsatzwachstum | F19: EBIT-Marge (bereinigt)
A20: IFX | B20: Infineon Technologies AG | C20: 0 | D20: Technologie | E20: Umsatzwachstum | F20: Segmentergebnis-Marge
B21: Linde plc | D21: Chemie | E21: Ausgeschlossen, Begründung unter Kapitel 3.1
A22: LHA | B22: Deutsche Lufthansa AG | C22: 0 | D22: Transport & Logistik | F22: Bereinigtes EBIT
A23: MRK | B23: Merck KGaA | C23: 0 | D23: Pharma & Healthcare | E23: Umsatzerlöse | F23: EBITDA pre
A24: MTX | B24: MTU Aero Engines AG | C24: 0 | D24: Industrie | E24: Umsatz(/Bereinigter Umsatz) | F24: Bereinigtes EBIT/ EBIT-Marge
A25: MUV2 | B25: Muenchener Rueck AG | C25: 1 | D25: Versicherungen | E25: nicht prognostiziert | F25: Konzernergebnis | G25: Umsatz -> KPI1 fehlend
A26: RWE | B26: RWE AG | C26: 0 | D26: Versorger | E26: nicht prognostiziert | F26: Bereinigtes EBITDA | G26: Umsatz -> KPI1 fehlend
A27: SAP | B27: SAP SE | C27: 0 | D27: Technologie | E27: Cloud- und Softwareerlöse | F27: Betriebsergebnis Non-IFRS (wb.) | G27: Prognose Non-IFRS + waehrungsbereinigt
A28: SIE | B28: Siemens AG | C28: 0 | D28: Industrie | E28: Umsatzerlöse | F28: EBITA-Marge / EPS pre PPA | G28: Geschaeftsjahr endet 30.09. KPI2: Ergebnismarge Industrial Business (2020-2021), ab GJ 2022 EPS pre PPA wegen geänderter Konzernsteuerung nach Siemens-Energy-Spin-off 09/2020
A29: VOW3 | B29: Volkswagen AG | C29: 0 | D29: Automobile | E29: Umsatzerlöse | F29: Operative Umsatzrendite
A30: VNA | B30: Vonovia SE | C30: 0 | D30: Immobilien | E30: Group FFO | F30: Bereinigtes EBITDA | G30: KPI1: Group Funds from Operations -> wichtigste operative Kennzahl für Rentabilität und Cashflow in der Immobilienbranche. KPI1 ab 2023 fehlend (Prognose für 2024 fehlt).
B31: Wirecard | D31: Technologie | E31: Ausgeschlossen, Begründung unter Kapitel 3.1
A33: Stichprobe: DAX30 zum Stichtag 01.01.2020 (Stand nach Indexanpassung 09/2019). Ausgeschlossen: Wirecard AG (Insolvenz 2020, keine verlaesslichen Ist-Werte) und Linde plc (irische Gesellschaft, US-GAAP, keine DRS-20-Prognoseberichtspflicht) -> 28 Unternehmen. Quelle: STOXX, Historical Index Compositions of the Equity- and Strategy Indices.

Sheet Daten
A1: Firma_ID | B1: Ist_Jahr | C1: KPI | D1: GB_Prognosequelle | E1: Seite_Prognose | F1: Prognoseform | G1: Angabetyp | H1: Einheit | I1: Prog_Untergrenze | J1: Prog_Obergrenze | K1: Basiswert_Vorjahr | L1: Ist_Wert | M1: Veränderung zum Vorjahr | N1: Rahmensprengung | O1: GB_Ist_Quelle | P1: Seite_Ist | Q1: Anmerkung | R1: Prognose_final | S1: Fehler (Prog.-Ist) | T1: Rel_Fehler (nur absolut) | U1: APE (nur absolut) | V1: Treffer_Bandbreite (1/0) | W1: Prognose_Wortlaut | X1: Trefferkategorie | Y1: Fehler_PP (nur %-KPI) | Z1: Branche
A2: ADS | B2: 2020 | C2: Umsatz | D2: 2019: https://report.adidas-group.com/2019/de/serviceseiten/downloads/files/adidas_geschaeftsbericht_2019.pdf | E2: 129 | F2: Bandbreite | G2: Wachstumsrate % | H2: % (wb. Wachstumsrate) | I2: 0.06 | J2: 0.08 | K2: 0.06 | L2: -0.14 | M2: -20 PP | N2: -20 PP | O2: 2020: https://report.adidas-group.com/2020/de/serviceseiten/downloads/files/annual-report-adidas-gb20.pdf | P2: 200 | R2: =IF(NOT(ISNUMBER(I2)),"",IF(F2="Mindestprognose",I2,IF(ISNUMBER(J2),(I2+J2)/2,I2))) -> 0.07 | S2: =IF(OR(R2="",NOT(ISNUMBER(L2))),"",R2-L2) -> 0.21 | T2: =IF(OR(S2="",G2<>"absolut",NOT(ISNUMBER(L2)),L2=0),"",S2/ABS(L2)) | U2: =IF(T2="","",ABS(T2)) | V2: =IF(OR(F2="Punkt",NOT(ISNUMBER(L2))),"",IF(F2="Mindestprognose",IF(L2>=I2,1,0),IF(AND(ISNUMBER(I2),ISNUMBER(J2),I2<>J2),IF(AND(L2>=I2,L2<=J2),1,0),""))) -> 0 | X2: =IF(OR(F2="qualitativ",F2="fehlend",NOT(ISNUMBER(L2))),"nicht auswertbar",IF(F2="Punkt","Punktprognose",IF(AND(ISNUMBER(I2),ISNUMBER(J2),I2<>J2),IF(L2<I2,"unterhalb",IF(L2>J2,"oberhalb","innerhalb")),"nicht auswertbar"))) -> unterhalb | Y2: =IF(AND(ISNUMBER(S2),OR(G2="Marge %",G2="Wachstumsrate %")),ABS(S2),"") -> 0.21 | Z2: =IFERROR(VLOOKUP(A2,Unternehmen!$A:$D,4,FALSE()),"") -> Konsumgueter
A3: ADS | B3: 2020 | C3: Operative Ergebnisgroesse | D3: 2019: https://report.adidas-group.com/2019/de/serviceseiten/downloads/files/adidas_geschaeftsbericht_2019.pdf | E3: 130 | F3: Bandbreite | G3: Marge % | H3: % (op. Marge) | I3: 0.115 | J3: 0.118 | K3: 0.113 | L3: 0.038 | M3: -7,5 PP | N3: -0,20 PP | O3: 2020: https://report.adidas-group.com/2020/de/serviceseiten/downloads/files/annual-report-adidas-gb20.pdf | P3: 200 | R3: =IF(NOT(ISNUMBER(I3)),"",IF(F3="Mindestprognose",I3,IF(ISNUMBER(J3),(I3+J3)/2,I3))) -> 0.1165 | S3: =IF(OR(R3="",NOT(ISNUMBER(L3))),"",R3-L3) -> 0.0785 | T3: =IF(OR(S3="",G3<>"absolut",NOT(ISNUMBER(L3)),L3=0),"",S3/ABS(L3)) | U3: =IF(T3="","",ABS(T3)) | V3: =IF(OR(F3="Punkt",NOT(ISNUMBER(L3))),"",IF(F3="Mindestprognose",IF(L3>=I3,1,0),IF(AND(ISNUMBER(I3),ISNUMBER(J3),I3<>J3),IF(AND(L3>=I3,L3<=J3),1,0),""))) -> 0 | X3: =IF(OR(F3="qualitativ",F3="fehlend",NOT(ISNUMBER(L3))),"nicht auswertbar",IF(F3="Punkt","Punktprognose",IF(AND(ISNUMBER(I3),ISNUMBER(J3),I3<>J3),IF(L3<I3,"unterhalb",IF(L3>J3,"oberhalb","innerhalb")),"nicht auswertbar"))) -> unterhalb | Y3: =IF(AND(ISNUMBER(S3),OR(G3="Marge %",G3="Wachstumsrate %")),ABS(S3),"") -> 0.0785 | Z3: =IFERROR(VLOOKUP(A3,Unternehmen!$A:$D,4,FALSE()),"") -> Konsumgueter
A4: ADS | B4: 2021 | C4: Umsatz | D4: 2020: https://report.adidas-group.com/2020/de/serviceseiten/downloads/files/annual-report-adidas-gb20.pdf | E4: 178 | F4: Bandbreite | G4: Wachstumsrate % | H4: % (wb. Wachstumsrate) | I4: 0.15 | J4: 0.19 | K4: -0.14 | L4: 0.16 | M4: 30 PP | N4: im Rahmen | O4: 2021: https://report.adidas-group.com/2021/de/serviceseiten/downloads/files/annual-report-adidas-gb21.pdf | P4: 3 | R4: =IF(NOT(ISNUMBER(I4)),"",IF(F4="Mindestprognose",I4,IF(ISNUMBER(J4),(I4+J4)/2,I4))) -> 0.17 | S4: =IF(OR(R4="",NOT(ISNUMBER(L4))),"",R4-L4) -> 0.01 | T4: =IF(OR(S4="",G4<>"absolut",NOT(ISNUMBER(L4)),L4=0),"",S4/ABS(L4)) | U4: =IF(T4="","",ABS(T4)) | V4: =IF(OR(F4="Punkt",NOT(ISNUMBER(L4))),"",IF(F4="Mindestprognose",IF(L4>=I4,1,0),IF(AND(ISNUMBER(I4),ISNUMBER(J4),I4<>J4),IF(AND(L4>=I4,L4<=J4),1,0),""))) -> 1 | X4: =IF(OR(F4="qualitativ",F4="fehlend",NOT(ISNUMBER(L4))),"nicht auswertbar",IF(F4="Punkt","Punktprognose",IF(AND(ISNUMBER(I4),ISNUMBER(J4),I4<>J4),IF(L4<I4,"unterhalb",IF(L4>J4,"oberhalb","innerhalb")),"nicht auswertbar"))) -> innerhalb | Y4: =IF(AND(ISNUMBER(S4),OR(G4="Marge %",G4="Wachstumsrate %")),ABS(S4),"") -> 0.01 | Z4: =IFERROR(VLOOKUP(A4,Unternehmen!$A:$D,4,FALSE()),"") -> Konsumgueter
A5: ADS | B5: 2021 | C5: Operative Ergebnisgroesse | D5: 2020: https://report.adidas-group.com/2020/de/serviceseiten/downloads/files/annual-report-adidas-gb20.pdf | E5: 179 | F5: Bandbreite | G5: Marge % | H5: % (op. Marge) | I5: 0.09 | J5: 0.1 | K5: 0.04 | L5: 0.094 | M5: 5,3 PP | N5: im Rahmen | O5: 2021: https://report.adidas-group.com/2021/de/serviceseiten/downloads/files/annual-report-adidas-gb21.pdf | P5: 3 | R5: =IF(NOT(ISNUMBER(I5)),"",IF(F5="Mindestprognose",I5,IF(ISNUMBER(J5),(I5+J5)/2,I5))) -> 0.095 | S5: =IF(OR(R5="",NOT(ISNUMBER(L5))),"",R5-L5) -> 0.001 | T5: =IF(OR(S5="",G5<>"absolut",NOT(ISNUMBER(L5)),L5=0),"",S5/ABS(L5)) | U5: =IF(T5="","",ABS(T5)) | V5: =IF(OR(F5="Punkt",NOT(ISNUMBER(L5))),"",IF(F5="Mindestprognose",IF(L5>=I5,1,0),IF(AND(ISNUMBER(I5),ISNUMBER(J5),I5<>J5),IF(AND(L5>=I5,L5<=J5),1,0),""))) -> 1 | X5: =IF(OR(F5="qualitativ",F5="fehlend",NOT(ISNUMBER(L5))),"nicht auswertbar",IF(F5="Punkt","Punktprognose",IF(AND(ISNUMBER(I5),ISNUMBER(J5),I5<>J5),IF(L5<I5,"unterhalb",IF(L5>J5,"oberhalb","innerhalb")),"nicht auswertbar"))) -> innerhalb | Y5: =IF(AND(ISNUMBER(S5),OR(G5="Marge %",G5="Wachstumsrate %")),ABS(S5),"") -> 0.001 | Z5: =IFERROR(VLOOKUP(A5,Unternehmen!$A:$D,4,FALSE()),"") -> Konsumgueter
A6: ADS | B6: 2022 | C6: Umsatz | D6: 2021: https://report.adidas-group.com/2021/de/serviceseiten/downloads/files/annual-report-adidas-gb21.pdf | E6: 198 | F6: Bandbreite | G6: Wachstumsrate % | H6: % (wb. Wachstumsrate) | I6: 0.12 | J6: 0.14 | K6: =L4 -> 0.16 | L6: 0.01 | M6: -15 PP | N6: -11 PP | O6: 2022: https://report.adidas-group.com/2022/de/_assets/downloads/annual-report-adidas-gb22.pdf | P6: 3 | R6: =IF(NOT(ISNUMBER(I6)),"",IF(F6="Mindestprognose",I6,IF(ISNUMBER(J6),(I6+J6)/2,I6))) -> 0.13 | S6: =IF(OR(R6="",NOT(ISNUMBER(L6))),"",R6-L6) -> 0.12 | T6: =IF(OR(S6="",G6<>"absolut",NOT(ISNUMBER(L6)),L6=0),"",S6/ABS(L6)) | U6: =IF(T6="","",ABS(T6)) | V6: =IF(OR(F6="Punkt",NOT(ISNUMBER(L6))),"",IF(F6="Mindestprognose",IF(L6>=I6,1,0),IF(AND(ISNUMBER(I6),ISNUMBER(J6),I6<>J6),IF(AND(L6>=I6,L6<=J6),1,0),""))) -> 0 | X6: =IF(OR(F6="qualitativ",F6="fehlend",NOT(ISNUMBER(L6))),"nicht auswertbar",IF(F6="Punkt","Punktprognose",IF(AND(ISNUMBER(I6),ISNUMBER(J6),I6<>J6),IF(L6<I6,"unterhalb",IF(L6>J6,"oberhalb","innerhalb")),"nicht auswertbar"))) -> unterhalb | Y6: =IF(AND(ISNUMBER(S6),OR(G6="Marge %",G6="Wachstumsrate %")),ABS(S6),"") -> 0.12 | Z6: =IFERROR(VLOOKUP(A6,Unternehmen!$A:$D,4,FALSE()),"") -> Konsumgueter
A7: ADS | B7: 2022 | C7: Operative Ergebnisgroesse | D7: 2021:https://report.adidas-group.com/2021/de/serviceseiten/downloads/files/annual-report-adidas-gb21.pdf | E7: 198 | F7: Bandbreite | G7: Marge % | H7: % (op. Marge) | I7: 0.105 | J7: 0.11 | K7: =L5 -> 0.094 | L7: 0.03 | M7: -6,4 PP | N7: -16,9 PP | O7: 2022: https://report.adidas-group.com/2022/de/_assets/downloads/annual-report-adidas-gb22.pdf | P7: 3 | R7: =IF(NOT(ISNUMBER(I7)),"",IF(F7="Mindestprognose",I7,IF(ISNUMBER(J7),(I7+J7)/2,I7))) -> 0.1075 | S7: =IF(OR(R7="",NOT(ISNUMBER(L7))),"",R7-L7) -> 0.0775 | T7: =IF(OR(S7="",G7<>"absolut",NOT(ISNUMBER(L7)),L7=0),"",S7/ABS(L7)) | U7: =IF(T7="","",ABS(T7)) | V7: =IF(OR(F7="Punkt",NOT(ISNUMBER(L7))),"",IF(F7="Mindestprognose",IF(L7>=I7,1,0),IF(AND(ISNUMBER(I7),ISNUMBER(J7),I7<>J7),IF(AND(L7>=I7,L7<=J7),1,0),""))) -> 0 | X7: =IF(OR(F7="qualitativ",F7="fehlend",NOT(ISNUMBER(L7))),"nicht auswertbar",IF(F7="Punkt","Punktprognose",IF(AND(ISNUMBER(I7),ISNUMBER(J7),I7<>J7),IF(L7<I7,"unterhalb",IF(L7>J7,"oberhalb","innerhalb")),"nicht auswertbar"))) -> unterhalb | Y7: =IF(AND(ISNUMBER(S7),OR(G7="Marge %",G7="Wachstumsrate %")),ABS(S7),"") -> 0.0775 | Z7: =IFERROR(VLOOKUP(A7,Unternehmen!$A:$D,4,FALSE()),"") -> Konsumgueter
A8: ADS | B8: 2023 | C8: Umsatz | D8: 2022: https://report.adidas-group.com/2022/de/_assets/downloads/annual-report-adidas-gb22.pdf | E8: 169 | F8: Bandbreite | G8: Wachstumsrate % | H8: % (wb. Wachstumsrate) | I8: -0.09 | J8: -0.07 | K8: =L7 -> 0.03 | L8: 0 | M8: -3 PP | N8: Positiv außerhalb Prognose (oberhalb) | O8: 2023: https://report.adidas-group.com/2023/de/_assets/downloads/annual-report-adidas-gb23.pdf | P8: 4 | R8: =IF(NOT(ISNUMBER(I8)),"",IF(F8="Mindestprognose",I8,IF(ISNUMBER(J8),(I8+J8)/2,I8))) -> -0.08 | S8: =IF(OR(R8="",NOT(ISNUMBER(L8))),"",R8-L8) -> -0.08 | T8: =IF(OR(S8="",G8<>"absolut",NOT(ISNUMBER(L8)),L8=0),"",S8/ABS(L8)) | U8: =IF(T8="","",ABS(T8)) | V8: =IF(OR(F8="Punkt",NOT(ISNUMBER(L8))),"",IF(F8="Mindestprognose",IF(L8>=I8,1,0),IF(AND(ISNUMBER(I8),ISNUMBER(J8),I8<>J8),IF(AND(L8>=I8,L8<=J8),1,0),""))) -> 0 | X8: =IF(OR(F8="qualitativ",F8="fehlend",NOT(ISNUMBER(L8))),"nicht auswertbar",IF(F8="Punkt","Punktprognose",IF(AND(ISNUMBER(I8),ISNUMBER(J8),I8<>J8),IF(L8<I8,"unterhalb",IF(L8>J8,"oberhalb","innerhalb")),"nicht auswertbar"))) -> oberhalb | Y8: =IF(AND(ISNUMBER(S8),OR(G8="Marge %",G8="Wachstumsrate %")),ABS(S8),"") -> 0.08 | Z8: =IFERROR(VLOOKUP(A8,Unternehmen!$A:$D,4,FALSE()),"") -> Konsumgueter
A9: ADS | B9: 2023 | C9: Operative Ergebnisgroesse | D9: 2022: https://report.adidas-group.com/2022/de/_assets/downloads/annual-report-adidas-gb22.pdf | E9: 169 | F9: Punkt | G9: absolut | H9: Mio. EUR | I9: -700 | J9: -700 | L9: 268 | N9: Positiv außerhalb Prognose (oberhalb) | O9: 2023: https://report.adidas-group.com/2023/de/_assets/downloads/annual-report-adidas-gb23.pdf | P9: 4 | Q9: METHODIK: Prognose -700 Mio (Verlust) vs. Ist +268 Mio -> Vorzeichenwechsel, relativer Fehler (-361 %) statistisch nicht sinnvoll interpretierbar; als Ausreisser behandeln oder in Robustheitsrechnung ausschliessen | R9: =IF(NOT(ISNUMBER(I9)),"",IF(F9="Mindestprognose",I9,IF(ISNUMBER(J9),(I9+J9)/2,I9))) -> -700 | S9: =IF(OR(R9="",NOT(ISNUMBER(L9))),"",R9-L9) -> -968 | T9: =IF(OR(S9="",G9<>"absolut",NOT(ISNUMBER(L9)),L9=0),"",S9/ABS(L9)) -> -3.6119403 | U9: =IF(T9="","",ABS(T9)) -> 3.6119403 | V9: =IF(OR(F9="Punkt",NOT(ISNUMBER(L9))),"",IF(F9="Mindestprognose",IF(L9>=I9,1,0),IF(AND(ISNUMBER(I9),ISNUMBER(J9),I9<>J9),IF(AND(L9>=I9,L9<=J9),1,0),""))) | X9: =IF(OR(F9="qualitativ",F9="fehlend",NOT(ISNUMBER(L9))),"nicht auswertbar",IF(F9="Punkt","Punktprognose",IF(AND(ISNUMBER(I9),ISNUMBER(J9),I9<>J9),IF(L9<I9,"unterhalb",IF(L9>J9,"oberhalb","innerhalb")),"nicht auswertbar"))) -> Punktprognose | Y9: =IF(AND(ISNUMBER(S9),OR(G9="Marge %",G9="Wachstumsrate %")),ABS(S9),"") | Z9: =IFERROR(VLOOKUP(A9,Unternehmen!$A:$D,4,FALSE()),"") -> Konsumgueter
A10: ADS | B10: 2024 | C10: Umsatz | D10: 2023: https://report.adidas-group.com/2023/de/_assets/downloads/annual-report-adidas-gb23.pdf | E10: 179 | F10: Bandbreite | G10: Wachstumsrate % | H10: % (wb. Wachstumsrate) | I10: 0.04 | J10: 0.06 | K10: =L8 -> 0 | L10: 0.12 | M10: 12 PP | N10: Positiv außerhalb Prognose (oberhalb) | O10: 2024: https://report.adidas-group.com/2024/de/_assets/downloads/annual-report-adidas-gb24.pdf | P10: 4 | R10: =IF(NOT(ISNUMBER(I10)),"",IF(F10="Mindestprognose",I10,IF(ISNUMBER(J10),(I10+J10)/2,I10))) -> 0.05 | S10: =IF(OR(R10="",NOT(ISNUMBER(L10))),"",R10-L10) -> -0.07 | T10: =IF(OR(S10="",G10<>"absolut",NOT(ISNUMBER(L10)),L10=0),"",S10/ABS(L10)) | U10: =IF(T10="","",ABS(T10)) | V10: =IF(OR(F10="Punkt",NOT(ISNUMBER(L10))),"",IF(F10="Mindestprognose",IF(L10>=I10,1,0),IF(AND(ISNUMBER(I10),ISNUMBER(J10),I10<>J10),IF(AND(L10>=I10,L10<=J10),1,0),""))) -> 0 | X10: =IF(OR(F10="qualitativ",F10="fehlend",NOT(ISNUMBER(L10))),"nicht auswertbar",IF(F10="Punkt","Punktprognose",IF(AND(ISNUMBER(I10),ISNUMBER(J10),I10<>J10),IF(L10<I10,"unterhalb",IF(L10>J10,"oberhalb","innerhalb")),"nicht auswertbar"))) -> oberhalb | Y10: =IF(AND(ISNUMBER(S10),OR(G10="Marge %",G10="Wachstumsrate %")),ABS(S10),"") -> 0.07 | Z10: =IFERROR(VLOOKUP(A10,Unternehmen!$A:$D,4,FALSE()),"") -> Konsumgueter
A11: ADS | B11: 2024 | C11: Operative Ergebnisgroesse | D11: 2023: https://report.adidas-group.com/2023/de/_assets/downloads/annual-report-adidas-gb23.pdf | E11: 179 | F11: Punkt | G11: absolut | H11: Mio. EUR | I11: 500 | J11: 500 | K11: =L9 -> 268 | L11: 1337 | M11: =L11-K11 -> 1069 | N11: Positiv außerhalb Prognose (oberhalb) | O11: 2024: https://report.adidas-group.com/2024/de/_assets/downloads/annual-report-adidas-gb24.pdf | P11: 4 | R11: =IF(NOT(ISNUMBER(I11)),"",IF(F11="Mindestprognose",I11,IF(ISNUMBER(J11),(I11+J11)/2,I11))) -> 500 | S11: =IF(OR(R11="",NOT(ISNUMBER(L11))),"",R11-L11) -> -837 | T11: =IF(OR(S11="",G11<>"absolut",NOT(ISNUMBER(L11)),L11=0),"",S11/ABS(L11)) -> -0.62602842 | U11: =IF(T11="","",ABS(T11)) -> 0.62602842 | V11: =IF(OR(F11="Punkt",NOT(ISNUMBER(L11))),"",IF(F11="Mindestprognose",IF(L11>=I11,1,0),IF(AND(ISNUMBER(I11),ISNUMBER(J11),I11<>J11),IF(AND(L11>=I11,L11<=J11),1,0),""))) | X11: =IF(OR(F11="qualitativ",F11="fehlend",NOT(ISNUMBER(L11))),"nicht auswertbar",IF(F11="Punkt","Punktprognose",IF(AND(ISNUMBER(I11),ISNUMBER(J11),I11<>J11),IF(L11<I11,"unterhalb",IF(L11>J11,"oberhalb","innerhalb")),"nicht auswertbar"))) -> Punktprognose | Y11: =IF(AND(ISNUMBER(S11),OR(G11="Marge %",G11="Wachstumsrate %")),ABS(S11),"") | Z11: =IFERROR(VLOOKUP(A11,Unternehmen!$A:$D,4,FALSE()),"") -> Konsumgueter
A12: ALV | B12: 2020 | C12: Operative Ergebnisgroesse | D12: 2019: https://www.allianz.com/content/dam/onemarketing/azcom/Allianz_com/investor-relations/en/results-reports/annual-report/ar-2019/de-GB-Gruppe-Geschaeftsbericht-Allianz-2019.pdf | E12: 67 | F12: Punkt mit Korridor | G12: absolut | H12: Mrd. EUR | I12: 11.5 | J12: 12.5 | K12: 11.855 | L12: 10.751 | M12: =L12-K12 -> -1.104 | N12: -750 Mio. EUR | O12: 2020: https://www.allianz.com/content/dam/onemarketing/azcom/Allianz_com/investor-relations/en/results-reports/annual-report/ar-2020/de-Allianz-Gruppe-Geschaeftsbericht-2020.pdf | P12: 67 | R12: =IF(NOT(ISNUMBER(I12)),"",IF(F12="Mindestprognose",I12,IF(ISNUMBER(J12),(I12+J12)/2,I12))) -> 12 | S12: =IF(OR(R12="",NOT(ISNUMBER(L12))),"",R12-L12) -> 1.249 | T12: =IF(OR(S12="",G12<>"absolut",NOT(ISNUMBER(L12)),L12=0),"",S12/ABS(L12)) -> 0.11617524 | U12: =IF(T12="","",ABS(T12)) -> 0.11617524 | V12: =IF(OR(F12="Punkt",NOT(ISNUMBER(L12))),"",IF(F12="Mindestprognose",IF(L12>=I12,1,0),IF(AND(ISNUMBER(I12),ISNUMBER(J12),I12<>J12),IF(AND(L12>=I12,L12<=J12),1,0),""))) -> 0 | X12: =IF(OR(F12="qualitativ",F12="fehlend",NOT(ISNUMBER(L12))),"nicht auswertbar",IF(F12="Punkt","Punktprognose",IF(AND(ISNUMBER(I12),ISNUMBER(J12),I12<>J12),IF(L12<I12,"unterhalb",IF(L12>J12,"oberhalb","innerhalb")),"nicht auswertbar"))) -> unterhalb | Y12: =IF(AND(ISNUMBER(S12),OR(G12="Marge %",G12="Wachstumsrate %")),ABS(S12),"") | Z12: =IFERROR(VLOOKUP(A12,Unternehmen!$A:$D,4,FALSE()),"") -> Versicherungen
A13: ALV | B13: 2020 | C13: Umsatz | D13: 2019: https://www.allianz.com/content/dam/onemarketing/azcom/Allianz_com/investor-relations/en/results-reports/annual-report/ar-2019/de-GB-Gruppe-Geschaeftsbericht-Allianz-2019.pdf | E13: 68 | F13: qualitativ | G13: absolut | H13: Mio. EUR | K13: 142.369 | L13: 140.455 | M13: =L13-K13 -> -1.914 | N13: Um 1.914 gesunken, obwohl es hätte steigen sollen | O13: 2020: https://www.allianz.com/content/dam/onemarketing/azcom/Allianz_com/investor-relations/en/results-reports/annual-report/ar-2020/de-Allianz-Gruppe-Geschaeftsbericht-2020.pdf | P13: 67 | R13: =IF(NOT(ISNUMBER(I13)),"",IF(F13="Mindestprognose",I13,IF(ISNUMBER(J13),(I13+J13)/2,I13))) | S13: =IF(OR(R13="",NOT(ISNUMBER(L13))),"",R13-L13) | T13: =IF(OR(S13="",G13<>"absolut",NOT(ISNUMBER(L13)),L13=0),"",S13/ABS(L13)) | U13: =IF(T13="","",ABS(T13)) | V13: =IF(OR(F13="Punkt",NOT(ISNUMBER(L13))),"",IF(F13="Mindestprognose",IF(L13>=I13,1,0),IF(AND(ISNUMBER(I13),ISNUMBER(J13),I13<>J13),IF(AND(L13>=I13,L13<=J13),1,0),""))) | W13: Moderates Wachstum | X13: =IF(OR(F13="qualitativ",F13="fehlend",NOT(ISNUMBER(L13))),"nicht auswertbar",IF(F13="Punkt","Punktprognose",IF(AND(ISNUMBER(I13),ISNUMBER(J13),I13<>J13),IF(L13<I13,"unterhalb",IF(L13>J13,"oberhalb","innerhalb")),"nicht auswertbar"))) -> nicht auswertbar | Y13: =IF(AND(ISNUMBER(S13),OR(G13="Marge %",G13="Wachstumsrate %")),ABS(S13),"") | Z13: =IFERROR(VLOOKUP(A13,Unternehmen!$A:$D,4,FALSE()),"") -> Versicherungen
A14: ALV | B14: 2021 | C14: Operative Ergebnisgroesse | D14: 2020: https://www.allianz.com/content/dam/onemarketing/azcom/Allianz_com/investor-relations/en/results-reports/annual-report/ar-2020/de-Allianz-Gruppe-Geschaeftsbericht-2020.pdf | E14: 80 | F14: Punkt mit Korridor | G14: absolut | H14: Mrd. EUR | I14: 11 | J14: 13 | K14: =L12 -> 10.751 | L14: 13.4 | M14: =L14-K14 -> 2.649 | N14: Positiv außerhalb Prognose (oberhalb) | O14: 2021: https://www.allianz.com/content/dam/onemarketing/azcom/Allianz_com/investor-relations/en/results-reports/annual-report/ar-2021/de-Allianz-Gruppe-Geschaeftsbericht-2021.pdf | P14: 78 | R14: =IF(NOT(ISNUMBER(I14)),"",IF(F14="Mindestprognose",I14,IF(ISNUMBER(J14),(I14+J14)/2,I14))) -> 12 | S14: =IF(OR(R14="",NOT(ISNUMBER(L14))),"",R14-L14) -> -1.4 | T14: =IF(OR(S14="",G14<>"absolut",NOT(ISNUMBER(L14)),L14=0),"",S14/ABS(L14)) -> -0.10447761 | U14: =IF(T14="","",ABS(T14)) -> 0.10447761 | V14: =IF(OR(F14="Punkt",NOT(ISNUMBER(L14))),"",IF(F14="Mindestprognose",IF(L14>=I14,1,0),IF(AND(ISNUMBER(I14),ISNUMBER(J14),I14<>J14),IF(AND(L14>=I14,L14<=J14),1,0),""))) -> 0 | X14: =IF(OR(F14="qualitativ",F14="fehlend",NOT(ISNUMBER(L14))),"nicht auswertbar",IF(F14="Punkt","Punktprognose",IF(AND(ISNUMBER(I14),ISNUMBER(J14),I14<>J14),IF(L14<I14,"unterhalb",IF(L14>J14,"oberhalb","innerhalb")),"nicht auswertbar"))) -> oberhalb | Y14: =IF(AND(ISNUMBER(S14),OR(G14="Marge %",G14="Wachstumsrate %")),ABS(S14),"") | Z14: =IFERROR(VLOOKUP(A14,Unternehmen!$A:$D,4,FALSE()),"") -> Versicherungen
A15: ALV | B15: 2021 | C15: Umsatz | D15: 2020: https://www.allianz.com/content/dam/onemarketing/azcom/Allianz_com/investor-relations/en/results-reports/annual-report/ar-2020/de-Allianz-Gruppe-Geschaeftsbericht-2020.pdf | E15: 80 | F15: qualitativ | G15: absolut | H15: Mio. EUR | K15: =L13 -> 140.455 | L15: 148.511 | M15: =L15-K15 -> 8.056 | N15: im Rahmen | O15: 2021: https://www.allianz.com/content/dam/onemarketing/azcom/Allianz_com/investor-relations/en/results-reports/annual-report/ar-2021/de-Allianz-Gruppe-Geschaeftsbericht-2021.pdf | P15: 78 | R15: =IF(NOT(ISNUMBER(I15)),"",IF(F15="Mindestprognose",I15,IF(ISNUMBER(J15),(I15+J15)/2,I15))) | S15: =IF(OR(R15="",NOT(ISNUMBER(L15))),"",R15-L15) | T15: =IF(OR(S15="",G15<>"absolut",NOT(ISNUMBER(L15)),L15=0),"",S15/ABS(L15)) | U15: =IF(T15="","",ABS(T15)) | V15: =IF(OR(F15="Punkt",NOT(ISNUMBER(L15))),"",IF(F15="Mindestprognose",IF(L15>=I15,1,0),IF(AND(ISNUMBER(I15),ISNUMBER(J15),I15<>J15),IF(AND(L15>=I15,L15<=J15),1,0),""))) | W15: Moderates Wachstum | X15: =IF(OR(F15="qualitativ",F15="fehlend",NOT(ISNUMBER(L15))),"nicht auswertbar",IF(F15="Punkt","Punktprognose",IF(AND(ISNUMBER(I15),ISNUMBER(J15),I15<>J15),IF(L15<I15,"unterhalb",IF(L15>J15,"oberhalb","innerhalb")),"nicht auswertbar"))) -> nicht auswertbar | Y15: =IF(AND(ISNUMBER(S15),OR(G15="Marge %",G15="Wachstumsrate %")),ABS(S15),"") | Z15: =IFERROR(VLOOKUP(A15,Unternehmen!$A:$D,4,FALSE()),"") -> Versicherungen
A16: ALV | B16: 2022 | C16: Operative Ergebnisgroesse | D16: 2021: https://www.allianz.com/content/dam/onemarketing/azcom/Allianz_com/investor-relations/en/results-reports/annual-report/ar-2021/de-Allianz-Gruppe-Geschaeftsbericht-2021.pdf | E16: 90 | F16: Punkt mit Korridor | G16: absolut | H16: Mrd. EUR | I16: 12.4 | J16: 14.4 | K16: =L14 -> 13.4 | L16: 14.164 | M16: =L16-K16 -> 0.764 | N16: im Rahmen | O16: 2022: https://www.allianz.com/content/dam/onemarketing/azcom/Allianz_com/investor-relations/en/results-reports/annual-report/ar-2022/de-Allianz-Gruppe-Geschaeftsbericht-2022.pdf | P16: 81 | R16: =IF(NOT(ISNUMBER(I16)),"",IF(F16="Mindestprognose",I16,IF(ISNUMBER(J16),(I16+J16)/2,I16))) -> 13.4 | S16: =IF(OR(R16="",NOT(ISNUMBER(L16))),"",R16-L16) -> -0.764 | T16: =IF(OR(S16="",G16<>"absolut",NOT(ISNUMBER(L16)),L16=0),"",S16/ABS(L16)) -> -0.053939565 | U16: =IF(T16="","",ABS(T16)) -> 0.053939565 | V16: =IF(OR(F16="Punkt",NOT(ISNUMBER(L16))),"",IF(F16="Mindestprognose",IF(L16>=I16,1,0),IF(AND(ISNUMBER(I16),ISNUMBER(J16),I16<>J16),IF(AND(L16>=I16,L16<=J16),1,0),""))) -> 1 | X16: =IF(OR(F16="qualitativ",F16="fehlend",NOT(ISNUMBER(L16))),"nicht auswertbar",IF(F16="Punkt","Punktprognose",IF(AND(ISNUMBER(I16),ISNUMBER(J16),I16<>J16),IF(L16<I16,"unterhalb",IF(L16>J16,"oberhalb","innerhalb")),"nicht auswertbar"))) -> innerhalb | Y16: =IF(AND(ISNUMBER(S16),OR(G16="Marge %",G16="Wachstumsrate %")),ABS(S16),"") | Z16: =IFERROR(VLOOKUP(A16,Unternehmen!$A:$D,4,FALSE()),"") -> Versicherungen
A17: ALV | B17: 2022 | C17: Umsatz | D17: 2021: https://www.allianz.com/content/dam/onemarketing/azcom/Allianz_com/investor-relations/en/results-reports/annual-report/ar-2021/de-Allianz-Gruppe-Geschaeftsbericht-2021.pdf | E17: 91 | F17: qualitativ | G17: absolut | H17: Mio. EUR | K17: =L15 -> 148.511 | L17: 152.671 | M17: =L17-K17 -> 4.16 | N17: im Rahmen | O17: 2022: https://www.allianz.com/content/dam/onemarketing/azcom/Allianz_com/investor-relations/en/results-reports/annual-report/ar-2022/de-Allianz-Gruppe-Geschaeftsbericht-2022.pdf | P17: 81 | R17: =IF(NOT(ISNUMBER(I17)),"",IF(F17="Mindestprognose",I17,IF(ISNUMBER(J17),(I17+J17)/2,I17))) | S17: =IF(OR(R17="",NOT(ISNUMBER(L17))),"",R17-L17) | T17: =IF(OR(S17="",G17<>"absolut",NOT(ISNUMBER(L17)),L17=0),"",S17/ABS(L17)) | U17: =IF(T17="","",ABS(T17)) | V17: =IF(OR(F17="Punkt",NOT(ISNUMBER(L17))),"",IF(F17="Mindestprognose",IF(L17>=I17,1,0),IF(AND(ISNUMBER(I17),ISNUMBER(J17),I17<>J17),IF(AND(L17>=I17,L17<=J17),1,0),""))) | W17: Moderates Wachstum | X17: =IF(OR(F17="qualitativ",F17="fehlend",NOT(ISNUMBER(L17))),"nicht auswertbar",IF(F17="Punkt","Punktprognose",IF(AND(ISNUMBER(I17),ISNUMBER(J17),I17<>J17),IF(L17<I17,"unterhalb",IF(L17>J17,"oberhalb","innerhalb")),"nicht auswertbar"))) -> nicht auswertbar | Y17: =IF(AND(ISNUMBER(S17),OR(G17="Marge %",G17="Wachstumsrate %")),ABS(S17),"") | Z17: =IFERROR(VLOOKUP(A17,Unternehmen!$A:$D,4,FALSE()),"") -> Versicherungen
A18: ALV | B18: 2023 | C18: Operative Ergebnisgroesse | D18: 2022: https://www.allianz.com/content/dam/onemarketing/azcom/Allianz_com/investor-relations/en/results-reports/annual-report/ar-2022/de-Allianz-Gruppe-Geschaeftsbericht-2022.pdf | E18: 94 | F18: Punkt mit Korridor | G18: absolut | H18: Mrd. EUR | I18: 13.2 | J18: 15.2 | K18: =L16 -> 14.164 | L18: 14.7 | M18: =L18-K18 -> 0.536 | N18: im Rahmen | O18: 2023: https://www.allianz.com/content/dam/onemarketing/azcom/Allianz_com/investor-relations/en/results-reports/annual-report/ar-2023/de-Allianz-Gruppe-Geschaeftsbericht-2023.pdf | P18: 128 | R18: =IF(NOT(ISNUMBER(I18)),"",IF(F18="Mindestprognose",I18,IF(ISNUMBER(J18),(I18+J18)/2,I18))) -> 14.2 | S18: =IF(OR(R18="",NOT(ISNUMBER(L18))),"",R18-L18) -> -0.5 | T18: =IF(OR(S18="",G18<>"absolut",NOT(ISNUMBER(L18)),L18=0),"",S18/ABS(L18)) -> -0.034013605 | U18: =IF(T18="","",ABS(T18)) -> 0.034013605 | V18: =IF(OR(F18="Punkt",NOT(ISNUMBER(L18))),"",IF(F18="Mindestprognose",IF(L18>=I18,1,0),IF(AND(ISNUMBER(I18),ISNUMBER(J18),I18<>J18),IF(AND(L18>=I18,L18<=J18),1,0),""))) -> 1 | X18: =IF(OR(F18="qualitativ",F18="fehlend",NOT(ISNUMBER(L18))),"nicht auswertbar",IF(F18="Punkt","Punktprognose",IF(AND(ISNUMBER(I18),ISNUMBER(J18),I18<>J18),IF(L18<I18,"unterhalb",IF(L18>J18,"oberhalb","innerhalb")),"nicht auswertbar"))) -> innerhalb | Y18: =IF(AND(ISNUMBER(S18),OR(G18="Marge %",G18="Wachstumsrate %")),ABS(S18),"") | Z18: =IFERROR(VLOOKUP(A18,Unternehmen!$A:$D,4,FALSE()),"") -> Versicherungen
A19: ALV | B19: 2023 | C19: Umsatz | D19: 2022: https://www.allianz.com/content/dam/onemarketing/azcom/Allianz_com/investor-relations/en/results-reports/annual-report/ar-2022/de-Allianz-Gruppe-Geschaeftsbericht-2022.pdf | E19: 94 | F19: Punkt | G19: Wachstumsrate % | H19: % (wb. Wachstumsrate) | I19: 0.07 | J19: 0.07 | L19: 0.08 | N19: Positiv außerhalb Prognose (oberhalb) | O19: 2023: https://www.allianz.com/content/dam/onemarketing/azcom/Allianz_com/investor-relations/en/results-reports/annual-report/ar-2023/de-Allianz-Gruppe-Geschaeftsbericht-2023.pdf | P19: 128 | R19: =IF(NOT(ISNUMBER(I19)),"",IF(F19="Mindestprognose",I19,IF(ISNUMBER(J19),(I19+J19)/2,I19))) -> 0.07 | S19: =IF(OR(R19="",NOT(ISNUMBER(L19))),"",R19-L19) -> -0.01 | T19: =IF(OR(S19="",G19<>"absolut",NOT(ISNUMBER(L19)),L19=0),"",S19/ABS(L19)) | U19: =IF(T19="","",ABS(T19)) | V19: =IF(OR(F19="Punkt",NOT(ISNUMBER(L19))),"",IF(F19="Mindestprognose",IF(L19>=I19,1,0),IF(AND(ISNUMBER(I19),ISNUMBER(J19),I19<>J19),IF(AND(L19>=I19,L19<=J19),1,0),""))) | W19: + 7% | X19: =IF(OR(F19="qualitativ",F19="fehlend",NOT(ISNUMBER(L19))),"nicht auswertbar",IF(F19="Punkt","Punktprognose",IF(AND(ISNUMBER(I19),ISNUMBER(J19),I19<>J19),IF(L19<I19,"unterhalb",IF(L19>J19,"oberhalb","innerhalb")),"nicht auswertbar"))) -> Punktprognose | Y19: =IF(AND(ISNUMBER(S19),OR(G19="Marge %",G19="Wachstumsrate %")),ABS(S19),"") -> 0.01 | Z19: =IFERROR(VLOOKUP(A19,Unternehmen!$A:$D,4,FALSE()),"") -> Versicherungen
A20: ALV | B20: 2024 | C20: Operative Ergebnisgroesse | D20: 2023: https://www.allianz.com/content/dam/onemarketing/azcom/Allianz_com/investor-relations/en/results-reports/annual-report/ar-2023/de-Allianz-Gruppe-Geschaeftsbericht-2023.pdf | E20: 130 | F20: Punkt mit Korridor | G20: absolut | H20: Mrd. EUR | I20: 13.8 | J20: 15.8 | K20: =L18 -> 14.7 | L20: 16 | M20: =L20-K20 -> 1.3 | N20: Positiv außerhalb Prognose (oberhalb) | O20: 2024: https://www.allianz.com/content/dam/onemarketing/azcom/Allianz_com/investor-relations/en/results-reports/annual-report/ar-2024/de-allianz-gruppe-geschaeftsbericht-2024.pdf | P20: 222 | R20: =IF(NOT(ISNUMBER(I20)),"",IF(F20="Mindestprognose",I20,IF(ISNUMBER(J20),(I20+J20)/2,I20))) -> 14.8 | S20: =IF(OR(R20="",NOT(ISNUMBER(L20))),"",R20-L20) -> -1.2 | T20: =IF(OR(S20="",G20<>"absolut",NOT(ISNUMBER(L20)),L20=0),"",S20/ABS(L20)) -> -0.075 | U20: =IF(T20="","",ABS(T20)) -> 0.075 | V20: =IF(OR(F20="Punkt",NOT(ISNUMBER(L20))),"",IF(F20="Mindestprognose",IF(L20>=I20,1,0),IF(AND(ISNUMBER(I20),ISNUMBER(J20),I20<>J20),IF(AND(L20>=I20,L20<=J20),1,0),""))) -> 0 | X20: =IF(OR(F20="qualitativ",F20="fehlend",NOT(ISNUMBER(L20))),"nicht auswertbar",IF(F20="Punkt","Punktprognose",IF(AND(ISNUMBER(I20),ISNUMBER(J20),I20<>J20),IF(L20<I20,"unterhalb",IF(L20>J20,"oberhalb","innerhalb")),"nicht auswertbar"))) -> oberhalb | Y20: =IF(AND(ISNUMBER(S20),OR(G20="Marge %",G20="Wachstumsrate %")),ABS(S20),"") | Z20: =IFERROR(VLOOKUP(A20,Unternehmen!$A:$D,4,FALSE()),"") -> Versicherungen
A21: ALV | B21: 2024 | C21: Umsatz | D21: 2023: https://www.allianz.com/content/dam/onemarketing/azcom/Allianz_com/investor-relations/en/results-reports/annual-report/ar-2023/de-Allianz-Gruppe-Geschaeftsbericht-2023.pdf | E21: 130 | F21: Punkt | G21: Wachstumsrate % | H21: % (wb. Wachstumsrate) | I21: 0.03 | J21: 0.03 | K21: =L19 -> 0.08 | L21: 0.083 | M21: 5,30 PP | N21: im Rahmen | O21: 2024: https://www.allianz.com/content/dam/onemarketing/azcom/Allianz_com/investor-relations/en/results-reports/annual-report/ar-2024/de-allianz-gruppe-geschaeftsbericht-2024.pdf | P21: 222 | R21: =IF(NOT(ISNUMBER(I21)),"",IF(F21="Mindestprognose",I21,IF(ISNUMBER(J21),(I21+J21)/2,I21))) -> 0.03 | S21: =IF(OR(R21="",NOT(ISNUMBER(L21))),"",R21-L21) -> -0.053 | T21: =IF(OR(S21="",G21<>"absolut",NOT(ISNUMBER(L21)),L21=0),"",S21/ABS(L21)) | U21: =IF(T21="","",ABS(T21)) | V21: =IF(OR(F21="Punkt",NOT(ISNUMBER(L21))),"",IF(F21="Mindestprognose",IF(L21>=I21,1,0),IF(AND(ISNUMBER(I21),ISNUMBER(J21),I21<>J21),IF(AND(L21>=I21,L21<=J21),1,0),""))) | W21: + 3% | X21: =IF(OR(F21="qualitativ",F21="fehlend",NOT(ISNUMBER(L21))),"nicht auswertbar",IF(F21="Punkt","Punktprognose",IF(AND(ISNUMBER(I21),ISNUMBER(J21),I21<>J21),IF(L21<I21,"unterhalb",IF(L21>J21,"oberhalb","innerhalb")),"nicht auswertbar"))) -> Punktprognose | Y21: =IF(AND(ISNUMBER(S21),OR(G21="Marge %",G21="Wachstumsrate %")),ABS(S21),"") -> 0.053 | Z21: =IFERROR(VLOOKUP(A21,Unternehmen!$A:$D,4,FALSE()),"") -> Versicherungen
A22: BAS | B22: 2020 | C22: Umsatz | D22: 2019: https://www.basf.com/dam/jcr:19509d83-1670-32bb-b58a-2ca8c594eb86/basf/www/global/documents/de/investor-relations/calendar-and-publications/reports/2020/BASF_Bericht_2019.pdf | E22: 136 | F22: Punkt mit Korridor | G22: absolut | H22: Mrd. EUR | I22: 60 | J22: 63 | K22: 59.316 | L22: 59.149 | M22: =L22-K22 -> -0.167 | N22: -0,85 Mrd. EUR | O22: 2020: https://www.basf.com/dam/jcr:14cf35ed-802f-3b49-8bef-363aa9646373/basf/www/global/documents/de/investor-relations/calendar-and-publications/reports/2021/BASF_Bericht_2020.pdf | P22: 156 | R22: =IF(NOT(ISNUMBER(I22)),"",IF(F22="Mindestprognose",I22,IF(ISNUMBER(J22),(I22+J22)/2,I22))) -> 61.5 | S22: =IF(OR(R22="",NOT(ISNUMBER(L22))),"",R22-L22) -> 2.351 | T22: =IF(OR(S22="",G22<>"absolut",NOT(ISNUMBER(L22)),L22=0),"",S22/ABS(L22)) -> 0.039747079 | U22: =IF(T22="","",ABS(T22)) -> 0.039747079 | V22: =IF(OR(F22="Punkt",NOT(ISNUMBER(L22))),"",IF(F22="Mindestprognose",IF(L22>=I22,1,0),IF(AND(ISNUMBER(I22),ISNUMBER(J22),I22<>J22),IF(AND(L22>=I22,L22<=J22),1,0),""))) -> 0 | X22: =IF(OR(F22="qualitativ",F22="fehlend",NOT(ISNUMBER(L22))),"nicht auswertbar",IF(F22="Punkt","Punktprognose",IF(AND(ISNUMBER(I22),ISNUMBER(J22),I22<>J22),IF(L22<I22,"unterhalb",IF(L22>J22,"oberhalb","innerhalb")),"nicht auswertbar"))) -> unterhalb | Y22: =IF(AND(ISNUMBER(S22),OR(G22="Marge %",G22="Wachstumsrate %")),ABS(S22),"") | Z22: =IFERROR(VLOOKUP(A22,Unternehmen!$A:$D,4,FALSE()),"") -> Chemie
A23: BAS | B23: 2020 | C23: Operative Ergebnisgroesse | D23: 2019: https://www.basf.com/dam/jcr:19509d83-1670-32bb-b58a-2ca8c594eb86/basf/www/global/documents/de/investor-relations/calendar-and-publications/reports/2020/BASF_Bericht_2019.pdf | E23: 136 | F23: Punkt mit Korridor | G23: absolut | H23: Mrd. EUR | I23: 4.2 | J23: 4.8 | K23: 4.536 | L23: 3.56 | M23: =L23-K23 -> -0.976 | N23: -0,64 Mrd. EUR | O23: 2020: https://www.basf.com/dam/jcr:14cf35ed-802f-3b49-8bef-363aa9646373/basf/www/global/documents/de/investor-relations/calendar-and-publications/reports/2021/BASF_Bericht_2020.pdf | P23: 156 | R23: =IF(NOT(ISNUMBER(I23)),"",IF(F23="Mindestprognose",I23,IF(ISNUMBER(J23),(I23+J23)/2,I23))) -> 4.5 | S23: =IF(OR(R23="",NOT(ISNUMBER(L23))),"",R23-L23) -> 0.94 | T23: =IF(OR(S23="",G23<>"absolut",NOT(ISNUMBER(L23)),L23=0),"",S23/ABS(L23)) -> 0.26404494 | U23: =IF(T23="","",ABS(T23)) -> 0.26404494 | V23: =IF(OR(F23="Punkt",NOT(ISNUMBER(L23))),"",IF(F23="Mindestprognose",IF(L23>=I23,1,0),IF(AND(ISNUMBER(I23),ISNUMBER(J23),I23<>J23),IF(AND(L23>=I23,L23<=J23),1,0),""))) -> 0 | X23: =IF(OR(F23="qualitativ",F23="fehlend",NOT(ISNUMBER(L23))),"nicht auswertbar",IF(F23="Punkt","Punktprognose",IF(AND(ISNUMBER(I23),ISNUMBER(J23),I23<>J23),IF(L23<I23,"unterhalb",IF(L23>J23,"oberhalb","innerhalb")),"nicht auswertbar"))) -> unterhalb | Y23: =IF(AND(ISNUMBER(S23),OR(G23="Marge %",G23="Wachstumsrate %")),ABS(S23),"") | Z23: =IFERROR(VLOOKUP(A23,Unternehmen!$A:$D,4,FALSE()),"") -> Chemie
A24: BAS | B24: 2021 | C24: Umsatz | D24: 2020: https://www.basf.com/dam/jcr:14cf35ed-802f-3b49-8bef-363aa9646373/basf/www/global/documents/de/investor-relations/calendar-and-publications/reports/2021/BASF_Bericht_2020.pdf | E24: 155 | F24: Punkt mit Korridor | G24: absolut | H24: Mrd. EUR | I24: 61 | J24: 64 | K24: =L22 -> 59.149 | L24: 78.598 | M24: =L24-K24 -> 19.449 | N24: Positiv außerhalb Prognose (oberhalb) | O24: 2021: https://www.basf.com/dam/jcr:e0618338-8da4-31ba-b2b3-165dd93a6fcf/basf/www/global/documents/de/investor-relations/calendar-and-publications/reports/2022/BASF_Bericht_2021.pdf | P24: 149 | R24: =IF(NOT(ISNUMBER(I24)),"",IF(F24="Mindestprognose",I24,IF(ISNUMBER(J24),(I24+J24)/2,I24))) -> 62.5 | S24: =IF(OR(R24="",NOT(ISNUMBER(L24))),"",R24-L24) -> -16.098 | T24: =IF(OR(S24="",G24<>"absolut",NOT(ISNUMBER(L24)),L24=0),"",S24/ABS(L24)) -> -0.20481437 | U24: =IF(T24="","",ABS(T24)) -> 0.20481437 | V24: =IF(OR(F24="Punkt",NOT(ISNUMBER(L24))),"",IF(F24="Mindestprognose",IF(L24>=I24,1,0),IF(AND(ISNUMBER(I24),ISNUMBER(J24),I24<>J24),IF(AND(L24>=I24,L24<=J24),1,0),""))) -> 0 | X24: =IF(OR(F24="qualitativ",F24="fehlend",NOT(ISNUMBER(L24))),"nicht auswertbar",IF(F24="Punkt","Punktprognose",IF(AND(ISNUMBER(I24),ISNUMBER(J24),I24<>J24),IF(L24<I24,"unterhalb",IF(L24>J24,"oberhalb","innerhalb")),"nicht auswertbar"))) -> oberhalb | Y24: =IF(AND(ISNUMBER(S24),OR(G24="Marge %",G24="Wachstumsrate %")),ABS(S24),"") | Z24: =IFERROR(VLOOKUP(A24,Unternehmen!$A:$D,4,FALSE()),"") -> Chemie
A25: BAS | B25: 2021 | C25: Operative Ergebnisgroesse | D25: 2020: https://www.basf.com/dam/jcr:14cf35ed-802f-3b49-8bef-363aa9646373/basf/www/global/documents/de/investor-relations/calendar-and-publications/reports/2021/BASF_Bericht_2020.pdf | E25: 155 | F25: Punkt mit Korridor | G25: absolut | H25: Mrd. EUR | I25: 4.1 | J25: 5 | K25: =L23 -> 3.56 | L25: 7.768 | M25: =L25-K25 -> 4.208 | N25: Positiv außerhalb Prognose (oberhalb) | O25: 2021: https://www.basf.com/dam/jcr:e0618338-8da4-31ba-b2b3-165dd93a6fcf/basf/www/global/documents/de/investor-relations/calendar-and-publications/reports/2022/BASF_Bericht_2021.pdf | P25: 149 | R25: =IF(NOT(ISNUMBER(I25)),"",IF(F25="Mindestprognose",I25,IF(ISNUMBER(J25),(I25+J25)/2,I25))) -> 4.55 | S25: =IF(OR(R25="",NOT(ISNUMBER(L25))),"",R25-L25) -> -3.218 | T25: =IF(OR(S25="",G25<>"absolut",NOT(ISNUMBER(L25)),L25=0),"",S25/ABS(L25)) -> -0.41426365 | U25: =IF(T25="","",ABS(T25)) -> 0.41426365 | V25: =IF(OR(F25="Punkt",NOT(ISNUMBER(L25))),"",IF(F25="Mindestprognose",IF(L25>=I25,1,0),IF(AND(ISNUMBER(I25),ISNUMBER(J25),I25<>J25),IF(AND(L25>=I25,L25<=J25),1,0),""))) -> 0 | X25: =IF(OR(F25="qualitativ",F25="fehlend",NOT(ISNUMBER(L25))),"nicht auswertbar",IF(F25="Punkt","Punktprognose",IF(AND(ISNUMBER(I25),ISNUMBER(J25),I25<>J25),IF(L25<I25,"unterhalb",IF(L25>J25,"oberhalb","innerhalb")),"nicht auswertbar"))) -> oberhalb | Y25: =IF(AND(ISNUMBER(S25),OR(G25="Marge %",G25="Wachstumsrate %")),ABS(S25),"") | Z25: =IFERROR(VLOOKUP(A25,Unternehmen!$A:$D,4,FALSE()),"") -> Chemie
A26: BAS | B26: 2022 | C26: Umsatz | D26: 2021: https://www.basf.com/dam/jcr:e0618338-8da4-31ba-b2b3-165dd93a6fcf/basf/www/global/documents/de/investor-relations/calendar-and-publications/reports/2022/BASF_Bericht_2021.pdf | E26: 149 | F26: Punkt mit Korridor | G26: absolut | H26: Mrd. EUR | I26: 74 | J26: 77 | K26: =L24 -> 78.598 | L26: 87.327 | M26: =L26-K26 -> 8.729 | N26: Positiv außerhalb Prognose (oberhalb) | O26: 2022: https://www.basf.com/dam/jcr:29580e49-03df-3dff-a5fe-e16171be6e3f/basf/www/global/documents/de/investor-relations/calendar-and-publications/reports/2023/BASF_Bericht_2022.pdf | P26: 155 | R26: =IF(NOT(ISNUMBER(I26)),"",IF(F26="Mindestprognose",I26,IF(ISNUMBER(J26),(I26+J26)/2,I26))) -> 75.5 | S26: =IF(OR(R26="",NOT(ISNUMBER(L26))),"",R26-L26) -> -11.827 | T26: =IF(OR(S26="",G26<>"absolut",NOT(ISNUMBER(L26)),L26=0),"",S26/ABS(L26)) -> -0.13543349 | U26: =IF(T26="","",ABS(T26)) -> 0.13543349 | V26: =IF(OR(F26="Punkt",NOT(ISNUMBER(L26))),"",IF(F26="Mindestprognose",IF(L26>=I26,1,0),IF(AND(ISNUMBER(I26),ISNUMBER(J26),I26<>J26),IF(AND(L26>=I26,L26<=J26),1,0),""))) -> 0 | X26: =IF(OR(F26="qualitativ",F26="fehlend",NOT(ISNUMBER(L26))),"nicht auswertbar",IF(F26="Punkt","Punktprognose",IF(AND(ISNUMBER(I26),ISNUMBER(J26),I26<>J26),IF(L26<I26,"unterhalb",IF(L26>J26,"oberhalb","innerhalb")),"nicht auswertbar"))) -> oberhalb | Y26: =IF(AND(ISNUMBER(S26),OR(G26="Marge %",G26="Wachstumsrate %")),ABS(S26),"") | Z26: =IFERROR(VLOOKUP(A26,Unternehmen!$A:$D,4,FALSE()),"") -> Chemie
A27: BAS | B27: 2022 | C27: Operative Ergebnisgroesse | D27: 2021: https://www.basf.com/dam/jcr:e0618338-8da4-31ba-b2b3-165dd93a6fcf/basf/www/global/documents/de/investor-relations/calendar-and-publications/reports/2022/BASF_Bericht_2021.pdf | E27: 149 | F27: Punkt mit Korridor | G27: absolut | H27: Mrd. EUR | I27: 6.6 | J27: 7.2 | K27: =L25 -> 7.768 | L27: 6.878 | M27: =L27-K27 -> -0.89 | N27: im Rahmen | O27: 2022: https://www.basf.com/dam/jcr:29580e49-03df-3dff-a5fe-e16171be6e3f/basf/www/global/documents/de/investor-relations/calendar-and-publications/reports/2023/BASF_Bericht_2022.pdf | P27: 155 | R27: =IF(NOT(ISNUMBER(I27)),"",IF(F27="Mindestprognose",I27,IF(ISNUMBER(J27),(I27+J27)/2,I27))) -> 6.9 | S27: =IF(OR(R27="",NOT(ISNUMBER(L27))),"",R27-L27) -> 0.022 | T27: =IF(OR(S27="",G27<>"absolut",NOT(ISNUMBER(L27)),L27=0),"",S27/ABS(L27)) -> 0.0031986042 | U27: =IF(T27="","",ABS(T27)) -> 0.0031986042 | V27: =IF(OR(F27="Punkt",NOT(ISNUMBER(L27))),"",IF(F27="Mindestprognose",IF(L27>=I27,1,0),IF(AND(ISNUMBER(I27),ISNUMBER(J27),I27<>J27),IF(AND(L27>=I27,L27<=J27),1,0),""))) -> 1 | X27: =IF(OR(F27="qualitativ",F27="fehlend",NOT(ISNUMBER(L27))),"nicht auswertbar",IF(F27="Punkt","Punktprognose",IF(AND(ISNUMBER(I27),ISNUMBER(J27),I27<>J27),IF(L27<I27,"unterhalb",IF(L27>J27,"oberhalb","innerhalb")),"nicht auswertbar"))) -> innerhalb | Y27: =IF(AND(ISNUMBER(S27),OR(G27="Marge %",G27="Wachstumsrate %")),ABS(S27),"") | Z27: =IFERROR(VLOOKUP(A27,Unternehmen!$A:$D,4,FALSE()),"") -> Chemie
A28: BAS | B28: 2023 | C28: Umsatz | D28: 2022: https://www.basf.com/dam/jcr:29580e49-03df-3dff-a5fe-e16171be6e3f/basf/www/global/documents/de/investor-relations/calendar-and-publications/reports/2023/BASF_Bericht_2022.pdf | E28: 155 | F28: Punkt mit Korridor | G28: absolut | H28: Mrd. EUR | I28: 84 | J28: 87 | K28: =L26 -> 87.327 | L28: 68.902 | M28: =L28-K28 -> -18.425 | N28: -15,10 Mrd. EUR | O28: 2023: https://www.basf.com/dam/jcr:dad0be3d-5bac-3832-a127-7c8cefeb7f41/basf/www/global/documents/de/investor-relations/calendar-and-publications/reports/2024/BASF_Bericht_2023.pdf | P28: 250 | R28: =IF(NOT(ISNUMBER(I28)),"",IF(F28="Mindestprognose",I28,IF(ISNUMBER(J28),(I28+J28)/2,I28))) -> 85.5 | S28: =IF(OR(R28="",NOT(ISNUMBER(L28))),"",R28-L28) -> 16.598 | T28: =IF(OR(S28="",G28<>"absolut",NOT(ISNUMBER(L28)),L28=0),"",S28/ABS(L28)) -> 0.24089286 | U28: =IF(T28="","",ABS(T28)) -> 0.24089286 | V28: =IF(OR(F28="Punkt",NOT(ISNUMBER(L28))),"",IF(F28="Mindestprognose",IF(L28>=I28,1,0),IF(AND(ISNUMBER(I28),ISNUMBER(J28),I28<>J28),IF(AND(L28>=I28,L28<=J28),1,0),""))) -> 0 | X28: =IF(OR(F28="qualitativ",F28="fehlend",NOT(ISNUMBER(L28))),"nicht auswertbar",IF(F28="Punkt","Punktprognose",IF(AND(ISNUMBER(I28),ISNUMBER(J28),I28<>J28),IF(L28<I28,"unterhalb",IF(L28>J28,"oberhalb","innerhalb")),"nicht auswertbar"))) -> unterhalb | Y28: =IF(AND(ISNUMBER(S28),OR(G28="Marge %",G28="Wachstumsrate %")),ABS(S28),"") | Z28: =IFERROR(VLOOKUP(A28,Unternehmen!$A:$D,4,FALSE()),"") -> Chemie
A29: BAS | B29: 2023 | C29: Operative Ergebnisgroesse | D29: 2022: https://www.basf.com/dam/jcr:29580e49-03df-3dff-a5fe-e16171be6e3f/basf/www/global/documents/de/investor-relations/calendar-and-publications/reports/2023/BASF_Bericht_2022.pdf | E29: 155 | F29: Punkt mit Korridor | G29: absolut | H29: Mrd. EUR | I29: 4.8 | J29: 5.4 | K29: =L27 -> 6.878 | L29: 3.806 | M29: =L29-K29 -> -3.072 | N29: -0,99 Mrd. EUR | O29: 2023: https://www.basf.com/dam/jcr:dad0be3d-5bac-3832-a127-7c8cefeb7f41/basf/www/global/documents/de/investor-relations/calendar-and-publications/reports/2024/BASF_Bericht_2023.pdf | P29: 244 | R29: =IF(NOT(ISNUMBER(I29)),"",IF(F29="Mindestprognose",I29,IF(ISNUMBER(J29),(I29+J29)/2,I29))) -> 5.1 | S29: =IF(OR(R29="",NOT(ISNUMBER(L29))),"",R29-L29) -> 1.294 | T29: =IF(OR(S29="",G29<>"absolut",NOT(ISNUMBER(L29)),L29=0),"",S29/ABS(L29)) -> 0.33998949 | U29: =IF(T29="","",ABS(T29)) -> 0.33998949 | V29: =IF(OR(F29="Punkt",NOT(ISNUMBER(L29))),"",IF(F29="Mindestprognose",IF(L29>=I29,1,0),IF(AND(ISNUMBER(I29),ISNUMBER(J29),I29<>J29),IF(AND(L29>=I29,L29<=J29),1,0),""))) -> 0 | X29: =IF(OR(F29="qualitativ",F29="fehlend",NOT(ISNUMBER(L29))),"nicht auswertbar",IF(F29="Punkt","Punktprognose",IF(AND(ISNUMBER(I29),ISNUMBER(J29),I29<>J29),IF(L29<I29,"unterhalb",IF(L29>J29,"oberhalb","innerhalb")),"nicht auswertbar"))) -> unterhalb | Y29: =IF(AND(ISNUMBER(S29),OR(G29="Marge %",G29="Wachstumsrate %")),ABS(S29),"") | Z29: =IFERROR(VLOOKUP(A29,Unternehmen!$A:$D,4,FALSE()),"") -> Chemie
A30: BAS | B30: 2024 | C30: Umsatz | D30: 2023: https://www.basf.com/dam/jcr:dad0be3d-5bac-3832-a127-7c8cefeb7f41/basf/www/global/documents/de/investor-relations/calendar-and-publications/reports/2024/BASF_Bericht_2023.pdf | F30: fehlend | Q30: Im Jahr 2024 fehl Umsatzprognose | R30: =IF(NOT(ISNUMBER(I30)),"",IF(F30="Mindestprognose",I30,IF(ISNUMBER(J30),(I30+J30)/2,I30))) | S30: =IF(OR(R30="",NOT(ISNUMBER(L30))),"",R30-L30) | T30: =IF(OR(S30="",G30<>"absolut",NOT(ISNUMBER(L30)),L30=0),"",S30/ABS(L30)) | U30: =IF(T30="","",ABS(T30)) | V30: =IF(OR(F30="Punkt",NOT(ISNUMBER(L30))),"",IF(F30="Mindestprognose",IF(L30>=I30,1,0),IF(AND(ISNUMBER(I30),ISNUMBER(J30),I30<>J30),IF(AND(L30>=I30,L30<=J30),1,0),""))) | X30: =IF(OR(F30="qualitativ",F30="fehlend",NOT(ISNUMBER(L30))),"nicht auswertbar",IF(F30="Punkt","Punktprognose",IF(AND(ISNUMBER(I30),ISNUMBER(J30),I30<>J30),IF(L30<I30,"unterhalb",IF(L30>J30,"oberhalb","innerhalb")),"nicht auswertbar"))) -> nicht auswertbar | Y30: =IF(AND(ISNUMBER(S30),OR(G30="Marge %",G30="Wachstumsrate %")),ABS(S30),"") | Z30: =IFERROR(VLOOKUP(A30,Unternehmen!$A:$D,4,FALSE()),"") -> Chemie
A31: BAS | B31: 2024 | C31: Operative Ergebnisgroesse | D31: 2023: https://www.basf.com/dam/jcr:dad0be3d-5bac-3832-a127-7c8cefeb7f41/basf/www/global/documents/de/investor-relations/calendar-and-publications/reports/2024/BASF_Bericht_2023.pdf | E31: 170 | F31: Punkt mit Korridor | G31: absolut | H31: Mrd. EUR | I31: 8 | J31: 8.6 | L31: 7.858 | N31: -0,14 Mrd. EUR | O31: 2024: https://www.basf.com/dam/jcr:d3e39e4b-cfca-49fc-8df8-984053c2a322/basf/www/global/documents/de/investor-relations/calendar-and-publications/reports/2025/BASF_Bericht_2024.pdf?vid=lIIH3WpJGD7dq3XzAnQeXe.7T7O_Rv6h | P31: 82 | Q31: KPI2 bei BASF: EBIT vor Sondereinfluessen (Kennzeichnung '*' aus KPI-Spalte hierher verschoben) | R31: =IF(NOT(ISNUMBER(I31)),"",IF(F31="Mindestprognose",I31,IF(ISNUMBER(J31),(I31+J31)/2,I31))) -> 8.3 | S31: =IF(OR(R31="",NOT(ISNUMBER(L31))),"",R31-L31) -> 0.442 | T31: =IF(OR(S31="",G31<>"absolut",NOT(ISNUMBER(L31)),L31=0),"",S31/ABS(L31)) -> 0.056248409 | U31: =IF(T31="","",ABS(T31)) -> 0.056248409 | V31: =IF(OR(F31="Punkt",NOT(ISNUMBER(L31))),"",IF(F31="Mindestprognose",IF(L31>=I31,1,0),IF(AND(ISNUMBER(I31),ISNUMBER(J31),I31<>J31),IF(AND(L31>=I31,L31<=J31),1,0),""))) -> 0 | X31: =IF(OR(F31="qualitativ",F31="fehlend",NOT(ISNUMBER(L31))),"nicht auswertbar",IF(F31="Punkt","Punktprognose",IF(AND(ISNUMBER(I31),ISNUMBER(J31),I31<>J31),IF(L31<I31,"unterhalb",IF(L31>J31,"oberhalb","innerhalb")),"nicht auswertbar"))) -> unterhalb | Y31: =IF(AND(ISNUMBER(S31),OR(G31="Marge %",G31="Wachstumsrate %")),ABS(S31),"") | Z31: =IFERROR(VLOOKUP(A31,Unternehmen!$A:$D,4,FALSE()),"") -> Chemie
A32: BAYN | B32: 2020 | C32: Umsatz | D32: 2019: https://www.bayer.com/sites/default/files/2020-11/geschaeftsbericht-2019-der-bayer-ag.pdf | E32: 87 | F32: Punkt mit Korridor | G32: absolut | H32: Mrd. EUR | I32: 44 | J32: 45 | K32: 43.545 | L32: 41.4 | M32: =L32-K32 -> -2.145 | N32: -2,60 Mrd. EUR | O32: 2020: https://www.bayer.com/sites/default/files/2021-02/Bayer-Geschaeftsbericht-2020.pdf | P32: 2 | R32: =IF(NOT(ISNUMBER(I32)),"",IF(F32="Mindestprognose",I32,IF(ISNUMBER(J32),(I32+J32)/2,I32))) -> 44.5 | S32: =IF(OR(R32="",NOT(ISNUMBER(L32))),"",R32-L32) -> 3.1 | T32: =IF(OR(S32="",G32<>"absolut",NOT(ISNUMBER(L32)),L32=0),"",S32/ABS(L32)) -> 0.074879227 | U32: =IF(T32="","",ABS(T32)) -> 0.074879227 | V32: =IF(OR(F32="Punkt",NOT(ISNUMBER(L32))),"",IF(F32="Mindestprognose",IF(L32>=I32,1,0),IF(AND(ISNUMBER(I32),ISNUMBER(J32),I32<>J32),IF(AND(L32>=I32,L32<=J32),1,0),""))) -> 0 | X32: =IF(OR(F32="qualitativ",F32="fehlend",NOT(ISNUMBER(L32))),"nicht auswertbar",IF(F32="Punkt","Punktprognose",IF(AND(ISNUMBER(I32),ISNUMBER(J32),I32<>J32),IF(L32<I32,"unterhalb",IF(L32>J32,"oberhalb","innerhalb")),"nicht auswertbar"))) -> unterhalb | Y32: =IF(AND(ISNUMBER(S32),OR(G32="Marge %",G32="Wachstumsrate %")),ABS(S32),"") | Z32: =IFERROR(VLOOKUP(A32,Unternehmen!$A:$D,4,FALSE()),"") -> Pharma & Healthcare
A33: BAYN | B33: 2020 | C33: Operative Ergebnisgroesse | D33: 2019: https://www.bayer.com/sites/default/files/2020-11/geschaeftsbericht-2019-der-bayer-ag.pdf | E33: 87 | F33: Punkt mit Korridor | G33: absolut | H33: Mrd. EUR | I33: 12.3 | J33: 12.6 | K33: 11.474 | L33: 11.461 | M33: =L33-K33 -> -0.013 | N33: -0,84 Mrd. EUR | O33: 2020: https://www.bayer.com/sites/default/files/2021-02/Bayer-Geschaeftsbericht-2020.pdf | P33: 2 | R33: =IF(NOT(ISNUMBER(I33)),"",IF(F33="Mindestprognose",I33,IF(ISNUMBER(J33),(I33+J33)/2,I33))) -> 12.45 | S33: =IF(OR(R33="",NOT(ISNUMBER(L33))),"",R33-L33) -> 0.989 | T33: =IF(OR(S33="",G33<>"absolut",NOT(ISNUMBER(L33)),L33=0),"",S33/ABS(L33)) -> 0.086292645 | U33: =IF(T33="","",ABS(T33)) -> 0.086292645 | V33: =IF(OR(F33="Punkt",NOT(ISNUMBER(L33))),"",IF(F33="Mindestprognose",IF(L33>=I33,1,0),IF(AND(ISNUMBER(I33),ISNUMBER(J33),I33<>J33),IF(AND(L33>=I33,L33<=J33),1,0),""))) -> 0 | X33: =IF(OR(F33="qualitativ",F33="fehlend",NOT(ISNUMBER(L33))),"nicht auswertbar",IF(F33="Punkt","Punktprognose",IF(AND(ISNUMBER(I33),ISNUMBER(J33),I33<>J33),IF(L33<I33,"unterhalb",IF(L33>J33,"oberhalb","innerhalb")),"nicht auswertbar"))) -> unterhalb | Y33: =IF(AND(ISNUMBER(S33),OR(G33="Marge %",G33="Wachstumsrate %")),ABS(S33),"") | Z33: =IFERROR(VLOOKUP(A33,Unternehmen!$A:$D,4,FALSE()),"") -> Pharma & Healthcare
A34: BAYN | B34: 2021 | C34: Umsatz | D34: 2020: https://www.bayer.com/sites/default/files/2021-02/Bayer-Geschaeftsbericht-2020.pdf | E34: 101 | F34: Punkt mit Korridor | G34: absolut | H34: Mrd. EUR | I34: 42 | J34: 43 | K34: =L32 -> 41.4 | L34: 44.081 | M34: =L34-K34 -> 2.681 | N34: Positiv außerhalb Prognose (oberhalb) | O34: 2021: https://www.bayer.com/sites/default/files/2022-03/Bayer-Geschaeftsbericht-2021.pdf | P34: 2 | R34: =IF(NOT(ISNUMBER(I34)),"",IF(F34="Mindestprognose",I34,IF(ISNUMBER(J34),(I34+J34)/2,I34))) -> 42.5 | S34: =IF(OR(R34="",NOT(ISNUMBER(L34))),"",R34-L34) -> -1.581 | T34: =IF(OR(S34="",G34<>"absolut",NOT(ISNUMBER(L34)),L34=0),"",S34/ABS(L34)) -> -0.035865793 | U34: =IF(T34="","",ABS(T34)) -> 0.035865793 | V34: =IF(OR(F34="Punkt",NOT(ISNUMBER(L34))),"",IF(F34="Mindestprognose",IF(L34>=I34,1,0),IF(AND(ISNUMBER(I34),ISNUMBER(J34),I34<>J34),IF(AND(L34>=I34,L34<=J34),1,0),""))) -> 0 | X34: =IF(OR(F34="qualitativ",F34="fehlend",NOT(ISNUMBER(L34))),"nicht auswertbar",IF(F34="Punkt","Punktprognose",IF(AND(ISNUMBER(I34),ISNUMBER(J34),I34<>J34),IF(L34<I34,"unterhalb",IF(L34>J34,"oberhalb","innerhalb")),"nicht auswertbar"))) -> oberhalb | Y34: =IF(AND(ISNUMBER(S34),OR(G34="Marge %",G34="Wachstumsrate %")),ABS(S34),"") | Z34: =IFERROR(VLOOKUP(A34,Unternehmen!$A:$D,4,FALSE()),"") -> Pharma & Healthcare
A35: BAYN | B35: 2021 | C35: Operative Ergebnisgroesse | D35: 2020: https://www.bayer.com/sites/default/files/2021-02/Bayer-Geschaeftsbericht-2020.pdf | E35: 101 | F35: Punkt | G35: Marge % | H35: % (op. Marge) | I35: 0.27 | J35: 0.27 | K35: 0.277 | L35: 0.254 | M35: -2,30 PP | N35: -2,40 PP | O35: 2021: https://www.bayer.com/sites/default/files/2022-03/Bayer-Geschaeftsbericht-2021.pdf | P35: 2 | R35: =IF(NOT(ISNUMBER(I35)),"",IF(F35="Mindestprognose",I35,IF(ISNUMBER(J35),(I35+J35)/2,I35))) -> 0.27 | S35: =IF(OR(R35="",NOT(ISNUMBER(L35))),"",R35-L35) -> 0.016 | T35: =IF(OR(S35="",G35<>"absolut",NOT(ISNUMBER(L35)),L35=0),"",S35/ABS(L35)) | U35: =IF(T35="","",ABS(T35)) | V35: =IF(OR(F35="Punkt",NOT(ISNUMBER(L35))),"",IF(F35="Mindestprognose",IF(L35>=I35,1,0),IF(AND(ISNUMBER(I35),ISNUMBER(J35),I35<>J35),IF(AND(L35>=I35,L35<=J35),1,0),""))) | X35: =IF(OR(F35="qualitativ",F35="fehlend",NOT(ISNUMBER(L35))),"nicht auswertbar",IF(F35="Punkt","Punktprognose",IF(AND(ISNUMBER(I35),ISNUMBER(J35),I35<>J35),IF(L35<I35,"unterhalb",IF(L35>J35,"oberhalb","innerhalb")),"nicht auswertbar"))) -> Punktprognose | Y35: =IF(AND(ISNUMBER(S35),OR(G35="Marge %",G35="Wachstumsrate %")),ABS(S35),"") -> 0.016 | Z35: =IFERROR(VLOOKUP(A35,Unternehmen!$A:$D,4,FALSE()),"") -> Pharma & Healthcare
A36: BAYN | B36: 2022 | C36: Umsatz | D36: 2021: https://www.bayer.com/sites/default/files/2022-03/Bayer-Geschaeftsbericht-2021.pdf | E36: 99 | F36: Punkt | G36: absolut | H36: Mrd. EUR | I36: 46 | J36: 46 | K36: =L34 -> 44.081 | L36: 50.739 | M36: =L36-K36 -> 6.658 | N36: Positiv außerhalb Prognose (oberhalb) | O36: 2022: https://www.bayer.com/sites/default/files/2023-02/Bayer-Geschaeftsbericht-2022.pdf | P36: 2 | R36: =IF(NOT(ISNUMBER(I36)),"",IF(F36="Mindestprognose",I36,IF(ISNUMBER(J36),(I36+J36)/2,I36))) -> 46 | S36: =IF(OR(R36="",NOT(ISNUMBER(L36))),"",R36-L36) -> -4.739 | T36: =IF(OR(S36="",G36<>"absolut",NOT(ISNUMBER(L36)),L36=0),"",S36/ABS(L36)) -> -0.093399555 | U36: =IF(T36="","",ABS(T36)) -> 0.093399555 | V36: =IF(OR(F36="Punkt",NOT(ISNUMBER(L36))),"",IF(F36="Mindestprognose",IF(L36>=I36,1,0),IF(AND(ISNUMBER(I36),ISNUMBER(J36),I36<>J36),IF(AND(L36>=I36,L36<=J36),1,0),""))) | X36: =IF(OR(F36="qualitativ",F36="fehlend",NOT(ISNUMBER(L36))),"nicht auswertbar",IF(F36="Punkt","Punktprognose",IF(AND(ISNUMBER(I36),ISNUMBER(J36),I36<>J36),IF(L36<I36,"unterhalb",IF(L36>J36,"oberhalb","innerhalb")),"nicht auswertbar"))) -> Punktprognose | Y36: =IF(AND(ISNUMBER(S36),OR(G36="Marge %",G36="Wachstumsrate %")),ABS(S36),"") | Z36: =IFERROR(VLOOKUP(A36,Unternehmen!$A:$D,4,FALSE()),"") -> Pharma & Healthcare
A37: BAYN | B37: 2022 | C37: Operative Ergebnisgroesse | D37: 2021: https://www.bayer.com/sites/default/files/2022-03/Bayer-Geschaeftsbericht-2021.pdf | E37: 99 | F37: Punkt | G37: Marge % | H37: % (op. Marge) | I37: 0.26 | J37: 0.26 | K37: =L35 -> 0.254 | L37: 0.266 | M37: 1,20 PP | N37: Positiv außerhalb Prognose (oberhalb) | O37: 2022: https://www.bayer.com/sites/default/files/2023-02/Bayer-Geschaeftsbericht-2022.pdf | P37: 2 | R37: =IF(NOT(ISNUMBER(I37)),"",IF(F37="Mindestprognose",I37,IF(ISNUMBER(J37),(I37+J37)/2,I37))) -> 0.26 | S37: =IF(OR(R37="",NOT(ISNUMBER(L37))),"",R37-L37) -> -0.006 | T37: =IF(OR(S37="",G37<>"absolut",NOT(ISNUMBER(L37)),L37=0),"",S37/ABS(L37)) | U37: =IF(T37="","",ABS(T37)) | V37: =IF(OR(F37="Punkt",NOT(ISNUMBER(L37))),"",IF(F37="Mindestprognose",IF(L37>=I37,1,0),IF(AND(ISNUMBER(I37),ISNUMBER(J37),I37<>J37),IF(AND(L37>=I37,L37<=J37),1,0),""))) | X37: =IF(OR(F37="qualitativ",F37="fehlend",NOT(ISNUMBER(L37))),"nicht auswertbar",IF(F37="Punkt","Punktprognose",IF(AND(ISNUMBER(I37),ISNUMBER(J37),I37<>J37),IF(L37<I37,"unterhalb",IF(L37>J37,"oberhalb","innerhalb")),"nicht auswertbar"))) -> Punktprognose | Y37: =IF(AND(ISNUMBER(S37),OR(G37="Marge %",G37="Wachstumsrate %")),ABS(S37),"") -> 0.006 | Z37: =IFERROR(VLOOKUP(A37,Unternehmen!$A:$D,4,FALSE()),"") -> Pharma & Healthcare
A38: BAYN | B38: 2023 | C38: Umsatz | D38: 2022: https://www.bayer.com/sites/default/files/2023-02/Bayer-Geschaeftsbericht-2022.pdf | E38: 112 | F38: Punkt mit Korridor | G38: absolut | H38: Mrd. EUR | I38: 50 | J38: 51 | K38: =L36 -> 50.739 | L38: 47.637 | M38: =L38-K38 -> -3.102 | N38: -2,36 Mrd. EUR | O38: 2023: https://www.bayer.com/sites/default/files/2024-03/bayer-geschaeftsbericht-2023.pdf | P38: 2 | R38: =IF(NOT(ISNUMBER(I38)),"",IF(F38="Mindestprognose",I38,IF(ISNUMBER(J38),(I38+J38)/2,I38))) -> 50.5 | S38: =IF(OR(R38="",NOT(ISNUMBER(L38))),"",R38-L38) -> 2.863 | T38: =IF(OR(S38="",G38<>"absolut",NOT(ISNUMBER(L38)),L38=0),"",S38/ABS(L38)) -> 0.060100342 | U38: =IF(T38="","",ABS(T38)) -> 0.060100342 | V38: =IF(OR(F38="Punkt",NOT(ISNUMBER(L38))),"",IF(F38="Mindestprognose",IF(L38>=I38,1,0),IF(AND(ISNUMBER(I38),ISNUMBER(J38),I38<>J38),IF(AND(L38>=I38,L38<=J38),1,0),""))) -> 0 | X38: =IF(OR(F38="qualitativ",F38="fehlend",NOT(ISNUMBER(L38))),"nicht auswertbar",IF(F38="Punkt","Punktprognose",IF(AND(ISNUMBER(I38),ISNUMBER(J38),I38<>J38),IF(L38<I38,"unterhalb",IF(L38>J38,"oberhalb","innerhalb")),"nicht auswertbar"))) -> unterhalb | Y38: =IF(AND(ISNUMBER(S38),OR(G38="Marge %",G38="Wachstumsrate %")),ABS(S38),"") | Z38: =IFERROR(VLOOKUP(A38,Unternehmen!$A:$D,4,FALSE()),"") -> Pharma & Healthcare
A39: BAYN | B39: 2023 | C39: Operative Ergebnisgroesse | D39: 2022: https://www.bayer.com/sites/default/files/2023-02/Bayer-Geschaeftsbericht-2022.pdf | E39: 112 | F39: Punkt mit Korridor | G39: absolut | H39: Mrd. EUR | I39: 12.5 | J39: 13 | K39: 13.5 | L39: 11.706 | M39: =L39-K39 -> -1.794 | N39: -0,79 Mrd. EUR | O39: 2023: https://www.bayer.com/sites/default/files/2024-03/bayer-geschaeftsbericht-2023.pdf | P39: 2 | R39: =IF(NOT(ISNUMBER(I39)),"",IF(F39="Mindestprognose",I39,IF(ISNUMBER(J39),(I39+J39)/2,I39))) -> 12.75 | S39: =IF(OR(R39="",NOT(ISNUMBER(L39))),"",R39-L39) -> 1.044 | T39: =IF(OR(S39="",G39<>"absolut",NOT(ISNUMBER(L39)),L39=0),"",S39/ABS(L39)) -> 0.089185033 | U39: =IF(T39="","",ABS(T39)) -> 0.089185033 | V39: =IF(OR(F39="Punkt",NOT(ISNUMBER(L39))),"",IF(F39="Mindestprognose",IF(L39>=I39,1,0),IF(AND(ISNUMBER(I39),ISNUMBER(J39),I39<>J39),IF(AND(L39>=I39,L39<=J39),1,0),""))) -> 0 | X39: =IF(OR(F39="qualitativ",F39="fehlend",NOT(ISNUMBER(L39))),"nicht auswertbar",IF(F39="Punkt","Punktprognose",IF(AND(ISNUMBER(I39),ISNUMBER(J39),I39<>J39),IF(L39<I39,"unterhalb",IF(L39>J39,"oberhalb","innerhalb")),"nicht auswertbar"))) -> unterhalb | Y39: =IF(AND(ISNUMBER(S39),OR(G39="Marge %",G39="Wachstumsrate %")),ABS(S39),"") | Z39: =IFERROR(VLOOKUP(A39,Unternehmen!$A:$D,4,FALSE()),"") -> Pharma & Healthcare
A40: BAYN | B40: 2024 | C40: Umsatz | D40: 2023: https://www.bayer.com/sites/default/files/2024-03/bayer-geschaeftsbericht-2023.pdf | E40: 101 | F40: Punkt mit Korridor | G40: absolut | H40: Mrd. EUR | I40: 46 | J40: 48 | K40: =L38 -> 47.637 | L40: 46.606 | M40: =L40-K40 -> -1.031 | N40: im Rahmen | O40: 2024: https://www.bayer.com/sites/default/files/2025-03/bayer-geschaeftsbericht-2024.pdf | P40: 2 | R40: =IF(NOT(ISNUMBER(I40)),"",IF(F40="Mindestprognose",I40,IF(ISNUMBER(J40),(I40+J40)/2,I40))) -> 47 | S40: =IF(OR(R40="",NOT(ISNUMBER(L40))),"",R40-L40) -> 0.394 | T40: =IF(OR(S40="",G40<>"absolut",NOT(ISNUMBER(L40)),L40=0),"",S40/ABS(L40)) -> 0.0084538471 | U40: =IF(T40="","",ABS(T40)) -> 0.0084538471 | V40: =IF(OR(F40="Punkt",NOT(ISNUMBER(L40))),"",IF(F40="Mindestprognose",IF(L40>=I40,1,0),IF(AND(ISNUMBER(I40),ISNUMBER(J40),I40<>J40),IF(AND(L40>=I40,L40<=J40),1,0),""))) -> 1 | X40: =IF(OR(F40="qualitativ",F40="fehlend",NOT(ISNUMBER(L40))),"nicht auswertbar",IF(F40="Punkt","Punktprognose",IF(AND(ISNUMBER(I40),ISNUMBER(J40),I40<>J40),IF(L40<I40,"unterhalb",IF(L40>J40,"oberhalb","innerhalb")),"nicht auswertbar"))) -> innerhalb | Y40: =IF(AND(ISNUMBER(S40),OR(G40="Marge %",G40="Wachstumsrate %")),ABS(S40),"") | Z40: =IFERROR(VLOOKUP(A40,Unternehmen!$A:$D,4,FALSE()),"") -> Pharma & Healthcare
A41: BAYN | B41: 2024 | C41: Operative Ergebnisgroesse | D41: 2023: https://www.bayer.com/sites/default/files/2024-03/bayer-geschaeftsbericht-2023.pdf | E41: 101 | F41: Punkt mit Korridor | G41: absolut | H41: Mrd. EUR | I41: 10.4 | J41: 11 | K41: =L39 -> 11.706 | L41: 10.123 | M41: =L41-K41 -> -1.583 | N41: -0,28 Mrd. EUR | O41: 2024: https://www.bayer.com/sites/default/files/2025-03/bayer-geschaeftsbericht-2024.pdf | P41: 2 | R41: =IF(NOT(ISNUMBER(I41)),"",IF(F41="Mindestprognose",I41,IF(ISNUMBER(J41),(I41+J41)/2,I41))) -> 10.7 | S41: =IF(OR(R41="",NOT(ISNUMBER(L41))),"",R41-L41) -> 0.577 | T41: =IF(OR(S41="",G41<>"absolut",NOT(ISNUMBER(L41)),L41=0),"",S41/ABS(L41)) -> 0.056998913 | U41: =IF(T41="","",ABS(T41)) -> 0.056998913 | V41: =IF(OR(F41="Punkt",NOT(ISNUMBER(L41))),"",IF(F41="Mindestprognose",IF(L41>=I41,1,0),IF(AND(ISNUMBER(I41),ISNUMBER(J41),I41<>J41),IF(AND(L41>=I41,L41<=J41),1,0),""))) -> 0 | X41: =IF(OR(F41="qualitativ",F41="fehlend",NOT(ISNUMBER(L41))),"nicht auswertbar",IF(F41="Punkt","Punktprognose",IF(AND(ISNUMBER(I41),ISNUMBER(J41),I41<>J41),IF(L41<I41,"unterhalb",IF(L41>J41,"oberhalb","innerhalb")),"nicht auswertbar"))) -> unterhalb | Y41: =IF(AND(ISNUMBER(S41),OR(G41="Marge %",G41="Wachstumsrate %")),ABS(S41),"") | Z41: =IFERROR(VLOOKUP(A41,Unternehmen!$A:$D,4,FALSE()),"") -> Pharma & Healthcare
A42: BEI | B42: 2020 | C42: Umsatz | D42: 2019 | E42: 60 | F42: Bandbreite | G42: Wachstumsrate % | H42: % (wb. Wachstumsrate) | I42: 0.03 | J42: 0.05 | K42: 0.041 | L42: -0.057 | M42: -9,80 PP | N42: -8,70 PP | O42: 2020 | P42: I | R42: =IF(NOT(ISNUMBER(I42)),"",IF(F42="Mindestprognose",I42,IF(ISNUMBER(J42),(I42+J42)/2,I42))) -> 0.04 | S42: =IF(OR(R42="",NOT(ISNUMBER(L42))),"",R42-L42) -> 0.097 | T42: =IF(OR(S42="",G42<>"absolut",NOT(ISNUMBER(L42)),L42=0),"",S42/ABS(L42)) | U42: =IF(T42="","",ABS(T42)) | V42: =IF(OR(F42="Punkt",NOT(ISNUMBER(L42))),"",IF(F42="Mindestprognose",IF(L42>=I42,1,0),IF(AND(ISNUMBER(I42),ISNUMBER(J42),I42<>J42),IF(AND(L42>=I42,L42<=J42),1,0),""))) -> 0 | X42: =IF(OR(F42="qualitativ",F42="fehlend",NOT(ISNUMBER(L42))),"nicht auswertbar",IF(F42="Punkt","Punktprognose",IF(AND(ISNUMBER(I42),ISNUMBER(J42),I42<>J42),IF(L42<I42,"unterhalb",IF(L42>J42,"oberhalb","innerhalb")),"nicht auswertbar"))) -> unterhalb | Y42: =IF(AND(ISNUMBER(S42),OR(G42="Marge %",G42="Wachstumsrate %")),ABS(S42),"") -> 0.097 | Z42: =IFERROR(VLOOKUP(A42,Unternehmen!$A:$D,4,FALSE()),"") -> Konsumgueter
A43: BEI | B43: 2020 | C43: Operative Ergebnisgroesse | D43: 2019 | E43: 60 | F43: Bandbreite | G43: Marge % | H43: % (op. Marge) | I43: 0.14 | J43: 0.145 | K43: 0.135 | L43: 0.118 | M43: -1,70 PP | N43: -2,20 PP | O43: 2020 | P43: I | R43: =IF(NOT(ISNUMBER(I43)),"",IF(F43="Mindestprognose",I43,IF(ISNUMBER(J43),(I43+J43)/2,I43))) -> 0.1425 | S43: =IF(OR(R43="",NOT(ISNUMBER(L43))),"",R43-L43) -> 0.0245 | T43: =IF(OR(S43="",G43<>"absolut",NOT(ISNUMBER(L43)),L43=0),"",S43/ABS(L43)) | U43: =IF(T43="","",ABS(T43)) | V43: =IF(OR(F43="Punkt",NOT(ISNUMBER(L43))),"",IF(F43="Mindestprognose",IF(L43>=I43,1,0),IF(AND(ISNUMBER(I43),ISNUMBER(J43),I43<>J43),IF(AND(L43>=I43,L43<=J43),1,0),""))) -> 0 | X43: =IF(OR(F43="qualitativ",F43="fehlend",NOT(ISNUMBER(L43))),"nicht auswertbar",IF(F43="Punkt","Punktprognose",IF(AND(ISNUMBER(I43),ISNUMBER(J43),I43<>J43),IF(L43<I43,"unterhalb",IF(L43>J43,"oberhalb","innerhalb")),"nicht auswertbar"))) -> unterhalb | Y43: =IF(AND(ISNUMBER(S43),OR(G43="Marge %",G43="Wachstumsrate %")),ABS(S43),"") -> 0.0245 | Z43: =IFERROR(VLOOKUP(A43,Unternehmen!$A:$D,4,FALSE()),"") -> Konsumgueter
A44: BEI | B44: 2021 | C44: Umsatz | D44: 2020 | E44: 83 | F44: qualitativ | G44: Wachstumsrate % | H44: % (wb. Wachstumsrate) | K44: =L42 -> -0.057 | L44: 0.097 | M44: 15,40 PP | N44: im Rahmen | O44: 2021 | P44: I | Q44: Da durch die Pandemie die Prognosefähigkeit beeinträchtigt war, wurden keine konkrete Werte geschätzt. | R44: =IF(NOT(ISNUMBER(I44)),"",IF(F44="Mindestprognose",I44,IF(ISNUMBER(J44),(I44+J44)/2,I44))) | S44: =IF(OR(R44="",NOT(ISNUMBER(L44))),"",R44-L44) | T44: =IF(OR(S44="",G44<>"absolut",NOT(ISNUMBER(L44)),L44=0),"",S44/ABS(L44)) | U44: =IF(T44="","",ABS(T44)) | V44: =IF(OR(F44="Punkt",NOT(ISNUMBER(L44))),"",IF(F44="Mindestprognose",IF(L44>=I44,1,0),IF(AND(ISNUMBER(I44),ISNUMBER(J44),I44<>J44),IF(AND(L44>=I44,L44<=J44),1,0),""))) | W44: Von positivem Umsatzwachstum ausgegangen | X44: =IF(OR(F44="qualitativ",F44="fehlend",NOT(ISNUMBER(L44))),"nicht auswertbar",IF(F44="Punkt","Punktprognose",IF(AND(ISNUMBER(I44),ISNUMBER(J44),I44<>J44),IF(L44<I44,"unterhalb",IF(L44>J44,"oberhalb","innerhalb")),"nicht auswertbar"))) -> nicht auswertbar | Y44: =IF(AND(ISNUMBER(S44),OR(G44="Marge %",G44="Wachstumsrate %")),ABS(S44),"") | Z44: =IFERROR(VLOOKUP(A44,Unternehmen!$A:$D,4,FALSE()),"") -> Konsumgueter
A45: BEI | B45: 2021 | C45: Operative Ergebnisgroesse | D45: 2020 | E45: 83 | F45: qualitativ | G45: Marge % | H45: % (op. Marge) | K45: =L43 -> 0.118 | L45: 0.122 | M45: 0,40 PP | N45: Positiv außerhalb Prognose (oberhalb) | O45: 2021 | P45: I | R45: =IF(NOT(ISNUMBER(I45)),"",IF(F45="Mindestprognose",I45,IF(ISNUMBER(J45),(I45+J45)/2,I45))) | S45: =IF(OR(R45="",NOT(ISNUMBER(L45))),"",R45-L45) | T45: =IF(OR(S45="",G45<>"absolut",NOT(ISNUMBER(L45)),L45=0),"",S45/ABS(L45)) | U45: =IF(T45="","",ABS(T45)) | V45: =IF(OR(F45="Punkt",NOT(ISNUMBER(L45))),"",IF(F45="Mindestprognose",IF(L45>=I45,1,0),IF(AND(ISNUMBER(I45),ISNUMBER(J45),I45<>J45),IF(AND(L45>=I45,L45<=J45),1,0),""))) | W45: Wird unter Vorjahresniveau erwartet | X45: =IF(OR(F45="qualitativ",F45="fehlend",NOT(ISNUMBER(L45))),"nicht auswertbar",IF(F45="Punkt","Punktprognose",IF(AND(ISNUMBER(I45),ISNUMBER(J45),I45<>J45),IF(L45<I45,"unterhalb",IF(L45>J45,"oberhalb","innerhalb")),"nicht auswertbar"))) -> nicht auswertbar | Y45: =IF(AND(ISNUMBER(S45),OR(G45="Marge %",G45="Wachstumsrate %")),ABS(S45),"") | Z45: =IFERROR(VLOOKUP(A45,Unternehmen!$A:$D,4,FALSE()),"") -> Konsumgueter
A46: BEI | B46: 2022 | C46: Umsatz | D46: 2021 | E46: 106 | F46: verbal-quantifiziert | G46: Wachstumsrate % | H46: % (wb. Wachstumsrate) | I46: 0.04 | J46: 0.06 | K46: =L44 -> 0.097 | L46: 0.102 | M46: 0,50 PP | N46: Positiv außerhalb Prognose (oberhalb) | O46: 2022: https://reports.beiersdorf.com/geschaeftsbericht/2022/_assets/downloads/entire-beiersdorf-gb22.pdf?h=BWs5hys8 | P46: 2 | R46: =IF(NOT(ISNUMBER(I46)),"",IF(F46="Mindestprognose",I46,IF(ISNUMBER(J46),(I46+J46)/2,I46))) -> 0.05 | S46: =IF(OR(R46="",NOT(ISNUMBER(L46))),"",R46-L46) -> -0.052 | T46: =IF(OR(S46="",G46<>"absolut",NOT(ISNUMBER(L46)),L46=0),"",S46/ABS(L46)) | U46: =IF(T46="","",ABS(T46)) | V46: =IF(OR(F46="Punkt",NOT(ISNUMBER(L46))),"",IF(F46="Mindestprognose",IF(L46>=I46,1,0),IF(AND(ISNUMBER(I46),ISNUMBER(J46),I46<>J46),IF(AND(L46>=I46,L46<=J46),1,0),""))) -> 0 | X46: =IF(OR(F46="qualitativ",F46="fehlend",NOT(ISNUMBER(L46))),"nicht auswertbar",IF(F46="Punkt","Punktprognose",IF(AND(ISNUMBER(I46),ISNUMBER(J46),I46<>J46),IF(L46<I46,"unterhalb",IF(L46>J46,"oberhalb","innerhalb")),"nicht auswertbar"))) -> oberhalb | Y46: =IF(AND(ISNUMBER(S46),OR(G46="Marge %",G46="Wachstumsrate %")),ABS(S46),"") -> 0.052 | Z46: =IFERROR(VLOOKUP(A46,Unternehmen!$A:$D,4,FALSE()),"") -> Konsumgueter
A47: BEI | B47: 2022 | C47: Operative Ergebnisgroesse | D47: 2021 | E47: 106 | F47: qualitativ | G47: Marge % | H47: % (op. Marge) | K47: =L45 -> 0.122 | L47: 0.124 | M47: 0,20 PP | N47: im Rahmen | O47: 2022: https://reports.beiersdorf.com/geschaeftsbericht/2022/_assets/downloads/entire-beiersdorf-gb22.pdf?h=BWs5hys8 | P47: 2 | R47: =IF(NOT(ISNUMBER(I47)),"",IF(F47="Mindestprognose",I47,IF(ISNUMBER(J47),(I47+J47)/2,I47))) | S47: =IF(OR(R47="",NOT(ISNUMBER(L47))),"",R47-L47) | T47: =IF(OR(S47="",G47<>"absolut",NOT(ISNUMBER(L47)),L47=0),"",S47/ABS(L47)) | U47: =IF(T47="","",ABS(T47)) | V47: =IF(OR(F47="Punkt",NOT(ISNUMBER(L47))),"",IF(F47="Mindestprognose",IF(L47>=I47,1,0),IF(AND(ISNUMBER(I47),ISNUMBER(J47),I47<>J47),IF(AND(L47>=I47,L47<=J47),1,0),""))) | W47: Leicht über Vorjahr geschätzt | X47: =IF(OR(F47="qualitativ",F47="fehlend",NOT(ISNUMBER(L47))),"nicht auswertbar",IF(F47="Punkt","Punktprognose",IF(AND(ISNUMBER(I47),ISNUMBER(J47),I47<>J47),IF(L47<I47,"unterhalb",IF(L47>J47,"oberhalb","innerhalb")),"nicht auswertbar"))) -> nicht auswertbar | Y47: =IF(AND(ISNUMBER(S47),OR(G47="Marge %",G47="Wachstumsrate %")),ABS(S47),"") | Z47: =IFERROR(VLOOKUP(A47,Unternehmen!$A:$D,4,FALSE()),"") -> Konsumgueter
A48: BEI | B48: 2023 | C48: Umsatz | D48: 2022: https://reports.beiersdorf.com/geschaeftsbericht/2022/_assets/downloads/entire-beiersdorf-gb22.pdf?h=BWs5hys8 | E48: 174 | F48: qualitativ | G48: Wachstumsrate % | H48: % (wb. Wachstumsrate) | K48: =L46 -> 0.102 | L48: 0.108 | M48: 0,60 PP | N48: im Rahmen | O48: 2023: https://reports.beiersdorf.com/geschaeftsbericht/2023/_assets/downloads/entire-beiersdorf-gb23.pdf?h=YzK4wNp_ | P48: 2 | R48: =IF(NOT(ISNUMBER(I48)),"",IF(F48="Mindestprognose",I48,IF(ISNUMBER(J48),(I48+J48)/2,I48))) | S48: =IF(OR(R48="",NOT(ISNUMBER(L48))),"",R48-L48) | T48: =IF(OR(S48="",G48<>"absolut",NOT(ISNUMBER(L48)),L48=0),"",S48/ABS(L48)) | U48: =IF(T48="","",ABS(T48)) | V48: =IF(OR(F48="Punkt",NOT(ISNUMBER(L48))),"",IF(F48="Mindestprognose",IF(L48>=I48,1,0),IF(AND(ISNUMBER(I48),ISNUMBER(J48),I48<>J48),IF(AND(L48>=I48,L48<=J48),1,0),""))) | W48: Leicht über Vorjahr geschätzt | X48: =IF(OR(F48="qualitativ",F48="fehlend",NOT(ISNUMBER(L48))),"nicht auswertbar",IF(F48="Punkt","Punktprognose",IF(AND(ISNUMBER(I48),ISNUMBER(J48),I48<>J48),IF(L48<I48,"unterhalb",IF(L48>J48,"oberhalb","innerhalb")),"nicht auswertbar"))) -> nicht auswertbar | Y48: =IF(AND(ISNUMBER(S48),OR(G48="Marge %",G48="Wachstumsrate %")),ABS(S48),"") | Z48: =IFERROR(VLOOKUP(A48,Unternehmen!$A:$D,4,FALSE()),"") -> Konsumgueter
A49: BEI | B49: 2023 | C49: Operative Ergebnisgroesse | D49: 2022: https://reports.beiersdorf.com/geschaeftsbericht/2022/_assets/downloads/entire-beiersdorf-gb22.pdf?h=BWs5hys8 | E49: 174 | F49: Punkt | G49: Marge % | H49: % (op. Marge) | I49: 0.129 | J49: 0.129 | K49: =L47 -> 0.124 | L49: 0.117 | M49: -0,70 PP | N49: -1,2 PP | O49: 2023: https://reports.beiersdorf.com/geschaeftsbericht/2023/_assets/downloads/entire-beiersdorf-gb23.pdf?h=YzK4wNp_ | P49: 2 | R49: =IF(NOT(ISNUMBER(I49)),"",IF(F49="Mindestprognose",I49,IF(ISNUMBER(J49),(I49+J49)/2,I49))) -> 0.129 | S49: =IF(OR(R49="",NOT(ISNUMBER(L49))),"",R49-L49) -> 0.012 | T49: =IF(OR(S49="",G49<>"absolut",NOT(ISNUMBER(L49)),L49=0),"",S49/ABS(L49)) | U49: =IF(T49="","",ABS(T49)) | V49: =IF(OR(F49="Punkt",NOT(ISNUMBER(L49))),"",IF(F49="Mindestprognose",IF(L49>=I49,1,0),IF(AND(ISNUMBER(I49),ISNUMBER(J49),I49<>J49),IF(AND(L49>=I49,L49<=J49),1,0),""))) | X49: =IF(OR(F49="qualitativ",F49="fehlend",NOT(ISNUMBER(L49))),"nicht auswertbar",IF(F49="Punkt","Punktprognose",IF(AND(ISNUMBER(I49),ISNUMBER(J49),I49<>J49),IF(L49<I49,"unterhalb",IF(L49>J49,"oberhalb","innerhalb")),"nicht auswertbar"))) -> Punktprognose | Y49: =IF(AND(ISNUMBER(S49),OR(G49="Marge %",G49="Wachstumsrate %")),ABS(S49),"") -> 0.012 | Z49: =IFERROR(VLOOKUP(A49,Unternehmen!$A:$D,4,FALSE()),"") -> Konsumgueter
A50: BEI | B50: 2024 | C50: Umsatz | D50: 2023: https://reports.beiersdorf.com/geschaeftsbericht/2023/_assets/downloads/entire-beiersdorf-gb23.pdf?h=YzK4wNp_ | E50: 179 | F50: verbal-quantifiziert | G50: Wachstumsrate % | H50: % (wb. Wachstumsrate) | I50: 0.04 | J50: 0.06 | K50: =L48 -> 0.108 | L50: 0.065 | M50: -4,30 PP | N50: im Rahmen | O50: 2024: https://reports.beiersdorf.com/geschaeftsbericht/2024/_assets/downloads/entire-beiersdorf-gb24.pdf?h=R7Y3_PC- | P50: 2 | R50: =IF(NOT(ISNUMBER(I50)),"",IF(F50="Mindestprognose",I50,IF(ISNUMBER(J50),(I50+J50)/2,I50))) -> 0.05 | S50: =IF(OR(R50="",NOT(ISNUMBER(L50))),"",R50-L50) -> -0.015 | T50: =IF(OR(S50="",G50<>"absolut",NOT(ISNUMBER(L50)),L50=0),"",S50/ABS(L50)) | U50: =IF(T50="","",ABS(T50)) | V50: =IF(OR(F50="Punkt",NOT(ISNUMBER(L50))),"",IF(F50="Mindestprognose",IF(L50>=I50,1,0),IF(AND(ISNUMBER(I50),ISNUMBER(J50),I50<>J50),IF(AND(L50>=I50,L50<=J50),1,0),""))) -> 0 | X50: =IF(OR(F50="qualitativ",F50="fehlend",NOT(ISNUMBER(L50))),"nicht auswertbar",IF(F50="Punkt","Punktprognose",IF(AND(ISNUMBER(I50),ISNUMBER(J50),I50<>J50),IF(L50<I50,"unterhalb",IF(L50>J50,"oberhalb","innerhalb")),"nicht auswertbar"))) -> oberhalb | Y50: =IF(AND(ISNUMBER(S50),OR(G50="Marge %",G50="Wachstumsrate %")),ABS(S50),"") -> 0.015 | Z50: =IFERROR(VLOOKUP(A50,Unternehmen!$A:$D,4,FALSE()),"") -> Konsumgueter
A51: BEI | B51: 2024 | C51: Operative Ergebnisgroesse | D51: 2023: https://reports.beiersdorf.com/geschaeftsbericht/2023/_assets/downloads/entire-beiersdorf-gb23.pdf?h=YzK4wNp_ | E51: 179 | F51: Punkt | G51: Marge % | H51: % (op. Marge) | I51: 0.122 | J51: 0.122 | K51: =L49 -> 0.117 | L51: 0.131 | M51: 1,40 PP | N51: Positiv außerhalb Prognose (oberhalb) | O51: 2024: https://reports.beiersdorf.com/geschaeftsbericht/2024/_assets/downloads/entire-beiersdorf-gb24.pdf?h=R7Y3_PC- | P51: 2 | R51: =IF(NOT(ISNUMBER(I51)),"",IF(F51="Mindestprognose",I51,IF(ISNUMBER(J51),(I51+J51)/2,I51))) -> 0.122 | S51: =IF(OR(R51="",NOT(ISNUMBER(L51))),"",R51-L51) -> -0.009 | T51: =IF(OR(S51="",G51<>"absolut",NOT(ISNUMBER(L51)),L51=0),"",S51/ABS(L51)) | U51: =IF(T51="","",ABS(T51)) | V51: =IF(OR(F51="Punkt",NOT(ISNUMBER(L51))),"",IF(F51="Mindestprognose",IF(L51>=I51,1,0),IF(AND(ISNUMBER(I51),ISNUMBER(J51),I51<>J51),IF(AND(L51>=I51,L51<=J51),1,0),""))) | X51: =IF(OR(F51="qualitativ",F51="fehlend",NOT(ISNUMBER(L51))),"nicht auswertbar",IF(F51="Punkt","Punktprognose",IF(AND(ISNUMBER(I51),ISNUMBER(J51),I51<>J51),IF(L51<I51,"unterhalb",IF(L51>J51,"oberhalb","innerhalb")),"nicht auswertbar"))) -> Punktprognose | Y51: =IF(AND(ISNUMBER(S51),OR(G51="Marge %",G51="Wachstumsrate %")),ABS(S51),"") -> 0.009 | Z51: =IFERROR(VLOOKUP(A51,Unternehmen!$A:$D,4,FALSE()),"") -> Konsumgueter
A52: BMW | B52: 2020 | C52: Umsatz | F52: fehlend | R52: =IF(NOT(ISNUMBER(I52)),"",IF(F52="Mindestprognose",I52,IF(ISNUMBER(J52),(I52+J52)/2,I52))) | S52: =IF(OR(R52="",NOT(ISNUMBER(L52))),"",R52-L52) | T52: =IF(OR(S52="",G52<>"absolut",NOT(ISNUMBER(L52)),L52=0),"",S52/ABS(L52)) | U52: =IF(T52="","",ABS(T52)) | V52: =IF(OR(F52="Punkt",NOT(ISNUMBER(L52))),"",IF(F52="Mindestprognose",IF(L52>=I52,1,0),IF(AND(ISNUMBER(I52),ISNUMBER(J52),I52<>J52),IF(AND(L52>=I52,L52<=J52),1,0),""))) | X52: =IF(OR(F52="qualitativ",F52="fehlend",NOT(ISNUMBER(L52))),"nicht auswertbar",IF(F52="Punkt","Punktprognose",IF(AND(ISNUMBER(I52),ISNUMBER(J52),I52<>J52),IF(L52<I52,"unterhalb",IF(L52>J52,"oberhalb","innerhalb")),"nicht auswertbar"))) -> nicht auswertbar | Y52: =IF(AND(ISNUMBER(S52),OR(G52="Marge %",G52="Wachstumsrate %")),ABS(S52),"") | Z52: =IFERROR(VLOOKUP(A52,Unternehmen!$A:$D,4,FALSE()),"") -> Automobile
A53: BMW | B53: 2020 | C53: Operative Ergebnisgroesse | D53: 2019: https://www.bmwgroup.com/content/dam/grpw/websites/bmwgroup_com/ir/downloads/de/2020/gb/BMW-GB19_de_Finanzbericht.pdf | E53: 85 | F53: Bandbreite | G53: Marge % | H53: % (op. Marge) | I53: 0.02 | J53: 0.04 | K53: 0.049 | L53: 0.027 | M53: -2,20 PP | N53: im Rahmen | O53: 2020: https://www.bmwgroup.com/content/dam/grpw/websites/bmwgroup_com/ir/downloads/de/2021/bericht/BMW-Group-Bericht-2020-DE.pdf | P53: 163 | R53: =IF(NOT(ISNUMBER(I53)),"",IF(F53="Mindestprognose",I53,IF(ISNUMBER(J53),(I53+J53)/2,I53))) -> 0.03 | S53: =IF(OR(R53="",NOT(ISNUMBER(L53))),"",R53-L53) -> 0.003 | T53: =IF(OR(S53="",G53<>"absolut",NOT(ISNUMBER(L53)),L53=0),"",S53/ABS(L53)) | U53: =IF(T53="","",ABS(T53)) | V53: =IF(OR(F53="Punkt",NOT(ISNUMBER(L53))),"",IF(F53="Mindestprognose",IF(L53>=I53,1,0),IF(AND(ISNUMBER(I53),ISNUMBER(J53),I53<>J53),IF(AND(L53>=I53,L53<=J53),1,0),""))) -> 1 | X53: =IF(OR(F53="qualitativ",F53="fehlend",NOT(ISNUMBER(L53))),"nicht auswertbar",IF(F53="Punkt","Punktprognose",IF(AND(ISNUMBER(I53),ISNUMBER(J53),I53<>J53),IF(L53<I53,"unterhalb",IF(L53>J53,"oberhalb","innerhalb")),"nicht auswertbar"))) -> innerhalb | Y53: =IF(AND(ISNUMBER(S53),OR(G53="Marge %",G53="Wachstumsrate %")),ABS(S53),"") -> 0.003 | Z53: =IFERROR(VLOOKUP(A53,Unternehmen!$A:$D,4,FALSE()),"") -> Automobile
A54: BMW | B54: 2021 | C54: Umsatz | F54: fehlend | R54: =IF(NOT(ISNUMBER(I54)),"",IF(F54="Mindestprognose",I54,IF(ISNUMBER(J54),(I54+J54)/2,I54))) | S54: =IF(OR(R54="",NOT(ISNUMBER(L54))),"",R54-L54) | T54: =IF(OR(S54="",G54<>"absolut",NOT(ISNUMBER(L54)),L54=0),"",S54/ABS(L54)) | U54: =IF(T54="","",ABS(T54)) | V54: =IF(OR(F54="Punkt",NOT(ISNUMBER(L54))),"",IF(F54="Mindestprognose",IF(L54>=I54,1,0),IF(AND(ISNUMBER(I54),ISNUMBER(J54),I54<>J54),IF(AND(L54>=I54,L54<=J54),1,0),""))) | X54: =IF(OR(F54="qualitativ",F54="fehlend",NOT(ISNUMBER(L54))),"nicht auswertbar",IF(F54="Punkt","Punktprognose",IF(AND(ISNUMBER(I54),ISNUMBER(J54),I54<>J54),IF(L54<I54,"unterhalb",IF(L54>J54,"oberhalb","innerhalb")),"nicht auswertbar"))) -> nicht auswertbar | Y54: =IF(AND(ISNUMBER(S54),OR(G54="Marge %",G54="Wachstumsrate %")),ABS(S54),"") | Z54: =IFERROR(VLOOKUP(A54,Unternehmen!$A:$D,4,FALSE()),"") -> Automobile
A55: BMW | B55: 2021 | C55: Operative Ergebnisgroesse | D55: 2020: https://www.bmwgroup.com/content/dam/grpw/websites/bmwgroup_com/ir/downloads/de/2021/bericht/BMW-Group-Bericht-2020-DE.pdf | E55: 163 | F55: Bandbreite | G55: Marge % | H55: % (op. Marge) | I55: 0.06 | J55: 0.08 | K55: =L53 -> 0.027 | L55: 0.103 | M55: 7,60 PP | N55: Positiv außerhalb Prognose (oberhalb) | O55: 2021: https://www.bmwgroup.com/content/dam/grpw/websites/bmwgroup_com/ir/downloads/de/2022/bericht/BMW-Group-Bericht-2021-de.pdf | P55: 128 | R55: =IF(NOT(ISNUMBER(I55)),"",IF(F55="Mindestprognose",I55,IF(ISNUMBER(J55),(I55+J55)/2,I55))) -> 0.07 | S55: =IF(OR(R55="",NOT(ISNUMBER(L55))),"",R55-L55) -> -0.033 | T55: =IF(OR(S55="",G55<>"absolut",NOT(ISNUMBER(L55)),L55=0),"",S55/ABS(L55)) | U55: =IF(T55="","",ABS(T55)) | V55: =IF(OR(F55="Punkt",NOT(ISNUMBER(L55))),"",IF(F55="Mindestprognose",IF(L55>=I55,1,0),IF(AND(ISNUMBER(I55),ISNUMBER(J55),I55<>J55),IF(AND(L55>=I55,L55<=J55),1,0),""))) -> 0 | X55: =IF(OR(F55="qualitativ",F55="fehlend",NOT(ISNUMBER(L55))),"nicht auswertbar",IF(F55="Punkt","Punktprognose",IF(AND(ISNUMBER(I55),ISNUMBER(J55),I55<>J55),IF(L55<I55,"unterhalb",IF(L55>J55,"oberhalb","innerhalb")),"nicht auswertbar"))) -> oberhalb | Y55: =IF(AND(ISNUMBER(S55),OR(G55="Marge %",G55="Wachstumsrate %")),ABS(S55),"") -> 0.033 | Z55: =IFERROR(VLOOKUP(A55,Unternehmen!$A:$D,4,FALSE()),"") -> Automobile
A56: BMW | B56: 2022 | C56: Umsatz | F56: fehlend | R56: =IF(NOT(ISNUMBER(I56)),"",IF(F56="Mindestprognose",I56,IF(ISNUMBER(J56),(I56+J56)/2,I56))) | S56: =IF(OR(R56="",NOT(ISNUMBER(L56))),"",R56-L56) | T56: =IF(OR(S56="",G56<>"absolut",NOT(ISNUMBER(L56)),L56=0),"",S56/ABS(L56)) | U56: =IF(T56="","",ABS(T56)) | V56: =IF(OR(F56="Punkt",NOT(ISNUMBER(L56))),"",IF(F56="Mindestprognose",IF(L56>=I56,1,0),IF(AND(ISNUMBER(I56),ISNUMBER(J56),I56<>J56),IF(AND(L56>=I56,L56<=J56),1,0),""))) | X56: =IF(OR(F56="qualitativ",F56="fehlend",NOT(ISNUMBER(L56))),"nicht auswertbar",IF(F56="Punkt","Punktprognose",IF(AND(ISNUMBER(I56),ISNUMBER(J56),I56<>J56),IF(L56<I56,"unterhalb",IF(L56>J56,"oberhalb","innerhalb")),"nicht auswertbar"))) -> nicht auswertbar | Y56: =IF(AND(ISNUMBER(S56),OR(G56="Marge %",G56="Wachstumsrate %")),ABS(S56),"") | Z56: =IFERROR(VLOOKUP(A56,Unternehmen!$A:$D,4,FALSE()),"") -> Automobile
A57: BMW | B57: 2022 | C57: Operative Ergebnisgroesse | D57: 2021: https://www.bmwgroup.com/content/dam/grpw/websites/bmwgroup_com/ir/downloads/de/2022/bericht/BMW-Group-Bericht-2021-de.pdf | E57: 128 | F57: Bandbreite | G57: Marge % | H57: % (op. Marge) | I57: 0.07 | J57: 0.09 | K57: =L55 -> 0.103 | L57: 0.086 | M57: -1,70 PP | N57: im Rahmen | O57: 2022: https://www.bmwgroup.com/content/dam/grpw/websites/bmwgroup_com/ir/downloads/de/2023/bericht/BMW-Group-Bericht-2022-de.pdf | P57: 126 | R57: =IF(NOT(ISNUMBER(I57)),"",IF(F57="Mindestprognose",I57,IF(ISNUMBER(J57),(I57+J57)/2,I57))) -> 0.08 | S57: =IF(OR(R57="",NOT(ISNUMBER(L57))),"",R57-L57) -> -0.006 | T57: =IF(OR(S57="",G57<>"absolut",NOT(ISNUMBER(L57)),L57=0),"",S57/ABS(L57)) | U57: =IF(T57="","",ABS(T57)) | V57: =IF(OR(F57="Punkt",NOT(ISNUMBER(L57))),"",IF(F57="Mindestprognose",IF(L57>=I57,1,0),IF(AND(ISNUMBER(I57),ISNUMBER(J57),I57<>J57),IF(AND(L57>=I57,L57<=J57),1,0),""))) -> 1 | X57: =IF(OR(F57="qualitativ",F57="fehlend",NOT(ISNUMBER(L57))),"nicht auswertbar",IF(F57="Punkt","Punktprognose",IF(AND(ISNUMBER(I57),ISNUMBER(J57),I57<>J57),IF(L57<I57,"unterhalb",IF(L57>J57,"oberhalb","innerhalb")),"nicht auswertbar"))) -> innerhalb | Y57: =IF(AND(ISNUMBER(S57),OR(G57="Marge %",G57="Wachstumsrate %")),ABS(S57),"") -> 0.006 | Z57: =IFERROR(VLOOKUP(A57,Unternehmen!$A:$D,4,FALSE()),"") -> Automobile
A58: BMW | B58: 2023 | C58: Umsatz | F58: fehlend | R58: =IF(NOT(ISNUMBER(I58)),"",IF(F58="Mindestprognose",I58,IF(ISNUMBER(J58),(I58+J58)/2,I58))) | S58: =IF(OR(R58="",NOT(ISNUMBER(L58))),"",R58-L58) | T58: =IF(OR(S58="",G58<>"absolut",NOT(ISNUMBER(L58)),L58=0),"",S58/ABS(L58)) | U58: =IF(T58="","",ABS(T58)) | V58: =IF(OR(F58="Punkt",NOT(ISNUMBER(L58))),"",IF(F58="Mindestprognose",IF(L58>=I58,1,0),IF(AND(ISNUMBER(I58),ISNUMBER(J58),I58<>J58),IF(AND(L58>=I58,L58<=J58),1,0),""))) | X58: =IF(OR(F58="qualitativ",F58="fehlend",NOT(ISNUMBER(L58))),"nicht auswertbar",IF(F58="Punkt","Punktprognose",IF(AND(ISNUMBER(I58),ISNUMBER(J58),I58<>J58),IF(L58<I58,"unterhalb",IF(L58>J58,"oberhalb","innerhalb")),"nicht auswertbar"))) -> nicht auswertbar | Y58: =IF(AND(ISNUMBER(S58),OR(G58="Marge %",G58="Wachstumsrate %")),ABS(S58),"") | Z58: =IFERROR(VLOOKUP(A58,Unternehmen!$A:$D,4,FALSE()),"") -> Automobile
A59: BMW | B59: 2023 | C59: Operative Ergebnisgroesse | D59: 2022: https://www.bmwgroup.com/content/dam/grpw/websites/bmwgroup_com/ir/downloads/de/2023/bericht/BMW-Group-Bericht-2022-de.pdf | E59: 126 | F59: Bandbreite | G59: Marge % | H59: % (op. Marge) | I59: 0.08 | J59: 0.1 | K59: =L57 -> 0.086 | L59: 0.098 | M59: 1,20 PP | N59: im Rahmen | O59: 2023: https://www.bmwgroup.com/content/dam/grpw/websites/bmwgroup_com/ir/downloads/de/2024/bericht/BMW-Group-Bericht-2023-de.pdf | P59: 125 | R59: =IF(NOT(ISNUMBER(I59)),"",IF(F59="Mindestprognose",I59,IF(ISNUMBER(J59),(I59+J59)/2,I59))) -> 0.09 | S59: =IF(OR(R59="",NOT(ISNUMBER(L59))),"",R59-L59) -> -0.008 | T59: =IF(OR(S59="",G59<>"absolut",NOT(ISNUMBER(L59)),L59=0),"",S59/ABS(L59)) | U59: =IF(T59="","",ABS(T59)) | V59: =IF(OR(F59="Punkt",NOT(ISNUMBER(L59))),"",IF(F59="Mindestprognose",IF(L59>=I59,1,0),IF(AND(ISNUMBER(I59),ISNUMBER(J59),I59<>J59),IF(AND(L59>=I59,L59<=J59),1,0),""))) -> 1 | X59: =IF(OR(F59="qualitativ",F59="fehlend",NOT(ISNUMBER(L59))),"nicht auswertbar",IF(F59="Punkt","Punktprognose",IF(AND(ISNUMBER(I59),ISNUMBER(J59),I59<>J59),IF(L59<I59,"unterhalb",IF(L59>J59,"oberhalb","innerhalb")),"nicht auswertbar"))) -> innerhalb | Y59: =IF(AND(ISNUMBER(S59),OR(G59="Marge %",G59="Wachstumsrate %")),ABS(S59),"") -> 0.008 | Z59: =IFERROR(VLOOKUP(A59,Unternehmen!$A:$D,4,FALSE()),"") -> Automobile
A60: BMW | B60: 2024 | C60: Umsatz | F60: fehlend | R60: =IF(NOT(ISNUMBER(I60)),"",IF(F60="Mindestprognose",I60,IF(ISNUMBER(J60),(I60+J60)/2,I60))) | S60: =IF(OR(R60="",NOT(ISNUMBER(L60))),"",R60-L60) | T60: =IF(OR(S60="",G60<>"absolut",NOT(ISNUMBER(L60)),L60=0),"",S60/ABS(L60)) | U60: =IF(T60="","",ABS(T60)) | V60: =IF(OR(F60="Punkt",NOT(ISNUMBER(L60))),"",IF(F60="Mindestprognose",IF(L60>=I60,1,0),IF(AND(ISNUMBER(I60),ISNUMBER(J60),I60<>J60),IF(AND(L60>=I60,L60<=J60),1,0),""))) | X60: =IF(OR(F60="qualitativ",F60="fehlend",NOT(ISNUMBER(L60))),"nicht auswertbar",IF(F60="Punkt","Punktprognose",IF(AND(ISNUMBER(I60),ISNUMBER(J60),I60<>J60),IF(L60<I60,"unterhalb",IF(L60>J60,"oberhalb","innerhalb")),"nicht auswertbar"))) -> nicht auswertbar | Y60: =IF(AND(ISNUMBER(S60),OR(G60="Marge %",G60="Wachstumsrate %")),ABS(S60),"") | Z60: =IFERROR(VLOOKUP(A60,Unternehmen!$A:$D,4,FALSE()),"") -> Automobile
A61: BMW | B61: 2024 | C61: Operative Ergebnisgroesse | D61: 2023: https://www.bmwgroup.com/content/dam/grpw/websites/bmwgroup_com/ir/downloads/de/2024/bericht/BMW-Group-Bericht-2023-de.pdf | E61: 125 | F61: Bandbreite | G61: Marge % | H61: % (op. Marge) | I61: 0.08 | J61: 0.1 | K61: =L59 -> 0.098 | L61: 0.063 | M61: -3,50 PP | N61: -1,70 PP | O61: 2024: https://www.bmwgroup.com/de/bericht/2024/downloads/BMW-Group-Bericht-2024-de.pdf | P61: 263 | R61: =IF(NOT(ISNUMBER(I61)),"",IF(F61="Mindestprognose",I61,IF(ISNUMBER(J61),(I61+J61)/2,I61))) -> 0.09 | S61: =IF(OR(R61="",NOT(ISNUMBER(L61))),"",R61-L61) -> 0.027 | T61: =IF(OR(S61="",G61<>"absolut",NOT(ISNUMBER(L61)),L61=0),"",S61/ABS(L61)) | U61: =IF(T61="","",ABS(T61)) | V61: =IF(OR(F61="Punkt",NOT(ISNUMBER(L61))),"",IF(F61="Mindestprognose",IF(L61>=I61,1,0),IF(AND(ISNUMBER(I61),ISNUMBER(J61),I61<>J61),IF(AND(L61>=I61,L61<=J61),1,0),""))) -> 0 | X61: =IF(OR(F61="qualitativ",F61="fehlend",NOT(ISNUMBER(L61))),"nicht auswertbar",IF(F61="Punkt","Punktprognose",IF(AND(ISNUMBER(I61),ISNUMBER(J61),I61<>J61),IF(L61<I61,"unterhalb",IF(L61>J61,"oberhalb","innerhalb")),"nicht auswertbar"))) -> unterhalb | Y61: =IF(AND(ISNUMBER(S61),OR(G61="Marge %",G61="Wachstumsrate %")),ABS(S61),"") -> 0.027 | Z61: =IFERROR(VLOOKUP(A61,Unternehmen!$A:$D,4,FALSE()),"") -> Automobile
A62: CON | B62: 2020 | C62: Umsatz | D62: 2019: https://www.continental.com/fileadmin/__imported/sites/corporate/_international/german/hubpages/30_20investor_20relations/40_20finanzberichte/gesch_c3_a4ftsberichte/downloads/gesch_c3_a4ftsbericht_202019.pdf | E62: 104 | F62: Punkt mit Korridor | G62: absolut | H62: Mrd. EUR | I62: 42.5 | J62: 44.5 | K62: 44.5 | L62: 37.7 | M62: =L62-K62 -> -6.8 | N62: -4,80 Mrd. EUR | O62: 2020: https://www.continental.com/fileadmin/__imported/sites/corporate/_international/german/hubpages/30_20investor_20relations/40_20finanzberichte/gesch_c3_a4ftsberichte/downloads/gesch_c3_a4ftsbericht_202020.pdf | P62: 113 | R62: =IF(NOT(ISNUMBER(I62)),"",IF(F62="Mindestprognose",I62,IF(ISNUMBER(J62),(I62+J62)/2,I62))) -> 43.5 | S62: =IF(OR(R62="",NOT(ISNUMBER(L62))),"",R62-L62) -> 5.8 | T62: =IF(OR(S62="",G62<>"absolut",NOT(ISNUMBER(L62)),L62=0),"",S62/ABS(L62)) -> 0.15384615 | U62: =IF(T62="","",ABS(T62)) -> 0.15384615 | V62: =IF(OR(F62="Punkt",NOT(ISNUMBER(L62))),"",IF(F62="Mindestprognose",IF(L62>=I62,1,0),IF(AND(ISNUMBER(I62),ISNUMBER(J62),I62<>J62),IF(AND(L62>=I62,L62<=J62),1,0),""))) -> 0 | X62: =IF(OR(F62="qualitativ",F62="fehlend",NOT(ISNUMBER(L62))),"nicht auswertbar",IF(F62="Punkt","Punktprognose",IF(AND(ISNUMBER(I62),ISNUMBER(J62),I62<>J62),IF(L62<I62,"unterhalb",IF(L62>J62,"oberhalb","innerhalb")),"nicht auswertbar"))) -> unterhalb | Y62: =IF(AND(ISNUMBER(S62),OR(G62="Marge %",G62="Wachstumsrate %")),ABS(S62),"") | Z62: =IFERROR(VLOOKUP(A62,Unternehmen!$A:$D,4,FALSE()),"") -> Automobile
A63: CON | B63: 2020 | C63: Operative Ergebnisgroesse | D63: 2019: https://www.continental.com/fileadmin/__imported/sites/corporate/_international/german/hubpages/30_20investor_20relations/40_20finanzberichte/gesch_c3_a4ftsberichte/downloads/gesch_c3_a4ftsbericht_202019.pdf | E63: 104 | F63: Bandbreite | G63: Marge % | H63: % (op. Marge) | I63: 0.055 | J63: 0.065 | K63: 0.074 | L63: 0.035 | M63: -3,90 PP | N63: -2 PP | O63: 2020: https://www.continental.com/fileadmin/__imported/sites/corporate/_international/german/hubpages/30_20investor_20relations/40_20finanzberichte/gesch_c3_a4ftsberichte/downloads/gesch_c3_a4ftsbericht_202020.pdf | P63: 113 | R63: =IF(NOT(ISNUMBER(I63)),"",IF(F63="Mindestprognose",I63,IF(ISNUMBER(J63),(I63+J63)/2,I63))) -> 0.06 | S63: =IF(OR(R63="",NOT(ISNUMBER(L63))),"",R63-L63) -> 0.025 | T63: =IF(OR(S63="",G63<>"absolut",NOT(ISNUMBER(L63)),L63=0),"",S63/ABS(L63)) | U63: =IF(T63="","",ABS(T63)) | V63: =IF(OR(F63="Punkt",NOT(ISNUMBER(L63))),"",IF(F63="Mindestprognose",IF(L63>=I63,1,0),IF(AND(ISNUMBER(I63),ISNUMBER(J63),I63<>J63),IF(AND(L63>=I63,L63<=J63),1,0),""))) -> 0 | X63: =IF(OR(F63="qualitativ",F63="fehlend",NOT(ISNUMBER(L63))),"nicht auswertbar",IF(F63="Punkt","Punktprognose",IF(AND(ISNUMBER(I63),ISNUMBER(J63),I63<>J63),IF(L63<I63,"unterhalb",IF(L63>J63,"oberhalb","innerhalb")),"nicht auswertbar"))) -> unterhalb | Y63: =IF(AND(ISNUMBER(S63),OR(G63="Marge %",G63="Wachstumsrate %")),ABS(S63),"") -> 0.025 | Z63: =IFERROR(VLOOKUP(A63,Unternehmen!$A:$D,4,FALSE()),"") -> Automobile
A64: CON | B64: 2021 | C64: Umsatz | D64: 2020: https://www.continental.com/fileadmin/__imported/sites/corporate/_international/german/hubpages/30_20investor_20relations/40_20finanzberichte/gesch_c3_a4ftsberichte/downloads/gesch_c3_a4ftsbericht_202020.pdf | E64: 114 | F64: Punkt mit Korridor | G64: absolut | H64: Mrd. EUR | I64: 40.5 | J64: 42.5 | K64: =L62 -> 37.7 | L64: 33.8 | M64: =L64-K64 -> -3.9 | N64: -6,70 Mrd. EUR | O64: 2021: https://www.continental.com/fileadmin/__imported/sites/corporate/_international/german/hubpages/30_20investor_20relations/40_20finanzberichte/gesch_c3_a4ftsberichte/downloads/continental_geschaeftsbericht_2021_so.pdf | P64: 99 | R64: =IF(NOT(ISNUMBER(I64)),"",IF(F64="Mindestprognose",I64,IF(ISNUMBER(J64),(I64+J64)/2,I64))) -> 41.5 | S64: =IF(OR(R64="",NOT(ISNUMBER(L64))),"",R64-L64) -> 7.7 | T64: =IF(OR(S64="",G64<>"absolut",NOT(ISNUMBER(L64)),L64=0),"",S64/ABS(L64)) -> 0.22781065 | U64: =IF(T64="","",ABS(T64)) -> 0.22781065 | V64: =IF(OR(F64="Punkt",NOT(ISNUMBER(L64))),"",IF(F64="Mindestprognose",IF(L64>=I64,1,0),IF(AND(ISNUMBER(I64),ISNUMBER(J64),I64<>J64),IF(AND(L64>=I64,L64<=J64),1,0),""))) -> 0 | X64: =IF(OR(F64="qualitativ",F64="fehlend",NOT(ISNUMBER(L64))),"nicht auswertbar",IF(F64="Punkt","Punktprognose",IF(AND(ISNUMBER(I64),ISNUMBER(J64),I64<>J64),IF(L64<I64,"unterhalb",IF(L64>J64,"oberhalb","innerhalb")),"nicht auswertbar"))) -> unterhalb | Y64: =IF(AND(ISNUMBER(S64),OR(G64="Marge %",G64="Wachstumsrate %")),ABS(S64),"") | Z64: =IFERROR(VLOOKUP(A64,Unternehmen!$A:$D,4,FALSE()),"") -> Automobile
A65: CON | B65: 2021 | C65: Operative Ergebnisgroesse | D65: 2020: https://www.continental.com/fileadmin/__imported/sites/corporate/_international/german/hubpages/30_20investor_20relations/40_20finanzberichte/gesch_c3_a4ftsberichte/downloads/gesch_c3_a4ftsbericht_202020.pdf | E65: 114 | F65: Bandbreite | G65: Marge % | H65: % (op. Marge) | I65: 0.05 | J65: 0.06 | K65: =L63 -> 0.035 | L65: 0.056 | M65: 2,10 PP | N65: im Rahmen | O65: 2021: https://www.continental.com/fileadmin/__imported/sites/corporate/_international/german/hubpages/30_20investor_20relations/40_20finanzberichte/gesch_c3_a4ftsberichte/downloads/continental_geschaeftsbericht_2021_so.pdf | P65: 99 | R65: =IF(NOT(ISNUMBER(I65)),"",IF(F65="Mindestprognose",I65,IF(ISNUMBER(J65),(I65+J65)/2,I65))) -> 0.055 | S65: =IF(OR(R65="",NOT(ISNUMBER(L65))),"",R65-L65) -> -0.001 | T65: =IF(OR(S65="",G65<>"absolut",NOT(ISNUMBER(L65)),L65=0),"",S65/ABS(L65)) | U65: =IF(T65="","",ABS(T65)) | V65: =IF(OR(F65="Punkt",NOT(ISNUMBER(L65))),"",IF(F65="Mindestprognose",IF(L65>=I65,1,0),IF(AND(ISNUMBER(I65),ISNUMBER(J65),I65<>J65),IF(AND(L65>=I65,L65<=J65),1,0),""))) -> 1 | X65: =IF(OR(F65="qualitativ",F65="fehlend",NOT(ISNUMBER(L65))),"nicht auswertbar",IF(F65="Punkt","Punktprognose",IF(AND(ISNUMBER(I65),ISNUMBER(J65),I65<>J65),IF(L65<I65,"unterhalb",IF(L65>J65,"oberhalb","innerhalb")),"nicht auswertbar"))) -> innerhalb | Y65: =IF(AND(ISNUMBER(S65),OR(G65="Marge %",G65="Wachstumsrate %")),ABS(S65),"") -> 0.001 | Z65: =IFERROR(VLOOKUP(A65,Unternehmen!$A:$D,4,FALSE()),"") -> Automobile
A66: CON | B66: 2022 | C66: Umsatz | D66: 2021: https://www.continental.com/fileadmin/__imported/sites/corporate/_international/german/hubpages/30_20investor_20relations/40_20finanzberichte/gesch_c3_a4ftsberichte/downloads/continental_geschaeftsbericht_2021_so.pdf | E66: 101 | F66: Punkt mit Korridor | G66: absolut | H66: Mrd. EUR | I66: 38 | J66: 40 | K66: =L64 -> 33.8 | L66: 39.4 | M66: =L66-K66 -> 5.6 | N66: im Rahmen | O66: 2022: https://www.continental.com/fileadmin/__imported/sites/corporate/_international/german/hubpages/30_20investor_20relations/40_20finanzberichte/gesch_c3_a4ftsberichte/downloads/continental_geschaeftsbericht_2022.pdf | P66: 105 | R66: =IF(NOT(ISNUMBER(I66)),"",IF(F66="Mindestprognose",I66,IF(ISNUMBER(J66),(I66+J66)/2,I66))) -> 39 | S66: =IF(OR(R66="",NOT(ISNUMBER(L66))),"",R66-L66) -> -0.4 | T66: =IF(OR(S66="",G66<>"absolut",NOT(ISNUMBER(L66)),L66=0),"",S66/ABS(L66)) -> -0.010152284 | U66: =IF(T66="","",ABS(T66)) -> 0.010152284 | V66: =IF(OR(F66="Punkt",NOT(ISNUMBER(L66))),"",IF(F66="Mindestprognose",IF(L66>=I66,1,0),IF(AND(ISNUMBER(I66),ISNUMBER(J66),I66<>J66),IF(AND(L66>=I66,L66<=J66),1,0),""))) -> 1 | X66: =IF(OR(F66="qualitativ",F66="fehlend",NOT(ISNUMBER(L66))),"nicht auswertbar",IF(F66="Punkt","Punktprognose",IF(AND(ISNUMBER(I66),ISNUMBER(J66),I66<>J66),IF(L66<I66,"unterhalb",IF(L66>J66,"oberhalb","innerhalb")),"nicht auswertbar"))) -> innerhalb | Y66: =IF(AND(ISNUMBER(S66),OR(G66="Marge %",G66="Wachstumsrate %")),ABS(S66),"") | Z66: =IFERROR(VLOOKUP(A66,Unternehmen!$A:$D,4,FALSE()),"") -> Automobile
A67: CON | B67: 2022 | C67: Operative Ergebnisgroesse | D67: 2021: https://www.continental.com/fileadmin/__imported/sites/corporate/_international/german/hubpages/30_20investor_20relations/40_20finanzberichte/gesch_c3_a4ftsberichte/downloads/continental_geschaeftsbericht_2021_so.pdf | E67: 101 | F67: Bandbreite | G67: Marge % | H67: % (op. Marge) | I67: 0.055 | J67: 0.065 | K67: =L65 -> 0.056 | L67: 0.05 | M67: -0,60 PP | N67: im Rahmen | O67: 2022: https://www.continental.com/fileadmin/__imported/sites/corporate/_international/german/hubpages/30_20investor_20relations/40_20finanzberichte/gesch_c3_a4ftsberichte/downloads/continental_geschaeftsbericht_2022.pdf | P67: 105 | R67: =IF(NOT(ISNUMBER(I67)),"",IF(F67="Mindestprognose",I67,IF(ISNUMBER(J67),(I67+J67)/2,I67))) -> 0.06 | S67: =IF(OR(R67="",NOT(ISNUMBER(L67))),"",R67-L67) -> 0.01 | T67: =IF(OR(S67="",G67<>"absolut",NOT(ISNUMBER(L67)),L67=0),"",S67/ABS(L67)) | U67: =IF(T67="","",ABS(T67)) | V67: =IF(OR(F67="Punkt",NOT(ISNUMBER(L67))),"",IF(F67="Mindestprognose",IF(L67>=I67,1,0),IF(AND(ISNUMBER(I67),ISNUMBER(J67),I67<>J67),IF(AND(L67>=I67,L67<=J67),1,0),""))) -> 0 | X67: =IF(OR(F67="qualitativ",F67="fehlend",NOT(ISNUMBER(L67))),"nicht auswertbar",IF(F67="Punkt","Punktprognose",IF(AND(ISNUMBER(I67),ISNUMBER(J67),I67<>J67),IF(L67<I67,"unterhalb",IF(L67>J67,"oberhalb","innerhalb")),"nicht auswertbar"))) -> unterhalb | Y67: =IF(AND(ISNUMBER(S67),OR(G67="Marge %",G67="Wachstumsrate %")),ABS(S67),"") -> 0.01 | Z67: =IFERROR(VLOOKUP(A67,Unternehmen!$A:$D,4,FALSE()),"") -> Automobile
A68: CON | B68: 2023 | C68: Umsatz | D68: 2022: https://www.continental.com/fileadmin/__imported/sites/corporate/_international/german/hubpages/30_20investor_20relations/40_20finanzberichte/gesch_c3_a4ftsberichte/downloads/continental_geschaeftsbericht_2022.pdf | E68: 106 | F68: Punkt mit Korridor | G68: absolut | H68: Mrd. EUR | I68: 42 | J68: 45 | K68: =L66 -> 39.4 | L68: 41.4 | M68: =L68-K68 -> 2 | N68: -0,60 Mrd. EUR | O68: 2023: https://www.continental.com/fileadmin/__imported/sites/corporate/_international/german/hubpages/30_20investor_20relations/40_20finanzberichte/gesch_c3_a4ftsberichte/downloads/geschaeftsbericht_2023.pdf | P68: 112 | R68: =IF(NOT(ISNUMBER(I68)),"",IF(F68="Mindestprognose",I68,IF(ISNUMBER(J68),(I68+J68)/2,I68))) -> 43.5 | S68: =IF(OR(R68="",NOT(ISNUMBER(L68))),"",R68-L68) -> 2.1 | T68: =IF(OR(S68="",G68<>"absolut",NOT(ISNUMBER(L68)),L68=0),"",S68/ABS(L68)) -> 0.050724638 | U68: =IF(T68="","",ABS(T68)) -> 0.050724638 | V68: =IF(OR(F68="Punkt",NOT(ISNUMBER(L68))),"",IF(F68="Mindestprognose",IF(L68>=I68,1,0),IF(AND(ISNUMBER(I68),ISNUMBER(J68),I68<>J68),IF(AND(L68>=I68,L68<=J68),1,0),""))) -> 0 | X68: =IF(OR(F68="qualitativ",F68="fehlend",NOT(ISNUMBER(L68))),"nicht auswertbar",IF(F68="Punkt","Punktprognose",IF(AND(ISNUMBER(I68),ISNUMBER(J68),I68<>J68),IF(L68<I68,"unterhalb",IF(L68>J68,"oberhalb","innerhalb")),"nicht auswertbar"))) -> unterhalb | Y68: =IF(AND(ISNUMBER(S68),OR(G68="Marge %",G68="Wachstumsrate %")),ABS(S68),"") | Z68: =IFERROR(VLOOKUP(A68,Unternehmen!$A:$D,4,FALSE()),"") -> Automobile
A69: CON | B69: 2023 | C69: Operative Ergebnisgroesse | D69: 2022: https://www.continental.com/fileadmin/__imported/sites/corporate/_international/german/hubpages/30_20investor_20relations/40_20finanzberichte/gesch_c3_a4ftsberichte/downloads/continental_geschaeftsbericht_2022.pdf | E69: 106 | F69: Bandbreite | G69: Marge % | H69: % (op. Marge) | I69: 0.055 | J69: 0.065 | K69: =L67 -> 0.05 | L69: 0.061 | M69: 1,10 PP | N69: im Rahmen | O69: 2023: https://www.continental.com/fileadmin/__imported/sites/corporate/_international/german/hubpages/30_20investor_20relations/40_20finanzberichte/gesch_c3_a4ftsberichte/downloads/geschaeftsbericht_2023.pdf | P69: 112 | R69: =IF(NOT(ISNUMBER(I69)),"",IF(F69="Mindestprognose",I69,IF(ISNUMBER(J69),(I69+J69)/2,I69))) -> 0.06 | S69: =IF(OR(R69="",NOT(ISNUMBER(L69))),"",R69-L69) -> -0.001 | T69: =IF(OR(S69="",G69<>"absolut",NOT(ISNUMBER(L69)),L69=0),"",S69/ABS(L69)) | U69: =IF(T69="","",ABS(T69)) | V69: =IF(OR(F69="Punkt",NOT(ISNUMBER(L69))),"",IF(F69="Mindestprognose",IF(L69>=I69,1,0),IF(AND(ISNUMBER(I69),ISNUMBER(J69),I69<>J69),IF(AND(L69>=I69,L69<=J69),1,0),""))) -> 1 | X69: =IF(OR(F69="qualitativ",F69="fehlend",NOT(ISNUMBER(L69))),"nicht auswertbar",IF(F69="Punkt","Punktprognose",IF(AND(ISNUMBER(I69),ISNUMBER(J69),I69<>J69),IF(L69<I69,"unterhalb",IF(L69>J69,"oberhalb","innerhalb")),"nicht auswertbar"))) -> innerhalb | Y69: =IF(AND(ISNUMBER(S69),OR(G69="Marge %",G69="Wachstumsrate %")),ABS(S69),"") -> 0.001 | Z69: =IFERROR(VLOOKUP(A69,Unternehmen!$A:$D,4,FALSE()),"") -> Automobile
A70: CON | B70: 2024 | C70: Umsatz | D70: 2023: https://www.continental.com/fileadmin/__imported/sites/corporate/_international/german/hubpages/30_20investor_20relations/40_20finanzberichte/gesch_c3_a4ftsberichte/downloads/geschaeftsbericht_2023.pdf | E70: 112 | F70: Punkt mit Korridor | G70: absolut | H70: Mrd. EUR | I70: 41 | J70: 44 | K70: =L68 -> 41.4 | L70: 39.7 | M70: =L70-K70 -> -1.7 | N70: -1,30 Mrd. EUR | O70: 2024: https://www.continental.com/fileadmin/__imported/sites/corporate/_international/german/hubpages/30_20investor_20relations/40_20finanzberichte/gesch_c3_a4ftsberichte/downloads/geschaeftsbericht-2024.pdf | P70: 94 | R70: =IF(NOT(ISNUMBER(I70)),"",IF(F70="Mindestprognose",I70,IF(ISNUMBER(J70),(I70+J70)/2,I70))) -> 42.5 | S70: =IF(OR(R70="",NOT(ISNUMBER(L70))),"",R70-L70) -> 2.8 | T70: =IF(OR(S70="",G70<>"absolut",NOT(ISNUMBER(L70)),L70=0),"",S70/ABS(L70)) -> 0.070528967 | U70: =IF(T70="","",ABS(T70)) -> 0.070528967 | V70: =IF(OR(F70="Punkt",NOT(ISNUMBER(L70))),"",IF(F70="Mindestprognose",IF(L70>=I70,1,0),IF(AND(ISNUMBER(I70),ISNUMBER(J70),I70<>J70),IF(AND(L70>=I70,L70<=J70),1,0),""))) -> 0 | X70: =IF(OR(F70="qualitativ",F70="fehlend",NOT(ISNUMBER(L70))),"nicht auswertbar",IF(F70="Punkt","Punktprognose",IF(AND(ISNUMBER(I70),ISNUMBER(J70),I70<>J70),IF(L70<I70,"unterhalb",IF(L70>J70,"oberhalb","innerhalb")),"nicht auswertbar"))) -> unterhalb | Y70: =IF(AND(ISNUMBER(S70),OR(G70="Marge %",G70="Wachstumsrate %")),ABS(S70),"") | Z70: =IFERROR(VLOOKUP(A70,Unternehmen!$A:$D,4,FALSE()),"") -> Automobile
A71: CON | B71: 2024 | C71: Operative Ergebnisgroesse | D71: 2023: https://www.continental.com/fileadmin/__imported/sites/corporate/_international/german/hubpages/30_20investor_20relations/40_20finanzberichte/gesch_c3_a4ftsberichte/downloads/geschaeftsbericht_2023.pdf | E71: 112 | F71: Bandbreite | G71: Marge % | H71: % (op. Marge) | I71: 0.06 | J71: 0.07 | K71: =L69 -> 0.061 | L71: 0.068 | M71: 0,70 PP | N71: im Rahmen | O71: 2024: https://www.continental.com/fileadmin/__imported/sites/corporate/_international/german/hubpages/30_20investor_20relations/40_20finanzberichte/gesch_c3_a4ftsberichte/downloads/geschaeftsbericht-2024.pdf | P71: 94 | R71: =IF(NOT(ISNUMBER(I71)),"",IF(F71="Mindestprognose",I71,IF(ISNUMBER(J71),(I71+J71)/2,I71))) -> 0.065 | S71: =IF(OR(R71="",NOT(ISNUMBER(L71))),"",R71-L71) -> -0.003 | T71: =IF(OR(S71="",G71<>"absolut",NOT(ISNUMBER(L71)),L71=0),"",S71/ABS(L71)) | U71: =IF(T71="","",ABS(T71)) | V71: =IF(OR(F71="Punkt",NOT(ISNUMBER(L71))),"",IF(F71="Mindestprognose",IF(L71>=I71,1,0),IF(AND(ISNUMBER(I71),ISNUMBER(J71),I71<>J71),IF(AND(L71>=I71,L71<=J71),1,0),""))) -> 1 | X71: =IF(OR(F71="qualitativ",F71="fehlend",NOT(ISNUMBER(L71))),"nicht auswertbar",IF(F71="Punkt","Punktprognose",IF(AND(ISNUMBER(I71),ISNUMBER(J71),I71<>J71),IF(L71<I71,"unterhalb",IF(L71>J71,"oberhalb","innerhalb")),"nicht auswertbar"))) -> innerhalb | Y71: =IF(AND(ISNUMBER(S71),OR(G71="Marge %",G71="Wachstumsrate %")),ABS(S71),"") -> 0.003 | Z71: =IFERROR(VLOOKUP(A71,Unternehmen!$A:$D,4,FALSE()),"") -> Automobile
A72: 1COV | B72: 2020 | C72: Umsatz | D72: 2019: https://bericht.covestro.com/geschaeftsbericht-2019/serviceseiten/downloads/files/covestro_gb19_gesamt.pdf | F72: fehlend | Q72: Beide KPI's fehlen im Jahr 2019 und 2020 | R72: =IF(NOT(ISNUMBER(I72)),"",IF(F72="Mindestprognose",I72,IF(ISNUMBER(J72),(I72+J72)/2,I72))) | S72: =IF(OR(R72="",NOT(ISNUMBER(L72))),"",R72-L72) | T72: =IF(OR(S72="",G72<>"absolut",NOT(ISNUMBER(L72)),L72=0),"",S72/ABS(L72)) | U72: =IF(T72="","",ABS(T72)) | V72: =IF(OR(F72="Punkt",NOT(ISNUMBER(L72))),"",IF(F72="Mindestprognose",IF(L72>=I72,1,0),IF(AND(ISNUMBER(I72),ISNUMBER(J72),I72<>J72),IF(AND(L72>=I72,L72<=J72),1,0),""))) | X72: =IF(OR(F72="qualitativ",F72="fehlend",NOT(ISNUMBER(L72))),"nicht auswertbar",IF(F72="Punkt","Punktprognose",IF(AND(ISNUMBER(I72),ISNUMBER(J72),I72<>J72),IF(L72<I72,"unterhalb",IF(L72>J72,"oberhalb","innerhalb")),"nicht auswertbar"))) -> nicht auswertbar | Y72: =IF(AND(ISNUMBER(S72),OR(G72="Marge %",G72="Wachstumsrate %")),ABS(S72),"") | Z72: =IFERROR(VLOOKUP(A72,Unternehmen!$A:$D,4,FALSE()),"") -> Chemie
A73: 1COV | B73: 2020 | C73: Operative Ergebnisgroesse | D73: 2019: https://bericht.covestro.com/geschaeftsbericht-2019/serviceseiten/downloads/files/covestro_gb19_gesamt.pdf | F73: fehlend | R73: =IF(NOT(ISNUMBER(I73)),"",IF(F73="Mindestprognose",I73,IF(ISNUMBER(J73),(I73+J73)/2,I73))) | S73: =IF(OR(R73="",NOT(ISNUMBER(L73))),"",R73-L73) | T73: =IF(OR(S73="",G73<>"absolut",NOT(ISNUMBER(L73)),L73=0),"",S73/ABS(L73)) | U73: =IF(T73="","",ABS(T73)) | V73: =IF(OR(F73="Punkt",NOT(ISNUMBER(L73))),"",IF(F73="Mindestprognose",IF(L73>=I73,1,0),IF(AND(ISNUMBER(I73),ISNUMBER(J73),I73<>J73),IF(AND(L73>=I73,L73<=J73),1,0),""))) | X73: =IF(OR(F73="qualitativ",F73="fehlend",NOT(ISNUMBER(L73))),"nicht auswertbar",IF(F73="Punkt","Punktprognose",IF(AND(ISNUMBER(I73),ISNUMBER(J73),I73<>J73),IF(L73<I73,"unterhalb",IF(L73>J73,"oberhalb","innerhalb")),"nicht auswertbar"))) -> nicht auswertbar | Y73: =IF(AND(ISNUMBER(S73),OR(G73="Marge %",G73="Wachstumsrate %")),ABS(S73),"") | Z73: =IFERROR(VLOOKUP(A73,Unternehmen!$A:$D,4,FALSE()),"") -> Chemie
A74: 1COV | B74: 2021 | C74: Umsatz | D74: 2020: https://www.bericht.covestro.com/geschaeftsbericht-2020/serviceseiten/downloads/files/covestro-ar20-entire.pdf | F74: fehlend | R74: =IF(NOT(ISNUMBER(I74)),"",IF(F74="Mindestprognose",I74,IF(ISNUMBER(J74),(I74+J74)/2,I74))) | S74: =IF(OR(R74="",NOT(ISNUMBER(L74))),"",R74-L74) | T74: =IF(OR(S74="",G74<>"absolut",NOT(ISNUMBER(L74)),L74=0),"",S74/ABS(L74)) | U74: =IF(T74="","",ABS(T74)) | V74: =IF(OR(F74="Punkt",NOT(ISNUMBER(L74))),"",IF(F74="Mindestprognose",IF(L74>=I74,1,0),IF(AND(ISNUMBER(I74),ISNUMBER(J74),I74<>J74),IF(AND(L74>=I74,L74<=J74),1,0),""))) | X74: =IF(OR(F74="qualitativ",F74="fehlend",NOT(ISNUMBER(L74))),"nicht auswertbar",IF(F74="Punkt","Punktprognose",IF(AND(ISNUMBER(I74),ISNUMBER(J74),I74<>J74),IF(L74<I74,"unterhalb",IF(L74>J74,"oberhalb","innerhalb")),"nicht auswertbar"))) -> nicht auswertbar | Y74: =IF(AND(ISNUMBER(S74),OR(G74="Marge %",G74="Wachstumsrate %")),ABS(S74),"") | Z74: =IFERROR(VLOOKUP(A74,Unternehmen!$A:$D,4,FALSE()),"") -> Chemie
A75: 1COV | B75: 2021 | C75: Operative Ergebnisgroesse | D75: 2020: https://www.bericht.covestro.com/geschaeftsbericht-2020/serviceseiten/downloads/files/covestro-ar20-entire.pdf | F75: fehlend | R75: =IF(NOT(ISNUMBER(I75)),"",IF(F75="Mindestprognose",I75,IF(ISNUMBER(J75),(I75+J75)/2,I75))) | S75: =IF(OR(R75="",NOT(ISNUMBER(L75))),"",R75-L75) | T75: =IF(OR(S75="",G75<>"absolut",NOT(ISNUMBER(L75)),L75=0),"",S75/ABS(L75)) | U75: =IF(T75="","",ABS(T75)) | V75: =IF(OR(F75="Punkt",NOT(ISNUMBER(L75))),"",IF(F75="Mindestprognose",IF(L75>=I75,1,0),IF(AND(ISNUMBER(I75),ISNUMBER(J75),I75<>J75),IF(AND(L75>=I75,L75<=J75),1,0),""))) | X75: =IF(OR(F75="qualitativ",F75="fehlend",NOT(ISNUMBER(L75))),"nicht auswertbar",IF(F75="Punkt","Punktprognose",IF(AND(ISNUMBER(I75),ISNUMBER(J75),I75<>J75),IF(L75<I75,"unterhalb",IF(L75>J75,"oberhalb","innerhalb")),"nicht auswertbar"))) -> nicht auswertbar | Y75: =IF(AND(ISNUMBER(S75),OR(G75="Marge %",G75="Wachstumsrate %")),ABS(S75),"") | Z75: =IFERROR(VLOOKUP(A75,Unternehmen!$A:$D,4,FALSE()),"") -> Chemie
A76: 1COV | B76: 2022 | C76: Umsatz | D76: 2021: https://bericht.covestro.com/geschaeftsbericht-2021/serviceseiten/downloads/files/entire-covestro-ar21.pdf | F76: fehlend | Q76: Umsatzprognose als KPI fehlt | R76: =IF(NOT(ISNUMBER(I76)),"",IF(F76="Mindestprognose",I76,IF(ISNUMBER(J76),(I76+J76)/2,I76))) | S76: =IF(OR(R76="",NOT(ISNUMBER(L76))),"",R76-L76) | T76: =IF(OR(S76="",G76<>"absolut",NOT(ISNUMBER(L76)),L76=0),"",S76/ABS(L76)) | U76: =IF(T76="","",ABS(T76)) | V76: =IF(OR(F76="Punkt",NOT(ISNUMBER(L76))),"",IF(F76="Mindestprognose",IF(L76>=I76,1,0),IF(AND(ISNUMBER(I76),ISNUMBER(J76),I76<>J76),IF(AND(L76>=I76,L76<=J76),1,0),""))) | X76: =IF(OR(F76="qualitativ",F76="fehlend",NOT(ISNUMBER(L76))),"nicht auswertbar",IF(F76="Punkt","Punktprognose",IF(AND(ISNUMBER(I76),ISNUMBER(J76),I76<>J76),IF(L76<I76,"unterhalb",IF(L76>J76,"oberhalb","innerhalb")),"nicht auswertbar"))) -> nicht auswertbar | Y76: =IF(AND(ISNUMBER(S76),OR(G76="Marge %",G76="Wachstumsrate %")),ABS(S76),"") | Z76: =IFERROR(VLOOKUP(A76,Unternehmen!$A:$D,4,FALSE()),"") -> Chemie
A77: 1COV | B77: 2022 | C77: Operative Ergebnisgroesse | D77: 2021: https://bericht.covestro.com/geschaeftsbericht-2021/serviceseiten/downloads/files/entire-covestro-ar21.pdf | E77: 144 | F77: Punkt mit Korridor | G77: absolut | H77: Mio. EUR | I77: 2500 | J77: 3000 | K77: 3085 | L77: 1617 | M77: =L77-K77 -> -1468 | N77: -883 Mio. EUR | O77: 2022: https://bericht.covestro.com/geschaeftsbericht-2022/_assets/downloads/covestro-ar22-entire.pdf | P77: 152 | R77: =IF(NOT(ISNUMBER(I77)),"",IF(F77="Mindestprognose",I77,IF(ISNUMBER(J77),(I77+J77)/2,I77))) -> 2750 | S77: =IF(OR(R77="",NOT(ISNUMBER(L77))),"",R77-L77) -> 1133 | T77: =IF(OR(S77="",G77<>"absolut",NOT(ISNUMBER(L77)),L77=0),"",S77/ABS(L77)) -> 0.70068027 | U77: =IF(T77="","",ABS(T77)) -> 0.70068027 | V77: =IF(OR(F77="Punkt",NOT(ISNUMBER(L77))),"",IF(F77="Mindestprognose",IF(L77>=I77,1,0),IF(AND(ISNUMBER(I77),ISNUMBER(J77),I77<>J77),IF(AND(L77>=I77,L77<=J77),1,0),""))) -> 0 | X77: =IF(OR(F77="qualitativ",F77="fehlend",NOT(ISNUMBER(L77))),"nicht auswertbar",IF(F77="Punkt","Punktprognose",IF(AND(ISNUMBER(I77),ISNUMBER(J77),I77<>J77),IF(L77<I77,"unterhalb",IF(L77>J77,"oberhalb","innerhalb")),"nicht auswertbar"))) -> unterhalb | Y77: =IF(AND(ISNUMBER(S77),OR(G77="Marge %",G77="Wachstumsrate %")),ABS(S77),"") | Z77: =IFERROR(VLOOKUP(A77,Unternehmen!$A:$D,4,FALSE()),"") -> Chemie
A78: 1COV | B78: 2023 | C78: Umsatz | F78: fehlend | Q78: Umsatzprognose als KPI fehlt | R78: =IF(NOT(ISNUMBER(I78)),"",IF(F78="Mindestprognose",I78,IF(ISNUMBER(J78),(I78+J78)/2,I78))) | S78: =IF(OR(R78="",NOT(ISNUMBER(L78))),"",R78-L78) | T78: =IF(OR(S78="",G78<>"absolut",NOT(ISNUMBER(L78)),L78=0),"",S78/ABS(L78)) | U78: =IF(T78="","",ABS(T78)) | V78: =IF(OR(F78="Punkt",NOT(ISNUMBER(L78))),"",IF(F78="Mindestprognose",IF(L78>=I78,1,0),IF(AND(ISNUMBER(I78),ISNUMBER(J78),I78<>J78),IF(AND(L78>=I78,L78<=J78),1,0),""))) | X78: =IF(OR(F78="qualitativ",F78="fehlend",NOT(ISNUMBER(L78))),"nicht auswertbar",IF(F78="Punkt","Punktprognose",IF(AND(ISNUMBER(I78),ISNUMBER(J78),I78<>J78),IF(L78<I78,"unterhalb",IF(L78>J78,"oberhalb","innerhalb")),"nicht auswertbar"))) -> nicht auswertbar | Y78: =IF(AND(ISNUMBER(S78),OR(G78="Marge %",G78="Wachstumsrate %")),ABS(S78),"") | Z78: =IFERROR(VLOOKUP(A78,Unternehmen!$A:$D,4,FALSE()),"") -> Chemie
A79: 1COV | B79: 2023 | C79: Operative Ergebnisgroesse | D79: 2022: https://bericht.covestro.com/geschaeftsbericht-2022/_assets/downloads/covestro-ar22-entire.pdf | E79: 152 | F79: qualitativ | G79: absolut | H79: Mio. EUR | K79: =L77 -> 1617 | L79: 1080 | M79: =L79-K79 -> -537 | N79: im Rahmen | O79: 2023: https://bericht.covestro.com/geschaeftsbericht-2023/_assets/downloads/covestro-ar23-entire.pdf | P79: 84 | R79: =IF(NOT(ISNUMBER(I79)),"",IF(F79="Mindestprognose",I79,IF(ISNUMBER(J79),(I79+J79)/2,I79))) | S79: =IF(OR(R79="",NOT(ISNUMBER(L79))),"",R79-L79) | T79: =IF(OR(S79="",G79<>"absolut",NOT(ISNUMBER(L79)),L79=0),"",S79/ABS(L79)) | U79: =IF(T79="","",ABS(T79)) | V79: =IF(OR(F79="Punkt",NOT(ISNUMBER(L79))),"",IF(F79="Mindestprognose",IF(L79>=I79,1,0),IF(AND(ISNUMBER(I79),ISNUMBER(J79),I79<>J79),IF(AND(L79>=I79,L79<=J79),1,0),""))) | W79: Deutlich unterhalb des Vorjahres | X79: =IF(OR(F79="qualitativ",F79="fehlend",NOT(ISNUMBER(L79))),"nicht auswertbar",IF(F79="Punkt","Punktprognose",IF(AND(ISNUMBER(I79),ISNUMBER(J79),I79<>J79),IF(L79<I79,"unterhalb",IF(L79>J79,"oberhalb","innerhalb")),"nicht auswertbar"))) -> nicht auswertbar | Y79: =IF(AND(ISNUMBER(S79),OR(G79="Marge %",G79="Wachstumsrate %")),ABS(S79),"") | Z79: =IFERROR(VLOOKUP(A79,Unternehmen!$A:$D,4,FALSE()),"") -> Chemie
A80: 1COV | B80: 2024 | C80: Umsatz | F80: fehlend | Q80: Umsatzprognose als KPI fehlt | R80: =IF(NOT(ISNUMBER(I80)),"",IF(F80="Mindestprognose",I80,IF(ISNUMBER(J80),(I80+J80)/2,I80))) | S80: =IF(OR(R80="",NOT(ISNUMBER(L80))),"",R80-L80) | T80: =IF(OR(S80="",G80<>"absolut",NOT(ISNUMBER(L80)),L80=0),"",S80/ABS(L80)) | U80: =IF(T80="","",ABS(T80)) | V80: =IF(OR(F80="Punkt",NOT(ISNUMBER(L80))),"",IF(F80="Mindestprognose",IF(L80>=I80,1,0),IF(AND(ISNUMBER(I80),ISNUMBER(J80),I80<>J80),IF(AND(L80>=I80,L80<=J80),1,0),""))) | X80: =IF(OR(F80="qualitativ",F80="fehlend",NOT(ISNUMBER(L80))),"nicht auswertbar",IF(F80="Punkt","Punktprognose",IF(AND(ISNUMBER(I80),ISNUMBER(J80),I80<>J80),IF(L80<I80,"unterhalb",IF(L80>J80,"oberhalb","innerhalb")),"nicht auswertbar"))) -> nicht auswertbar | Y80: =IF(AND(ISNUMBER(S80),OR(G80="Marge %",G80="Wachstumsrate %")),ABS(S80),"") | Z80: =IFERROR(VLOOKUP(A80,Unternehmen!$A:$D,4,FALSE()),"") -> Chemie
A81: 1COV | B81: 2024 | C81: Operative Ergebnisgroesse | D81: 2023: https://bericht.covestro.com/geschaeftsbericht-2023/_assets/downloads/covestro-ar23-entire.pdf | E81: 84 | F81: Punkt mit Korridor | G81: absolut | H81: Mio. EUR | I81: 1000 | J81: 1600 | K81: =L79 -> 1080 | L81: 1071 | M81: =L81-K81 -> -9 | N81: Positiv außerhalb Prognose (oberhalb) | O81: 2024: https://geschaeftsbericht.covestro.com/ecomaXL/files/Covestro_2024_GB_DE.pdf | P81: 90 | R81: =IF(NOT(ISNUMBER(I81)),"",IF(F81="Mindestprognose",I81,IF(ISNUMBER(J81),(I81+J81)/2,I81))) -> 1300 | S81: =IF(OR(R81="",NOT(ISNUMBER(L81))),"",R81-L81) -> 229 | T81: =IF(OR(S81="",G81<>"absolut",NOT(ISNUMBER(L81)),L81=0),"",S81/ABS(L81)) -> 0.21381886 | U81: =IF(T81="","",ABS(T81)) -> 0.21381886 | V81: =IF(OR(F81="Punkt",NOT(ISNUMBER(L81))),"",IF(F81="Mindestprognose",IF(L81>=I81,1,0),IF(AND(ISNUMBER(I81),ISNUMBER(J81),I81<>J81),IF(AND(L81>=I81,L81<=J81),1,0),""))) -> 1 | X81: =IF(OR(F81="qualitativ",F81="fehlend",NOT(ISNUMBER(L81))),"nicht auswertbar",IF(F81="Punkt","Punktprognose",IF(AND(ISNUMBER(I81),ISNUMBER(J81),I81<>J81),IF(L81<I81,"unterhalb",IF(L81>J81,"oberhalb","innerhalb")),"nicht auswertbar"))) -> innerhalb | Y81: =IF(AND(ISNUMBER(S81),OR(G81="Marge %",G81="Wachstumsrate %")),ABS(S81),"") | Z81: =IFERROR(VLOOKUP(A81,Unternehmen!$A:$D,4,FALSE()),"") -> Chemie
A82: DAI | B82: 2020 | C82: Umsatz | D82: 2019: https://group.mercedes-benz.com/dokumente/investoren/berichte/geschaeftsberichte/daimler/daimler-ir-geschaeftsbericht-2019-inkl-zusammengefasster-lagebericht-daimler-ag.pdf | E82: 152 | F82: qualitativ | G82: absolut | H82: Mrd. EUR | K82: 172.75 | L82: 154.31 | M82: =L82-K82 -> -18.44 | N82: Veränderung von -11%, richtung verfehlt | O82: 2020: https://group.mercedes-benz.com/dokumente/investoren/berichte/geschaeftsberichte/daimler/daimler-ir-geschaeftsbericht-2020-inkl-zusammengefasster-lagebericht-daimler-ag.pdf | P82: 2 | R82: =IF(NOT(ISNUMBER(I82)),"",IF(F82="Mindestprognose",I82,IF(ISNUMBER(J82),(I82+J82)/2,I82))) | S82: =IF(OR(R82="",NOT(ISNUMBER(L82))),"",R82-L82) | T82: =IF(OR(S82="",G82<>"absolut",NOT(ISNUMBER(L82)),L82=0),"",S82/ABS(L82)) | U82: =IF(T82="","",ABS(T82)) | V82: =IF(OR(F82="Punkt",NOT(ISNUMBER(L82))),"",IF(F82="Mindestprognose",IF(L82>=I82,1,0),IF(AND(ISNUMBER(I82),ISNUMBER(J82),I82<>J82),IF(AND(L82>=I82,L82<=J82),1,0),""))) | W82: Bewegungen auf Niveau des Vorjahres | X82: =IF(OR(F82="qualitativ",F82="fehlend",NOT(ISNUMBER(L82))),"nicht auswertbar",IF(F82="Punkt","Punktprognose",IF(AND(ISNUMBER(I82),ISNUMBER(J82),I82<>J82),IF(L82<I82,"unterhalb",IF(L82>J82,"oberhalb","innerhalb")),"nicht auswertbar"))) -> nicht auswertbar | Y82: =IF(AND(ISNUMBER(S82),OR(G82="Marge %",G82="Wachstumsrate %")),ABS(S82),"") | Z82: =IFERROR(VLOOKUP(A82,Unternehmen!$A:$D,4,FALSE()),"") -> Automobile
A83: DAI | B83: 2020 | C83: Operative Ergebnisgroesse | D83: 2019: https://group.mercedes-benz.com/dokumente/investoren/berichte/geschaeftsberichte/daimler/daimler-ir-geschaeftsbericht-2019-inkl-zusammengefasster-lagebericht-daimler-ag.pdf | E83: 153 | F83: Bandbreite | G83: Marge % | H83: % (bereinigte Umsatzrendite) | I83: 0.04 | J83: 0.05 | K83: 0.058 | L83: 0.069 | M83: 1,10 PP | N83: Positiv außerhalb Prognose (oberhalb) | O83: 2020: https://group.mercedes-benz.com/dokumente/investoren/berichte/geschaeftsberichte/daimler/daimler-ir-geschaeftsbericht-2020-inkl-zusammengefasster-lagebericht-daimler-ag.pdf | P83: 3 | R83: =IF(NOT(ISNUMBER(I83)),"",IF(F83="Mindestprognose",I83,IF(ISNUMBER(J83),(I83+J83)/2,I83))) -> 0.045 | S83: =IF(OR(R83="",NOT(ISNUMBER(L83))),"",R83-L83) -> -0.024 | T83: =IF(OR(S83="",G83<>"absolut",NOT(ISNUMBER(L83)),L83=0),"",S83/ABS(L83)) | U83: =IF(T83="","",ABS(T83)) | V83: =IF(OR(F83="Punkt",NOT(ISNUMBER(L83))),"",IF(F83="Mindestprognose",IF(L83>=I83,1,0),IF(AND(ISNUMBER(I83),ISNUMBER(J83),I83<>J83),IF(AND(L83>=I83,L83<=J83),1,0),""))) -> 0 | X83: =IF(OR(F83="qualitativ",F83="fehlend",NOT(ISNUMBER(L83))),"nicht auswertbar",IF(F83="Punkt","Punktprognose",IF(AND(ISNUMBER(I83),ISNUMBER(J83),I83<>J83),IF(L83<I83,"unterhalb",IF(L83>J83,"oberhalb","innerhalb")),"nicht auswertbar"))) -> oberhalb | Y83: =IF(AND(ISNUMBER(S83),OR(G83="Marge %",G83="Wachstumsrate %")),ABS(S83),"") -> 0.024 | Z83: =IFERROR(VLOOKUP(A83,Unternehmen!$A:$D,4,FALSE()),"") -> Automobile
A84: DAI | B84: 2021 | C84: Umsatz | D84: 2020: https://group.mercedes-benz.com/dokumente/investoren/berichte/geschaeftsberichte/daimler/daimler-ir-geschaeftsbericht-2020-inkl-zusammengefasster-lagebericht-daimler-ag.pdf | E84: 132 | F84: qualitativ | G84: absolut | H84: Mrd. EUR | K84: =L82 -> 154.31 | L84: 167.97 | M84: =L84-K84 -> 13.66 | N84: Eingetroffen, fortgeführte Aktivitäten +9% | O84: 2021: https://group.mercedes-benz.com/dokumente/investoren/berichte/geschaeftsberichte/mercedes-benz/mercedes-benz-ir-geschaeftsbericht-2021-inkl-zusammengefasster-lagebericht-mbg-ag.pdf | P84: 61 | R84: =IF(NOT(ISNUMBER(I84)),"",IF(F84="Mindestprognose",I84,IF(ISNUMBER(J84),(I84+J84)/2,I84))) | S84: =IF(OR(R84="",NOT(ISNUMBER(L84))),"",R84-L84) | T84: =IF(OR(S84="",G84<>"absolut",NOT(ISNUMBER(L84)),L84=0),"",S84/ABS(L84)) | U84: =IF(T84="","",ABS(T84)) | V84: =IF(OR(F84="Punkt",NOT(ISNUMBER(L84))),"",IF(F84="Mindestprognose",IF(L84>=I84,1,0),IF(AND(ISNUMBER(I84),ISNUMBER(J84),I84<>J84),IF(AND(L84>=I84,L84<=J84),1,0),""))) | W84: Deutlich über dem Vorjahresniveau | X84: =IF(OR(F84="qualitativ",F84="fehlend",NOT(ISNUMBER(L84))),"nicht auswertbar",IF(F84="Punkt","Punktprognose",IF(AND(ISNUMBER(I84),ISNUMBER(J84),I84<>J84),IF(L84<I84,"unterhalb",IF(L84>J84,"oberhalb","innerhalb")),"nicht auswertbar"))) -> nicht auswertbar | Y84: =IF(AND(ISNUMBER(S84),OR(G84="Marge %",G84="Wachstumsrate %")),ABS(S84),"") | Z84: =IFERROR(VLOOKUP(A84,Unternehmen!$A:$D,4,FALSE()),"") -> Automobile
A85: DAI | B85: 2021 | C85: Operative Ergebnisgroesse | D85: 2020: https://group.mercedes-benz.com/dokumente/investoren/berichte/geschaeftsberichte/daimler/daimler-ir-geschaeftsbericht-2020-inkl-zusammengefasster-lagebericht-daimler-ag.pdf | E85: 132 | F85: Bandbreite | G85: Marge % | H85: % (bereinigte Umsatzrendite) | I85: 0.08 | J85: 0.1 | K85: =L83 -> 0.069 | L85: 0.127 | M85: 5,80 PP | N85: Positiv außerhalb Prognose (oberhalb) | O85: 2021: https://group.mercedes-benz.com/dokumente/investoren/berichte/geschaeftsberichte/mercedes-benz/mercedes-benz-ir-geschaeftsbericht-2021-inkl-zusammengefasster-lagebericht-mbg-ag.pdf | P85: 346 | R85: =IF(NOT(ISNUMBER(I85)),"",IF(F85="Mindestprognose",I85,IF(ISNUMBER(J85),(I85+J85)/2,I85))) -> 0.09 | S85: =IF(OR(R85="",NOT(ISNUMBER(L85))),"",R85-L85) -> -0.037 | T85: =IF(OR(S85="",G85<>"absolut",NOT(ISNUMBER(L85)),L85=0),"",S85/ABS(L85)) | U85: =IF(T85="","",ABS(T85)) | V85: =IF(OR(F85="Punkt",NOT(ISNUMBER(L85))),"",IF(F85="Mindestprognose",IF(L85>=I85,1,0),IF(AND(ISNUMBER(I85),ISNUMBER(J85),I85<>J85),IF(AND(L85>=I85,L85<=J85),1,0),""))) -> 0 | X85: =IF(OR(F85="qualitativ",F85="fehlend",NOT(ISNUMBER(L85))),"nicht auswertbar",IF(F85="Punkt","Punktprognose",IF(AND(ISNUMBER(I85),ISNUMBER(J85),I85<>J85),IF(L85<I85,"unterhalb",IF(L85>J85,"oberhalb","innerhalb")),"nicht auswertbar"))) -> oberhalb | Y85: =IF(AND(ISNUMBER(S85),OR(G85="Marge %",G85="Wachstumsrate %")),ABS(S85),"") -> 0.037 | Z85: =IFERROR(VLOOKUP(A85,Unternehmen!$A:$D,4,FALSE()),"") -> Automobile
A86: DAI | B86: 2022 | C86: Umsatz | D86: 2021: https://group.mercedes-benz.com/dokumente/investoren/berichte/geschaeftsberichte/mercedes-benz/mercedes-benz-ir-geschaeftsbericht-2021-inkl-zusammengefasster-lagebericht-mbg-ag.pdf | E86: 152 | F86: qualitativ | G86: absolut | H86: Mrd. EUR | K86: 133.893 | L86: 150.017 | M86: =L86-K86 -> 16.124 | N86: Richtung getroffen, intensität übertroffen +12% (deutlich über) | O86: 2022: https://group.mercedes-benz.com/dokumente/investoren/berichte/geschaeftsberichte/mercedes-benz/mercedes-benz-geschaeftsbericht-2022-inkl-zusammengefasster-lagebericht-mbg-ag.pdf | P86: 57 | R86: =IF(NOT(ISNUMBER(I86)),"",IF(F86="Mindestprognose",I86,IF(ISNUMBER(J86),(I86+J86)/2,I86))) | S86: =IF(OR(R86="",NOT(ISNUMBER(L86))),"",R86-L86) | T86: =IF(OR(S86="",G86<>"absolut",NOT(ISNUMBER(L86)),L86=0),"",S86/ABS(L86)) | U86: =IF(T86="","",ABS(T86)) | V86: =IF(OR(F86="Punkt",NOT(ISNUMBER(L86))),"",IF(F86="Mindestprognose",IF(L86>=I86,1,0),IF(AND(ISNUMBER(I86),ISNUMBER(J86),I86<>J86),IF(AND(L86>=I86,L86<=J86),1,0),""))) | W86: Leicht über dem Vorjahresniveau | X86: =IF(OR(F86="qualitativ",F86="fehlend",NOT(ISNUMBER(L86))),"nicht auswertbar",IF(F86="Punkt","Punktprognose",IF(AND(ISNUMBER(I86),ISNUMBER(J86),I86<>J86),IF(L86<I86,"unterhalb",IF(L86>J86,"oberhalb","innerhalb")),"nicht auswertbar"))) -> nicht auswertbar | Y86: =IF(AND(ISNUMBER(S86),OR(G86="Marge %",G86="Wachstumsrate %")),ABS(S86),"") | Z86: =IFERROR(VLOOKUP(A86,Unternehmen!$A:$D,4,FALSE()),"") -> Automobile
A87: DAI | B87: 2022 | C87: Operative Ergebnisgroesse | D87: 2021: https://group.mercedes-benz.com/dokumente/investoren/berichte/geschaeftsberichte/mercedes-benz/mercedes-benz-ir-geschaeftsbericht-2021-inkl-zusammengefasster-lagebericht-mbg-ag.pdf | E87: 152 | F87: Bandbreite | G87: Marge % | H87: % (bereinigte Umsatzrendite) | I87: 0.115 | J87: 0.13 | K87: 0.131 | L87: 0.146 | M87: 1,50 PP | N87: Positiv außerhalb Prognose (oberhalb) | O87: 2022: https://group.mercedes-benz.com/dokumente/investoren/berichte/geschaeftsberichte/mercedes-benz/mercedes-benz-geschaeftsbericht-2022-inkl-zusammengefasster-lagebericht-mbg-ag.pdf | P87: 361 | R87: =IF(NOT(ISNUMBER(I87)),"",IF(F87="Mindestprognose",I87,IF(ISNUMBER(J87),(I87+J87)/2,I87))) -> 0.1225 | S87: =IF(OR(R87="",NOT(ISNUMBER(L87))),"",R87-L87) -> -0.0235 | T87: =IF(OR(S87="",G87<>"absolut",NOT(ISNUMBER(L87)),L87=0),"",S87/ABS(L87)) | U87: =IF(T87="","",ABS(T87)) | V87: =IF(OR(F87="Punkt",NOT(ISNUMBER(L87))),"",IF(F87="Mindestprognose",IF(L87>=I87,1,0),IF(AND(ISNUMBER(I87),ISNUMBER(J87),I87<>J87),IF(AND(L87>=I87,L87<=J87),1,0),""))) -> 0 | X87: =IF(OR(F87="qualitativ",F87="fehlend",NOT(ISNUMBER(L87))),"nicht auswertbar",IF(F87="Punkt","Punktprognose",IF(AND(ISNUMBER(I87),ISNUMBER(J87),I87<>J87),IF(L87<I87,"unterhalb",IF(L87>J87,"oberhalb","innerhalb")),"nicht auswertbar"))) -> oberhalb | Y87: =IF(AND(ISNUMBER(S87),OR(G87="Marge %",G87="Wachstumsrate %")),ABS(S87),"") -> 0.0235 | Z87: =IFERROR(VLOOKUP(A87,Unternehmen!$A:$D,4,FALSE()),"") -> Automobile
A88: DAI | B88: 2023 | C88: Umsatz | D88: 2022: https://group.mercedes-benz.com/dokumente/investoren/berichte/geschaeftsberichte/mercedes-benz/mercedes-benz-geschaeftsbericht-2022-inkl-zusammengefasster-lagebericht-mbg-ag.pdf | E88: 137 | F88: qualitativ | G88: absolut | H88: Mrd. EUR | K88: =L86 -> 150.017 | L88: 153.22 | M88: =L88-K88 -> 3.203 | N88: 2% über Vorjahresniveau | O88: 2023: https://group.mercedes-benz.com/dokumente/investoren/berichte/geschaeftsberichte/mercedes-benz/mercedes-benz-geschaeftsbericht-2023-inkl-zusammengefasster-lagebericht-mbg-ag.pdf | P88: 129 | R88: =IF(NOT(ISNUMBER(I88)),"",IF(F88="Mindestprognose",I88,IF(ISNUMBER(J88),(I88+J88)/2,I88))) | S88: =IF(OR(R88="",NOT(ISNUMBER(L88))),"",R88-L88) | T88: =IF(OR(S88="",G88<>"absolut",NOT(ISNUMBER(L88)),L88=0),"",S88/ABS(L88)) | U88: =IF(T88="","",ABS(T88)) | V88: =IF(OR(F88="Punkt",NOT(ISNUMBER(L88))),"",IF(F88="Mindestprognose",IF(L88>=I88,1,0),IF(AND(ISNUMBER(I88),ISNUMBER(J88),I88<>J88),IF(AND(L88>=I88,L88<=J88),1,0),""))) | W88: Bewegungen auf Niveau des Vorjahres | X88: =IF(OR(F88="qualitativ",F88="fehlend",NOT(ISNUMBER(L88))),"nicht auswertbar",IF(F88="Punkt","Punktprognose",IF(AND(ISNUMBER(I88),ISNUMBER(J88),I88<>J88),IF(L88<I88,"unterhalb",IF(L88>J88,"oberhalb","innerhalb")),"nicht auswertbar"))) -> nicht auswertbar | Y88: =IF(AND(ISNUMBER(S88),OR(G88="Marge %",G88="Wachstumsrate %")),ABS(S88),"") | Z88: =IFERROR(VLOOKUP(A88,Unternehmen!$A:$D,4,FALSE()),"") -> Automobile
A89: DAI | B89: 2023 | C89: Operative Ergebnisgroesse | D89: 2022: https://group.mercedes-benz.com/dokumente/investoren/berichte/geschaeftsberichte/mercedes-benz/mercedes-benz-geschaeftsbericht-2022-inkl-zusammengefasster-lagebericht-mbg-ag.pdf | E89: 136 | F89: Bandbreite | G89: Marge % | H89: % (bereinigte Umsatzrendite) | I89: 0.12 | J89: 0.14 | K89: =L87 -> 0.146 | L89: 0.126 | M89: -2 PP | N89: im Rahmen | O89: 2023: https://group.mercedes-benz.com/dokumente/investoren/berichte/geschaeftsberichte/mercedes-benz/mercedes-benz-geschaeftsbericht-2023-inkl-zusammengefasster-lagebericht-mbg-ag.pdf | P89: 350 | R89: =IF(NOT(ISNUMBER(I89)),"",IF(F89="Mindestprognose",I89,IF(ISNUMBER(J89),(I89+J89)/2,I89))) -> 0.13 | S89: =IF(OR(R89="",NOT(ISNUMBER(L89))),"",R89-L89) -> 0.004 | T89: =IF(OR(S89="",G89<>"absolut",NOT(ISNUMBER(L89)),L89=0),"",S89/ABS(L89)) | U89: =IF(T89="","",ABS(T89)) | V89: =IF(OR(F89="Punkt",NOT(ISNUMBER(L89))),"",IF(F89="Mindestprognose",IF(L89>=I89,1,0),IF(AND(ISNUMBER(I89),ISNUMBER(J89),I89<>J89),IF(AND(L89>=I89,L89<=J89),1,0),""))) -> 1 | X89: =IF(OR(F89="qualitativ",F89="fehlend",NOT(ISNUMBER(L89))),"nicht auswertbar",IF(F89="Punkt","Punktprognose",IF(AND(ISNUMBER(I89),ISNUMBER(J89),I89<>J89),IF(L89<I89,"unterhalb",IF(L89>J89,"oberhalb","innerhalb")),"nicht auswertbar"))) -> innerhalb | Y89: =IF(AND(ISNUMBER(S89),OR(G89="Marge %",G89="Wachstumsrate %")),ABS(S89),"") -> 0.004 | Z89: =IFERROR(VLOOKUP(A89,Unternehmen!$A:$D,4,FALSE()),"") -> Automobile
A90: DAI | B90: 2024 | C90: Umsatz | D90: 2023: https://group.mercedes-benz.com/dokumente/investoren/berichte/geschaeftsberichte/mercedes-benz/mercedes-benz-geschaeftsbericht-2023-inkl-zusammengefasster-lagebericht-mbg-ag.pdf | E90: 136 | F90: qualitativ | G90: absolut | H90: Mrd. EUR | K90: =L88 -> 153.22 | L90: 145.59 | M90: =L90-K90 -> -7.63 | N90: -4% unter Vorjahresniveau | O90: 2024: https://group.mercedes-benz.com/dokumente/investoren/berichte/geschaeftsberichte/mercedes-benz/mercedes-benz-geschaeftsbericht-2024-inkl-zusammengefasster-lagebericht-mbg-ag.pdf | P90: 82 | R90: =IF(NOT(ISNUMBER(I90)),"",IF(F90="Mindestprognose",I90,IF(ISNUMBER(J90),(I90+J90)/2,I90))) | S90: =IF(OR(R90="",NOT(ISNUMBER(L90))),"",R90-L90) | T90: =IF(OR(S90="",G90<>"absolut",NOT(ISNUMBER(L90)),L90=0),"",S90/ABS(L90)) | U90: =IF(T90="","",ABS(T90)) | V90: =IF(OR(F90="Punkt",NOT(ISNUMBER(L90))),"",IF(F90="Mindestprognose",IF(L90>=I90,1,0),IF(AND(ISNUMBER(I90),ISNUMBER(J90),I90<>J90),IF(AND(L90>=I90,L90<=J90),1,0),""))) | W90: Bewegungen auf Niveau des Vorjahres | X90: =IF(OR(F90="qualitativ",F90="fehlend",NOT(ISNUMBER(L90))),"nicht auswertbar",IF(F90="Punkt","Punktprognose",IF(AND(ISNUMBER(I90),ISNUMBER(J90),I90<>J90),IF(L90<I90,"unterhalb",IF(L90>J90,"oberhalb","innerhalb")),"nicht auswertbar"))) -> nicht auswertbar | Y90: =IF(AND(ISNUMBER(S90),OR(G90="Marge %",G90="Wachstumsrate %")),ABS(S90),"") | Z90: =IFERROR(VLOOKUP(A90,Unternehmen!$A:$D,4,FALSE()),"") -> Automobile
A91: DAI | B91: 2024 | C91: Operative Ergebnisgroesse | D91: 2023: https://group.mercedes-benz.com/dokumente/investoren/berichte/geschaeftsberichte/mercedes-benz/mercedes-benz-geschaeftsbericht-2023-inkl-zusammengefasster-lagebericht-mbg-ag.pdf | E91: 137 | F91: Bandbreite | G91: Marge % | H91: % (bereinigte Umsatzrendite) | I91: 0.1 | J91: 0.12 | K91: =L89 -> 0.126 | L91: 0.081 | M91: -4,50 PP | N91: -1,90 PP | O91: 2024: https://group.mercedes-benz.com/dokumente/investoren/berichte/geschaeftsberichte/mercedes-benz/mercedes-benz-geschaeftsbericht-2024-inkl-zusammengefasster-lagebericht-mbg-ag.pdf | P91: 450 | R91: =IF(NOT(ISNUMBER(I91)),"",IF(F91="Mindestprognose",I91,IF(ISNUMBER(J91),(I91+J91)/2,I91))) -> 0.11 | S91: =IF(OR(R91="",NOT(ISNUMBER(L91))),"",R91-L91) -> 0.029 | T91: =IF(OR(S91="",G91<>"absolut",NOT(ISNUMBER(L91)),L91=0),"",S91/ABS(L91)) | U91: =IF(T91="","",ABS(T91)) | V91: =IF(OR(F91="Punkt",NOT(ISNUMBER(L91))),"",IF(F91="Mindestprognose",IF(L91>=I91,1,0),IF(AND(ISNUMBER(I91),ISNUMBER(J91),I91<>J91),IF(AND(L91>=I91,L91<=J91),1,0),""))) -> 0 | X91: =IF(OR(F91="qualitativ",F91="fehlend",NOT(ISNUMBER(L91))),"nicht auswertbar",IF(F91="Punkt","Punktprognose",IF(AND(ISNUMBER(I91),ISNUMBER(J91),I91<>J91),IF(L91<I91,"unterhalb",IF(L91>J91,"oberhalb","innerhalb")),"nicht auswertbar"))) -> unterhalb | Y91: =IF(AND(ISNUMBER(S91),OR(G91="Marge %",G91="Wachstumsrate %")),ABS(S91),"") -> 0.029 | Z91: =IFERROR(VLOOKUP(A91,Unternehmen!$A:$D,4,FALSE()),"") -> Automobile
A92: DBK | B92: 2020 | C92: Umsatz | D92: 2019: https://investor-relations.db.com/files/documents/annual-reports/Deutsche_Bank_Geschaeftsbericht_2019.pdf?language_id=3 | E92: 40 | F92: qualitativ | G92: absolut | H92: Mrd. EUR | K92: 23.165 | L92: 24.028 | M92: =L92-K92 -> 0.863 | N92: Positiv außerhalb Prognose (oberhalb) | O92: 2020: https://investor-relations.db.com/files/documents/annual-reports/Geschaeftsbericht_2020.pdf?language_id=3 | P92: 299 | R92: =IF(NOT(ISNUMBER(I92)),"",IF(F92="Mindestprognose",I92,IF(ISNUMBER(J92),(I92+J92)/2,I92))) | S92: =IF(OR(R92="",NOT(ISNUMBER(L92))),"",R92-L92) | T92: =IF(OR(S92="",G92<>"absolut",NOT(ISNUMBER(L92)),L92=0),"",S92/ABS(L92)) | U92: =IF(T92="","",ABS(T92)) | V92: =IF(OR(F92="Punkt",NOT(ISNUMBER(L92))),"",IF(F92="Mindestprognose",IF(L92>=I92,1,0),IF(AND(ISNUMBER(I92),ISNUMBER(J92),I92<>J92),IF(AND(L92>=I92,L92<=J92),1,0),""))) | W92: Im Vergleich zum Vorjahr geringfügig niedriger | X92: =IF(OR(F92="qualitativ",F92="fehlend",NOT(ISNUMBER(L92))),"nicht auswertbar",IF(F92="Punkt","Punktprognose",IF(AND(ISNUMBER(I92),ISNUMBER(J92),I92<>J92),IF(L92<I92,"unterhalb",IF(L92>J92,"oberhalb","innerhalb")),"nicht auswertbar"))) -> nicht auswertbar | Y92: =IF(AND(ISNUMBER(S92),OR(G92="Marge %",G92="Wachstumsrate %")),ABS(S92),"") | Z92: =IFERROR(VLOOKUP(A92,Unternehmen!$A:$D,4,FALSE()),"") -> Banken
A93: DBK | B93: 2020 | C93: Operative Ergebnisgroesse | D93: 2019: https://investor-relations.db.com/files/documents/annual-reports/Deutsche_Bank_Geschaeftsbericht_2019.pdf?language_id=3 | E93: 40 | F93: qualitativ | G93: Marge % | H93: % (bereinigte Umsatzrendite) | K93: -0.109 | L93: 0.002 | M93: 11,10 PP | N93: Gestiegen | O93: 2020: https://investor-relations.db.com/files/documents/annual-reports/Geschaeftsbericht_2020.pdf?language_id=3 | P93: 43 | R93: =IF(NOT(ISNUMBER(I93)),"",IF(F93="Mindestprognose",I93,IF(ISNUMBER(J93),(I93+J93)/2,I93))) | S93: =IF(OR(R93="",NOT(ISNUMBER(L93))),"",R93-L93) | T93: =IF(OR(S93="",G93<>"absolut",NOT(ISNUMBER(L93)),L93=0),"",S93/ABS(L93)) | U93: =IF(T93="","",ABS(T93)) | V93: =IF(OR(F93="Punkt",NOT(ISNUMBER(L93))),"",IF(F93="Mindestprognose",IF(L93>=I93,1,0),IF(AND(ISNUMBER(I93),ISNUMBER(J93),I93<>J93),IF(AND(L93>=I93,L93<=J93),1,0),""))) | W93: Sinkend/Belastet | X93: =IF(OR(F93="qualitativ",F93="fehlend",NOT(ISNUMBER(L93))),"nicht auswertbar",IF(F93="Punkt","Punktprognose",IF(AND(ISNUMBER(I93),ISNUMBER(J93),I93<>J93),IF(L93<I93,"unterhalb",IF(L93>J93,"oberhalb","innerhalb")),"nicht auswertbar"))) -> nicht auswertbar | Y93: =IF(AND(ISNUMBER(S93),OR(G93="Marge %",G93="Wachstumsrate %")),ABS(S93),"") | Z93: =IFERROR(VLOOKUP(A93,Unternehmen!$A:$D,4,FALSE()),"") -> Banken
A94: DBK | B94: 2021 | C94: Umsatz | D94: 2020: https://investor-relations.db.com/files/documents/annual-reports/Geschaeftsbericht_2020.pdf?language_id=2 | E94: 43 | F94: qualitativ | G94: absolut | H94: Mrd. EUR | K94: 24.028 | L94: 25.41 | M94: =L94-K94 -> 1.382 | N94: Positiv außerhalb Prognose (oberhalb) | O94: 2021: https://investor-relations.db.com/files/documents/annual-reports/2022/Geschaeftsbericht_2021.pdf | P94: 267 | R94: =IF(NOT(ISNUMBER(I94)),"",IF(F94="Mindestprognose",I94,IF(ISNUMBER(J94),(I94+J94)/2,I94))) | S94: =IF(OR(R94="",NOT(ISNUMBER(L94))),"",R94-L94) | T94: =IF(OR(S94="",G94<>"absolut",NOT(ISNUMBER(L94)),L94=0),"",S94/ABS(L94)) | U94: =IF(T94="","",ABS(T94)) | V94: =IF(OR(F94="Punkt",NOT(ISNUMBER(L94))),"",IF(F94="Mindestprognose",IF(L94>=I94,1,0),IF(AND(ISNUMBER(I94),ISNUMBER(J94),I94<>J94),IF(AND(L94>=I94,L94<=J94),1,0),""))) | W94: Im Vergleich zum Vorjahr geringfügig niedriger | X94: =IF(OR(F94="qualitativ",F94="fehlend",NOT(ISNUMBER(L94))),"nicht auswertbar",IF(F94="Punkt","Punktprognose",IF(AND(ISNUMBER(I94),ISNUMBER(J94),I94<>J94),IF(L94<I94,"unterhalb",IF(L94>J94,"oberhalb","innerhalb")),"nicht auswertbar"))) -> nicht auswertbar | Y94: =IF(AND(ISNUMBER(S94),OR(G94="Marge %",G94="Wachstumsrate %")),ABS(S94),"") | Z94: =IFERROR(VLOOKUP(A94,Unternehmen!$A:$D,4,FALSE()),"") -> Banken
A95: DBK | B95: 2021 | C95: Operative Ergebnisgroesse | F95: fehlend | R95: =IF(NOT(ISNUMBER(I95)),"",IF(F95="Mindestprognose",I95,IF(ISNUMBER(J95),(I95+J95)/2,I95))) | S95: =IF(OR(R95="",NOT(ISNUMBER(L95))),"",R95-L95) | T95: =IF(OR(S95="",G95<>"absolut",NOT(ISNUMBER(L95)),L95=0),"",S95/ABS(L95)) | U95: =IF(T95="","",ABS(T95)) | V95: =IF(OR(F95="Punkt",NOT(ISNUMBER(L95))),"",IF(F95="Mindestprognose",IF(L95>=I95,1,0),IF(AND(ISNUMBER(I95),ISNUMBER(J95),I95<>J95),IF(AND(L95>=I95,L95<=J95),1,0),""))) | X95: =IF(OR(F95="qualitativ",F95="fehlend",NOT(ISNUMBER(L95))),"nicht auswertbar",IF(F95="Punkt","Punktprognose",IF(AND(ISNUMBER(I95),ISNUMBER(J95),I95<>J95),IF(L95<I95,"unterhalb",IF(L95>J95,"oberhalb","innerhalb")),"nicht auswertbar"))) -> nicht auswertbar | Y95: =IF(AND(ISNUMBER(S95),OR(G95="Marge %",G95="Wachstumsrate %")),ABS(S95),"") | Z95: =IFERROR(VLOOKUP(A95,Unternehmen!$A:$D,4,FALSE()),"") -> Banken
A96: DBK | B96: 2022 | C96: Umsatz | D96: 2021: https://investor-relations.db.com/files/documents/annual-reports/2022/Geschaeftsbericht_2021.pdf | E96: 45 | F96: Bandbreite | G96: absolut | H96: Mrd. EUR | I96: 26 | J96: 27 | K96: =L94 -> 25.41 | L96: 27.21 | M96: =L96-K96 -> 1.8 | N96: Positiv außerhalb Prognose (oberhalb) | O96: 2022: https://investor-relations.db.com/files/documents/annual-reports/2023/Geschaeftsbericht-2022.pdf | P96: 268 | R96: =IF(NOT(ISNUMBER(I96)),"",IF(F96="Mindestprognose",I96,IF(ISNUMBER(J96),(I96+J96)/2,I96))) -> 26.5 | S96: =IF(OR(R96="",NOT(ISNUMBER(L96))),"",R96-L96) -> -0.71 | T96: =IF(OR(S96="",G96<>"absolut",NOT(ISNUMBER(L96)),L96=0),"",S96/ABS(L96)) -> -0.026093348 | U96: =IF(T96="","",ABS(T96)) -> 0.026093348 | V96: =IF(OR(F96="Punkt",NOT(ISNUMBER(L96))),"",IF(F96="Mindestprognose",IF(L96>=I96,1,0),IF(AND(ISNUMBER(I96),ISNUMBER(J96),I96<>J96),IF(AND(L96>=I96,L96<=J96),1,0),""))) -> 0 | X96: =IF(OR(F96="qualitativ",F96="fehlend",NOT(ISNUMBER(L96))),"nicht auswertbar",IF(F96="Punkt","Punktprognose",IF(AND(ISNUMBER(I96),ISNUMBER(J96),I96<>J96),IF(L96<I96,"unterhalb",IF(L96>J96,"oberhalb","innerhalb")),"nicht auswertbar"))) -> oberhalb | Y96: =IF(AND(ISNUMBER(S96),OR(G96="Marge %",G96="Wachstumsrate %")),ABS(S96),"") | Z96: =IFERROR(VLOOKUP(A96,Unternehmen!$A:$D,4,FALSE()),"") -> Banken
A97: DBK | B97: 2022 | C97: Operative Ergebnisgroesse | D97: 2021: https://investor-relations.db.com/files/documents/annual-reports/2022/Geschaeftsbericht_2021.pdf | E97: 45 | F97: Punkt | G97: Marge % | H97: % (bereinigte Umsatzrendite) | I97: 0.08 | J97: 0.08 | K97: 0.038 | L97: 0.094 | M97: 5,60 PP | N97: Positiv außerhalb Prognose (oberhalb) | O97: 2022: https://investor-relations.db.com/files/documents/annual-reports/2023/Geschaeftsbericht-2022.pdf | P97: 41 | R97: =IF(NOT(ISNUMBER(I97)),"",IF(F97="Mindestprognose",I97,IF(ISNUMBER(J97),(I97+J97)/2,I97))) -> 0.08 | S97: =IF(OR(R97="",NOT(ISNUMBER(L97))),"",R97-L97) -> -0.014 | T97: =IF(OR(S97="",G97<>"absolut",NOT(ISNUMBER(L97)),L97=0),"",S97/ABS(L97)) | U97: =IF(T97="","",ABS(T97)) | V97: =IF(OR(F97="Punkt",NOT(ISNUMBER(L97))),"",IF(F97="Mindestprognose",IF(L97>=I97,1,0),IF(AND(ISNUMBER(I97),ISNUMBER(J97),I97<>J97),IF(AND(L97>=I97,L97<=J97),1,0),""))) | X97: =IF(OR(F97="qualitativ",F97="fehlend",NOT(ISNUMBER(L97))),"nicht auswertbar",IF(F97="Punkt","Punktprognose",IF(AND(ISNUMBER(I97),ISNUMBER(J97),I97<>J97),IF(L97<I97,"unterhalb",IF(L97>J97,"oberhalb","innerhalb")),"nicht auswertbar"))) -> Punktprognose | Y97: =IF(AND(ISNUMBER(S97),OR(G97="Marge %",G97="Wachstumsrate %")),ABS(S97),"") -> 0.014 | Z97: =IFERROR(VLOOKUP(A97,Unternehmen!$A:$D,4,FALSE()),"") -> Banken
A98: DBK | B98: 2023 | C98: Umsatz | D98: 2022: https://investor-relations.db.com/files/documents/annual-reports/2023/Geschaeftsbericht-2022.pdf | E98: 41 | F98: Bandbreite | G98: absolut | H98: Mrd. EUR | I98: 28 | J98: 29 | K98: =L96 -> 27.21 | L98: 28.879 | M98: =L98-K98 -> 1.669 | N98: im Rahmen | O98: 2023: https://investor-relations.db.com/files/documents/annual-reports/2024/DB-AG-Geschaeftsbericht-2023.pdf | P98: 13 | R98: =IF(NOT(ISNUMBER(I98)),"",IF(F98="Mindestprognose",I98,IF(ISNUMBER(J98),(I98+J98)/2,I98))) -> 28.5 | S98: =IF(OR(R98="",NOT(ISNUMBER(L98))),"",R98-L98) -> -0.379 | T98: =IF(OR(S98="",G98<>"absolut",NOT(ISNUMBER(L98)),L98=0),"",S98/ABS(L98)) -> -0.013123723 | U98: =IF(T98="","",ABS(T98)) -> 0.013123723 | V98: =IF(OR(F98="Punkt",NOT(ISNUMBER(L98))),"",IF(F98="Mindestprognose",IF(L98>=I98,1,0),IF(AND(ISNUMBER(I98),ISNUMBER(J98),I98<>J98),IF(AND(L98>=I98,L98<=J98),1,0),""))) -> 1 | X98: =IF(OR(F98="qualitativ",F98="fehlend",NOT(ISNUMBER(L98))),"nicht auswertbar",IF(F98="Punkt","Punktprognose",IF(AND(ISNUMBER(I98),ISNUMBER(J98),I98<>J98),IF(L98<I98,"unterhalb",IF(L98>J98,"oberhalb","innerhalb")),"nicht auswertbar"))) -> innerhalb | Y98: =IF(AND(ISNUMBER(S98),OR(G98="Marge %",G98="Wachstumsrate %")),ABS(S98),"") | Z98: =IFERROR(VLOOKUP(A98,Unternehmen!$A:$D,4,FALSE()),"") -> Banken
A99: DBK | B99: 2023 | C99: Operative Ergebnisgroesse | F99: fehlend | R99: =IF(NOT(ISNUMBER(I99)),"",IF(F99="Mindestprognose",I99,IF(ISNUMBER(J99),(I99+J99)/2,I99))) | S99: =IF(OR(R99="",NOT(ISNUMBER(L99))),"",R99-L99) | T99: =IF(OR(S99="",G99<>"absolut",NOT(ISNUMBER(L99)),L99=0),"",S99/ABS(L99)) | U99: =IF(T99="","",ABS(T99)) | V99: =IF(OR(F99="Punkt",NOT(ISNUMBER(L99))),"",IF(F99="Mindestprognose",IF(L99>=I99,1,0),IF(AND(ISNUMBER(I99),ISNUMBER(J99),I99<>J99),IF(AND(L99>=I99,L99<=J99),1,0),""))) | X99: =IF(OR(F99="qualitativ",F99="fehlend",NOT(ISNUMBER(L99))),"nicht auswertbar",IF(F99="Punkt","Punktprognose",IF(AND(ISNUMBER(I99),ISNUMBER(J99),I99<>J99),IF(L99<I99,"unterhalb",IF(L99>J99,"oberhalb","innerhalb")),"nicht auswertbar"))) -> nicht auswertbar | Y99: =IF(AND(ISNUMBER(S99),OR(G99="Marge %",G99="Wachstumsrate %")),ABS(S99),"") | Z99: =IFERROR(VLOOKUP(A99,Unternehmen!$A:$D,4,FALSE()),"") -> Banken
A100: DBK | B100: 2024 | C100: Umsatz | D100: 2023: https://investor-relations.db.com/files/documents/annual-reports/2024/DB-AG-Geschaeftsbericht-2023.pdf | E100: 46 | F100: Punkt | G100: absolut | H100: Mrd. EUR | I100: 30 | J100: 30 | K100: =L98 -> 28.879 | L100: 30.092 | M100: =L100-K100 -> 1.213 | N100: im Rahmen | O100: 2024: https://investor-relations.db.com/files/documents/other-presentations-and-events/2024/Geschaeftsbericht-2024-3.pdf | P100: 488 | R100: =IF(NOT(ISNUMBER(I100)),"",IF(F100="Mindestprognose",I100,IF(ISNUMBER(J100),(I100+J100)/2,I100))) -> 30 | S100: =IF(OR(R100="",NOT(ISNUMBER(L100))),"",R100-L100) -> -0.092 | T100: =IF(OR(S100="",G100<>"absolut",NOT(ISNUMBER(L100)),L100=0),"",S100/ABS(L100)) -> -0.003057291 | U100: =IF(T100="","",ABS(T100)) -> 0.003057291 | V100: =IF(OR(F100="Punkt",NOT(ISNUMBER(L100))),"",IF(F100="Mindestprognose",IF(L100>=I100,1,0),IF(AND(ISNUMBER(I100),ISNUMBER(J100),I100<>J100),IF(AND(L100>=I100,L100<=J100),1,0),""))) | X100: =IF(OR(F100="qualitativ",F100="fehlend",NOT(ISNUMBER(L100))),"nicht auswertbar",IF(F100="Punkt","Punktprognose",IF(AND(ISNUMBER(I100),ISNUMBER(J100),I100<>J100),IF(L100<I100,"unterhalb",IF(L100>J100,"oberhalb","innerhalb")),"nicht auswertbar"))) -> Punktprognose | Y100: =IF(AND(ISNUMBER(S100),OR(G100="Marge %",G100="Wachstumsrate %")),ABS(S100),"") | Z100: =IFERROR(VLOOKUP(A100,Unternehmen!$A:$D,4,FALSE()),"") -> Banken
...

Sheet Auswertung
A1: Auswertung Prognosegenauigkeit der damaligen DAX30 Unternehmen (Ist-Jahre 2020-2024)
A3: 1. Ueberblick Stichprobe
A4: Beobachtungen gesamt | B4: =COUNTA(Daten!$A$2:$A$281) -> 280
A5: davon Umsatz | B5: =COUNTIF(Daten!$C$2:$C$281,"Umsatz") -> 140
A6: davon operative Ergebnisgroesse | B6: =COUNTIF(Daten!$C$2:$C$281,"Operative Ergebnisgroesse") -> 140
A8: quantitativ (mit Fehlerwert) | B8: =COUNT(Daten!$S$2:$S$281) -> 177 | C8: Kontrolle (quant.+qual.+fehlend+verbal o. Wert): | D8: =B8+B9+B10+B11 -> 280
A9: qualitativ | B9: =COUNTIF(Daten!$F$2:$F$281,"qualitativ") -> 61
A10: fehlend | B10: =COUNTIF(Daten!$F$2:$F$281,"fehlend") -> 38
A11: verbal-quantifiziert ohne Punktwert | B11: =SUMPRODUCT((Daten!$F$2:$F$281="verbal-quantifiziert")*NOT(ISNUMBER(Daten!$S$2:$S$281))) -> 4
A12: Anteil nicht quantifiziert | B12: =1-B8/B4 -> 0.36785714
A13: 2. Prognoseformen
A14: Bandbreite | B14: =COUNTIF(Daten!$F$2:$F$281,"Bandbreite") -> 78 | C14: =B14/COUNTA(Daten!$A$2:$A$281) -> 0.27857143
A15: Punkt mit Korridor | B15: =COUNTIF(Daten!$F$2:$F$281,"Punkt mit Korridor") -> 60 | C15: =B15/COUNTA(Daten!$A$2:$A$281) -> 0.21428571
A16: Punkt | B16: =COUNTIF(Daten!$F$2:$F$281,"Punkt") -> 31 | C16: =B16/COUNTA(Daten!$A$2:$A$281) -> 0.11071429
A17: verbal-quantifiziert | B17: =COUNTIF(Daten!$F$2:$F$281,"verbal-quantifiziert") -> 12 | C17: =B17/COUNTA(Daten!$A$2:$A$281) -> 0.042857143
A18: qualitativ | B18: =COUNTIF(Daten!$F$2:$F$281,"qualitativ") -> 61 | C18: =B18/COUNTA(Daten!$A$2:$A$281) -> 0.21785714
A19: fehlend | B19: =COUNTIF(Daten!$F$2:$F$281,"fehlend") -> 38 | C19: =B19/COUNTA(Daten!$A$2:$A$281) -> 0.13571429
A21: 3. Genauigkeit gesamt
A22: MAPE (nur absolute KPIs, EUR) | B22: =AVERAGEIFS(Daten!$U$2:$U$281,Daten!$G$2:$G$281,"absolut") -> 0.13360307
A23: Anzahl Beobachtungen dafuer | B23: =COUNTIFS(Daten!$G$2:$G$281,"absolut",Daten!$U$2:$U$281,">=0") -> 119
A24: Bias relativ (Mittel rel. Fehler) | B24: =AVERAGEIFS(Daten!$T$2:$T$281,Daten!$G$2:$G$281,"absolut") -> -0.027163763
A26: MAE in Prozentpunkten (%-KPIs) | B26: =AVERAGE(Daten!$Y$2:$Y$281) -> 0.029465517
A27: Anzahl Beobachtungen dafuer | B27: =COUNT(Daten!$Y$2:$Y$281) -> 58
A29: Trefferquote Bandbreite | B29: =AVERAGE(Daten!$V$2:$V$281) -> 0.28169014
A30: davon innerhalb | B30: =COUNTIF(Daten!$X$2:$X$281,"innerhalb") -> 40
A31: davon oberhalb (Unterschaetzung) | B31: =COUNTIF(Daten!$X$2:$X$281,"oberhalb") -> 49
A32: davon unterhalb (Ueberschaetzung) | B32: =COUNTIF(Daten!$X$2:$X$281,"unterhalb") -> 53
A34: 4. Nach KPI
B35: MAPE (absolut) | C35: n | D35: MAE PP (%-KPI) | E35: n | F35: Trefferquote
A36: Umsatz | B36: =IFERROR(AVERAGEIFS(Daten!$U$2:$U$281,Daten!$G$2:$G$281,"absolut",Daten!$C$2:$C$281,"Umsatz"),"") -> 0.058790235 | C36: =COUNTIFS(Daten!$G$2:$G$281,"absolut",Daten!$C$2:$C$281,"Umsatz",Daten!$U$2:$U$281,">=0") -> 49 | D36: =IFERROR(AVERAGEIFS(Daten!$Y$2:$Y$281,Daten!$C$2:$C$281,"Umsatz"),"") -> 0.053222222 | E36: =COUNTIFS(Daten!$C$2:$C$281,"Umsatz",Daten!$Y$2:$Y$281,">=0") -> 18 | F36: =IFERROR(AVERAGEIFS(Daten!$V$2:$V$281,Daten!$C$2:$C$281,"Umsatz"),"") -> 0.22033898
A37: Operative Ergebnisgroesse | B37: =IFERROR(AVERAGEIFS(Daten!$U$2:$U$281,Daten!$G$2:$G$281,"absolut",Daten!$C$2:$C$281,"Operative Ergebnisgroesse"),"") -> 0.18597205 | C37: =COUNTIFS(Daten!$G$2:$G$281,"absolut",Daten!$C$2:$C$281,"Operative Ergebnisgroesse",Daten!$U$2:$U$281,">=0") -> 70 | D37: =IFERROR(AVERAGEIFS(Daten!$Y$2:$Y$281,Daten!$C$2:$C$281,"Operative Ergebnisgroesse"),"") -> 0.018775 | E37: =COUNTIFS(Daten!$C$2:$C$281,"Operative Ergebnisgroesse",Daten!$Y$2:$Y$281,">=0") -> 40 | F37: =IFERROR(AVERAGEIFS(Daten!$V$2:$V$281,Daten!$C$2:$C$281,"Operative Ergebnisgroesse"),"") -> 0.3253012
A39: 5. Nach Ist-Jahr
A40: Jahr | B40: MAPE (absolut) | C40: n | D40: MAE PP (%-KPI) | E40: n | F40: Trefferquote | G40: Bias rel.
A41: 2020 | B41: =IFERROR(AVERAGEIFS(Daten!$U$2:$U$281,Daten!$G$2:$G$281,"absolut",Daten!$B$2:$B$281,2020),"") -> 0.1315667 | C41: =COUNTIFS(Daten!$G$2:$G$281,"absolut",Daten!$B$2:$B$281,2020,Daten!$U$2:$U$281,">=0") -> 20 | D41: =IFERROR(AVERAGEIFS(Daten!$Y$2:$Y$281,Daten!$B$2:$B$281,2020),"") -> 0.0522 | E41: =COUNTIFS(Daten!$B$2:$B$281,2020,Daten!$Y$2:$Y$281,">=0") -> 10 | F41: =IFERROR(AVERAGEIFS(Daten!$V$2:$V$281,Daten!$B$2:$B$281,2020),"") -> 0.16 | G41: =IFERROR(AVERAGEIFS(Daten!$T$2:$T$281,Daten!$G$2:$G$281,"absolut",Daten!$B$2:$B$281,2020),"") -> 0.086122532
A42: 2021 | B42: =IFERROR(AVERAGEIFS(Daten!$U$2:$U$281,Daten!$G$2:$G$281,"absolut",Daten!$B$2:$B$281,2021),"") -> 0.11739639 | C42: =COUNTIFS(Daten!$G$2:$G$281,"absolut",Daten!$B$2:$B$281,2021,Daten!$U$2:$U$281,">=0") -> 21 | D42: =IFERROR(AVERAGEIFS(Daten!$Y$2:$Y$281,Daten!$B$2:$B$281,2021),"") -> 0.018227273 | E42: =COUNTIFS(Daten!$B$2:$B$281,2021,Daten!$Y$2:$Y$281,">=0") -> 11 | F42: =IFERROR(AVERAGEIFS(Daten!$V$2:$V$281,Daten!$B$2:$B$281,2021),"") -> 0.16 | G42: =IFERROR(AVERAGEIFS(Daten!$T$2:$T$281,Daten!$G$2:$G$281,"absolut",Daten!$B$2:$B$281,2021),"") -> -0.051040693
A43: 2022 | B43: =IFERROR(AVERAGEIFS(Daten!$U$2:$U$281,Daten!$G$2:$G$281,"absolut",Daten!$B$2:$B$281,2022),"") -> 0.11994255 | C43: =COUNTIFS(Daten!$G$2:$G$281,"absolut",Daten!$B$2:$B$281,2022,Daten!$U$2:$U$281,">=0") -> 25 | D43: =IFERROR(AVERAGEIFS(Daten!$Y$2:$Y$281,Daten!$B$2:$B$281,2022),"") -> 0.034576923 | E43: =COUNTIFS(Daten!$B$2:$B$281,2022,Daten!$Y$2:$Y$281,">=0") -> 13 | F43: =IFERROR(AVERAGEIFS(Daten!$V$2:$V$281,Daten!$B$2:$B$281,2022),"") -> 0.33333333 | G43: =IFERROR(AVERAGEIFS(Daten!$T$2:$T$281,Daten!$G$2:$G$281,"absolut",Daten!$B$2:$B$281,2022),"") -> 0.0078482794
A44: 2023 | B44: =IFERROR(AVERAGEIFS(Daten!$U$2:$U$281,Daten!$G$2:$G$281,"absolut",Daten!$B$2:$B$281,2023),"") -> 0.21755754 | C44: =COUNTIFS(Daten!$G$2:$G$281,"absolut",Daten!$B$2:$B$281,2023,Daten!$U$2:$U$281,">=0") -> 27 | D44: =IFERROR(AVERAGEIFS(Daten!$Y$2:$Y$281,Daten!$B$2:$B$281,2023),"") -> 0.020090909 | E44: =COUNTIFS(Daten!$B$2:$B$281,2023,Daten!$Y$2:$Y$281,">=0") -> 11 | F44: =IFERROR(AVERAGEIFS(Daten!$V$2:$V$281,Daten!$B$2:$B$281,2023),"") -> 0.375 | G44: =IFERROR(AVERAGEIFS(Daten!$T$2:$T$281,Daten!$G$2:$G$281,"absolut",Daten!$B$2:$B$281,2023),"") -> -0.13856899
A45: 2024 | B45: =IFERROR(AVERAGEIFS(Daten!$U$2:$U$281,Daten!$G$2:$G$281,"absolut",Daten!$B$2:$B$281,2024),"") -> 0.074211135 | C45: =COUNTIFS(Daten!$G$2:$G$281,"absolut",Daten!$B$2:$B$281,2024,Daten!$U$2:$U$281,">=0") -> 26 | D45: =IFERROR(AVERAGEIFS(Daten!$Y$2:$Y$281,Daten!$B$2:$B$281,2024),"") -> 0.024307692 | E45: =COUNTIFS(Daten!$B$2:$B$281,2024,Daten!$Y$2:$Y$281,">=0") -> 13 | F45: =IFERROR(AVERAGEIFS(Daten!$V$2:$V$281,Daten!$B$2:$B$281,2024),"") -> 0.33333333 | G45: =IFERROR(AVERAGEIFS(Daten!$T$2:$T$281,Daten!$G$2:$G$281,"absolut",Daten!$B$2:$B$281,2024),"") -> -0.012997237
A47: 6. Nach Branche
A48: Branche | B48: MAPE (absolut) | C48: n | D48: MAE PP (%-KPI) | E48: n | F48: Trefferquote
A49: Automobile | B49: =IFERROR(AVERAGEIFS(Daten!$U$2:$U$281,Daten!$G$2:$G$281,"absolut",Daten!$Z$2:$Z$281,"Automobile"),"") -> 0.10261254 | C49: =COUNTIFS(Daten!$G$2:$G$281,"absolut",Daten!$Z$2:$Z$281,"Automobile",Daten!$U$2:$U$281,">=0") -> 5 | D49: =IFERROR(AVERAGEIFS(Daten!$Y$2:$Y$281,Daten!$Z$2:$Z$281,"Automobile"),"") -> 0.0153 | E49: =COUNTIFS(Daten!$Z$2:$Z$281,"Automobile",Daten!$Y$2:$Y$281,">=0") -> 20 | F49: =IFERROR(AVERAGEIFS(Daten!$V$2:$V$281,Daten!$Z$2:$Z$281,"Automobile"),"") -> 0.36
A50: Banken | B50: =IFERROR(AVERAGEIFS(Daten!$U$2:$U$281,Daten!$G$2:$G$281,"absolut",Daten!$Z$2:$Z$281,"Banken"),"") -> 0.014091454 | C50: =COUNTIFS(Daten!$G$2:$G$281,"absolut",Daten!$Z$2:$Z$281,"Banken",Daten!$U$2:$U$281,">=0") -> 3 | D50: =IFERROR(AVERAGEIFS(Daten!$Y$2:$Y$281,Daten!$Z$2:$Z$281,"Banken"),"") -> 0.014 | E50: =COUNTIFS(Daten!$Z$2:$Z$281,"Banken",Daten!$Y$2:$Y$281,">=0") -> 1 | F50: =IFERROR(AVERAGEIFS(Daten!$V$2:$V$281,Daten!$Z$2:$Z$281,"Banken"),"") -> 0.5
A51: Bau | B51: =IFERROR(AVERAGEIFS(Daten!$U$2:$U$281,Daten!$G$2:$G$281,"absolut",Daten!$Z$2:$Z$281,"Bau"),"") -> 0.094877379 | C51: =COUNTIFS(Daten!$G$2:$G$281,"absolut",Daten!$Z$2:$Z$281,"Bau",Daten!$U$2:$U$281,">=0") -> 2 | D51: =IFERROR(AVERAGEIFS(Daten!$Y$2:$Y$281,Daten!$Z$2:$Z$281,"Bau"),"") | E51: =COUNTIFS(Daten!$Z$2:$Z$281,"Bau",Daten!$Y$2:$Y$281,">=0") -> 0 | F51: =IFERROR(AVERAGEIFS(Daten!$V$2:$V$281,Daten!$Z$2:$Z$281,"Bau"),"") -> 0.5
A52: Chemie | B52: =IFERROR(AVERAGEIFS(Daten!$U$2:$U$281,Daten!$G$2:$G$281,"absolut",Daten!$Z$2:$Z$281,"Chemie"),"") -> 0.23755746 | C52: =COUNTIFS(Daten!$G$2:$G$281,"absolut",Daten!$Z$2:$Z$281,"Chemie",Daten!$U$2:$U$281,">=0") -> 11 | D52: =IFERROR(AVERAGEIFS(Daten!$Y$2:$Y$281,Daten!$Z$2:$Z$281,"Chemie"),"") | E52: =COUNTIFS(Daten!$Z$2:$Z$281,"Chemie",Daten!$Y$2:$Y$281,">=0") -> 0 | F52: =IFERROR(AVERAGEIFS(Daten!$V$2:$V$281,Daten!$Z$2:$Z$281,"Chemie"),"") -> 0.18181818
A53: Finanzdienstleister | B53: =IFERROR(AVERAGEIFS(Daten!$U$2:$U$281,Daten!$G$2:$G$281,"absolut",Daten!$Z$2:$Z$281,"Finanzdienstleister"),"") -> 0.06577644 | C53: =COUNTIFS(Daten!$G$2:$G$281,"absolut",Daten!$Z$2:$Z$281,"Finanzdienstleister",Daten!$U$2:$U$281,">=0") -> 9 | D53: =IFERROR(AVERAGEIFS(Daten!$Y$2:$Y$281,Daten!$Z$2:$Z$281,"Finanzdienstleister"),"") | E53: =COUNTIFS(Daten!$Z$2:$Z$281,"Finanzdienstleister",Daten!$Y$2:$Y$281,">=0") -> 0 | F53: =IFERROR(AVERAGEIFS(Daten!$V$2:$V$281,Daten!$Z$2:$Z$281,"Finanzdienstleister"),"") -> 0
A54: Immobilien | B54: =IFERROR(AVERAGEIFS(Daten!$U$2:$U$281,Daten!$G$2:$G$281,"absolut",Daten!$Z$2:$Z$281,"Immobilien"),"") -> 0.02108812 | C54: =COUNTIFS(Daten!$G$2:$G$281,"absolut",Daten!$Z$2:$Z$281,"Immobilien",Daten!$U$2:$U$281,">=0") -> 9 | D54: =IFERROR(AVERAGEIFS(Daten!$Y$2:$Y$281,Daten!$Z$2:$Z$281,"Immobilien"),"") | E54: =COUNTIFS(Daten!$Z$2:$Z$281,"Immobilien",Daten!$Y$2:$Y$281,">=0") -> 0 | F54: =IFERROR(AVERAGEIFS(Daten!$V$2:$V$281,Daten!$Z$2:$Z$281,"Immobilien"),"") -> 0.77777778
A55: Industrie | B55: =IFERROR(AVERAGEIFS(Daten!$U$2:$U$281,Daten!$G$2:$G$281,"absolut",Daten!$Z$2:$Z$281,"Industrie"),"") -> 0.14040823 | C55: =COUNTIFS(Daten!$G$2:$G$281,"absolut",Daten!$Z$2:$Z$281,"Industrie",Daten!$U$2:$U$281,">=0") -> 7 | D55: =IFERROR(AVERAGEIFS(Daten!$Y$2:$Y$281,Daten!$Z$2:$Z$281,"Industrie"),"") -> 0.0248 | E55: =COUNTIFS(Daten!$Z$2:$Z$281,"Industrie",Daten!$Y$2:$Y$281,">=0") -> 5 | F55: =IFERROR(AVERAGEIFS(Daten!$V$2:$V$281,Daten!$Z$2:$Z$281,"Industrie"),"") -> 0.25
A56: Konsumgueter | B56: =IFERROR(AVERAGEIFS(Daten!$U$2:$U$281,Daten!$G$2:$G$281,"absolut",Daten!$Z$2:$Z$281,"Konsumgueter"),"") -> 2.1189844 | C56: =COUNTIFS(Daten!$G$2:$G$281,"absolut",Daten!$Z$2:$Z$281,"Konsumgueter",Daten!$U$2:$U$281,">=0") -> 2 | D56: =IFERROR(AVERAGEIFS(Daten!$Y$2:$Y$281,Daten!$Z$2:$Z$281,"Konsumgueter"),"") -> 0.0445 | E56: =COUNTIFS(Daten!$Z$2:$Z$281,"Konsumgueter",Daten!$Y$2:$Y$281,">=0") -> 24 | F56: =IFERROR(AVERAGEIFS(Daten!$V$2:$V$281,Daten!$Z$2:$Z$281,"Konsumgueter"),"") -> 0.19047619
A57: Pharma & Healthcare | B57: =IFERROR(AVERAGEIFS(Daten!$U$2:$U$281,Daten!$G$2:$G$281,"absolut",Daten!$Z$2:$Z$281,"Pharma & Healthcare"),"") -> 0.062476361 | C57: =COUNTIFS(Daten!$G$2:$G$281,"absolut",Daten!$Z$2:$Z$281,"Pharma & Healthcare",Daten!$U$2:$U$281,">=0") -> 27 | D57: =IFERROR(AVERAGEIFS(Daten!$Y$2:$Y$281,Daten!$Z$2:$Z$281,"Pharma & Healthcare"),"") -> 0.011 | E57: =COUNTIFS(Daten!$Z$2:$Z$281,"Pharma & Healthcare",Daten!$Y$2:$Y$281,">=0") -> 2 | F57: =IFERROR(AVERAGEIFS(Daten!$V$2:$V$281,Daten!$Z$2:$Z$281,"Pharma & Healthcare"),"") -> 0.19230769
A58: Technologie | B58: =IFERROR(AVERAGEIFS(Daten!$U$2:$U$281,Daten!$G$2:$G$281,"absolut",Daten!$Z$2:$Z$281,"Technologie"),"") -> 0.051606702 | C58: =COUNTIFS(Daten!$G$2:$G$281,"absolut",Daten!$Z$2:$Z$281,"Technologie",Daten!$U$2:$U$281,">=0") -> 14 | D58: =IFERROR(AVERAGEIFS(Daten!$Y$2:$Y$281,Daten!$Z$2:$Z$281,"Technologie"),"") -> 0.028 | E58: =COUNTIFS(Daten!$Z$2:$Z$281,"Technologie",Daten!$Y$2:$Y$281,">=0") -> 4 | F58: =IFERROR(AVERAGEIFS(Daten!$V$2:$V$281,Daten!$Z$2:$Z$281,"Technologie"),"") -> 0.14285714
A59: Telekommunikation | B59: =IFERROR(AVERAGEIFS(Daten!$U$2:$U$281,Daten!$G$2:$G$281,"absolut",Daten!$Z$2:$Z$281,"Telekommunikation"),"") -> 0.076248851 | C59: =COUNTIFS(Daten!$G$2:$G$281,"absolut",Daten!$Z$2:$Z$281,"Telekommunikation",Daten!$U$2:$U$281,">=0") -> 5 | D59: =IFERROR(AVERAGEIFS(Daten!$Y$2:$Y$281,Daten!$Z$2:$Z$281,"Telekommunikation"),"") | E59: =COUNTIFS(Daten!$Z$2:$Z$281,"Telekommunikation",Daten!$Y$2:$Y$281,">=0") -> 0 | F59: =IFERROR(AVERAGEIFS(Daten!$V$2:$V$281,Daten!$Z$2:$Z$281,"Telekommunikation"),"")
A60: Transport & Logistik | B60: =IFERROR(AVERAGEIFS(Daten!$U$2:$U$281,Daten!$G$2:$G$281,"absolut",Daten!$Z$2:$Z$281,"Transport & Logistik"),"") -> 0.097765671 | C60: =COUNTIFS(Daten!$G$2:$G$281,"absolut",Daten!$Z$2:$Z$281,"Transport & Logistik",Daten!$U$2:$U$281,">=0") -> 5 | D60: =IFERROR(AVERAGEIFS(Daten!$Y$2:$Y$281,Daten!$Z$2:$Z$281,"Transport & Logistik"),"") | E60: =COUNTIFS(Daten!$Z$2:$Z$281,"Transport & Logistik",Daten!$Y$2:$Y$281,">=0") -> 0 | F60: =IFERROR(AVERAGEIFS(Daten!$V$2:$V$281,Daten!$Z$2:$Z$281,"Transport & Logistik"),"") -> 0.66666667
A61: Versicherungen | B61: =IFERROR(AVERAGEIFS(Daten!$U$2:$U$281,Daten!$G$2:$G$281,"absolut",Daten!$Z$2:$Z$281,"Versicherungen"),"") -> 0.17760302 | C61: =COUNTIFS(Daten!$G$2:$G$281,"absolut",Daten!$Z$2:$Z$281,"Versicherungen",Daten!$U$2:$U$281,">=0") -> 10 | D61: =IFERROR(AVERAGEIFS(Daten!$Y$2:$Y$281,Daten!$Z$2:$Z$281,"Versicherungen"),"") -> 0.0315 | E61: =COUNTIFS(Daten!$Z$2:$Z$281,"Versicherungen",Daten!$Y$2:$Y$281,">=0") -> 2 | F61: =IFERROR(AVERAGEIFS(Daten!$V$2:$V$281,Daten!$Z$2:$Z$281,"Versicherungen"),"") -> 0.4
A62: Versorger | B62: =IFERROR(AVERAGEIFS(Daten!$U$2:$U$281,Daten!$G$2:$G$281,"absolut",Daten!$Z$2:$Z$281,"Versorger"),"") -> 0.14824756 | C62: =COUNTIFS(Daten!$G$2:$G$281,"absolut",Daten!$Z$2:$Z$281,"Versorger",Daten!$U$2:$U$281,">=0") -> 10 | D62: =IFERROR(AVERAGEIFS(Daten!$Y$2:$Y$281,Daten!$Z$2:$Z$281,"Versorger"),"") | E62: =COUNTIFS(Daten!$Z$2:$Z$281,"Versorger",Daten!$Y$2:$Y$281,">=0") -> 0 | F62: =IFERROR(AVERAGEIFS(Daten!$V$2:$V$281,Daten!$Z$2:$Z$281,"Versorger"),"") -> 0.2
A64: 7. Nach Unternehmen
A65: Firma | B65: MAPE (absolut) | C65: n | D65: MAE PP (%-KPI) | E65: n | F65: Trefferquote | G65: qualitativ+fehlend
A66: ADS | B66: =IFERROR(AVERAGEIFS(Daten!$U$2:$U$281,Daten!$G$2:$G$281,"absolut",Daten!$A$2:$A$281,"ADS"),"") -> 2.1189844 | C66: =COUNTIFS(Daten!$G$2:$G$281,"absolut",Daten!$A$2:$A$281,"ADS",Daten!$U$2:$U$281,">=0") -> 2 | D66: =IFERROR(AVERAGEIFS(Daten!$Y$2:$Y$281,Daten!$A$2:$A$281,"ADS"),"") -> 0.080875 | E66: =COUNTIFS(Daten!$A$2:$A$281,"ADS",Daten!$Y$2:$Y$281,">=0") -> 8 | F66: =IFERROR(AVERAGEIFS(Daten!$V$2:$V$281,Daten!$A$2:$A$281,"ADS"),"") -> 0.25 | G66: =COUNTIFS(Daten!$A$2:$A$281,"ADS",Daten!$F$2:$F$281,"qualitativ")+COUNTIFS(Daten!$A$2:$A$281,"ADS",Daten!$F$2:$F$281,"fehlend") -> 0
A67: ALV | B67: =IFERROR(AVERAGEIFS(Daten!$U$2:$U$281,Daten!$G$2:$G$281,"absolut",Daten!$A$2:$A$281,"ALV"),"") -> 0.076721204 | C67: =COUNTIFS(Daten!$G$2:$G$281,"absolut",Daten!$A$2:$A$281,"ALV",Daten!$U$2:$U$281,">=0") -> 5 | D67: =IFERROR(AVERAGEIFS(Daten!$Y$2:$Y$281,Daten!$A$2:$A$281,"ALV"),"") -> 0.0315 | E67: =COUNTIFS(Daten!$A$2:$A$281,"ALV",Daten!$Y$2:$Y$281,">=0") -> 2 | F67: =IFERROR(AVERAGEIFS(Daten!$V$2:$V$281,Daten!$A$2:$A$281,"ALV"),"") -> 0.4 | G67: =COUNTIFS(Daten!$A$2:$A$281,"ALV",Daten!$F$2:$F$281,"qualitativ")+COUNTIFS(Daten!$A$2:$A$281,"ALV",Daten!$F$2:$F$281,"fehlend") -> 3
A68: BAS | B68: =IFERROR(AVERAGEIFS(Daten!$U$2:$U$281,Daten!$G$2:$G$281,"absolut",Daten!$A$2:$A$281,"BAS"),"") -> 0.18873699 | C68: =COUNTIFS(Daten!$G$2:$G$281,"absolut",Daten!$A$2:$A$281,"BAS",Daten!$U$2:$U$281,">=0") -> 9 | D68: =IFERROR(AVERAGEIFS(Daten!$Y$2:$Y$281,Daten!$A$2:$A$281,"BAS"),"") | E68: =COUNTIFS(Daten!$A$2:$A$281,"BAS",Daten!$Y$2:$Y$281,">=0") -> 0 | F68: =IFERROR(AVERAGEIFS(Daten!$V$2:$V$281,Daten!$A$2:$A$281,"BAS"),"") -> 0.11111111 | G68: =COUNTIFS(Daten!$A$2:$A$281,"BAS",Daten!$F$2:$F$281,"qualitativ")+COUNTIFS(Daten!$A$2:$A$281,"BAS",Daten!$F$2:$F$281,"fehlend") -> 1
A69: BAYN | B69: =IFERROR(AVERAGEIFS(Daten!$U$2:$U$281,Daten!$G$2:$G$281,"absolut",Daten!$A$2:$A$281,"BAYN"),"") -> 0.063146919 | C69: =COUNTIFS(Daten!$G$2:$G$281,"absolut",Daten!$A$2:$A$281,"BAYN",Daten!$U$2:$U$281,">=0") -> 8 | D69: =IFERROR(AVERAGEIFS(Daten!$Y$2:$Y$281,Daten!$A$2:$A$281,"BAYN"),"") -> 0.011 | E69: =COUNTIFS(Daten!$A$2:$A$281,"BAYN",Daten!$Y$2:$Y$281,">=0") -> 2 | F69: =IFERROR(AVERAGEIFS(Daten!$V$2:$V$281,Daten!$A$2:$A$281,"BAYN"),"") -> 0.14285714 | G69: =COUNTIFS(Daten!$A$2:$A$281,"BAYN",Daten!$F$2:$F$281,"qualitativ")+COUNTIFS(Daten!$A$2:$A$281,"BAYN",Daten!$F$2:$F$281,"fehlend") -> 0
A70: BEI | B70: =IFERROR(AVERAGEIFS(Daten!$U$2:$U$281,Daten!$G$2:$G$281,"absolut",Daten!$A$2:$A$281,"BEI"),"") | C70: =COUNTIFS(Daten!$G$2:$G$281,"absolut",Daten!$A$2:$A$281,"BEI",Daten!$U$2:$U$281,">=0") -> 0 | D70: =IFERROR(AVERAGEIFS(Daten!$Y$2:$Y$281,Daten!$A$2:$A$281,"BEI"),"") -> 0.034916667 | E70: =COUNTIFS(Daten!$A$2:$A$281,"BEI",Daten!$Y$2:$Y$281,">=0") -> 6 | F70: =IFERROR(AVERAGEIFS(Daten!$V$2:$V$281,Daten!$A$2:$A$281,"BEI"),"") -> 0 | G70: =COUNTIFS(Daten!$A$2:$A$281,"BEI",Daten!$F$2:$F$281,"qualitativ")+COUNTIFS(Daten!$A$2:$A$281,"BEI",Daten!$F$2:$F$281,"fehlend") -> 4
A71: BMW | B71: =IFERROR(AVERAGEIFS(Daten!$U$2:$U$281,Daten!$G$2:$G$281,"absolut",Daten!$A$2:$A$281,"BMW"),"") | C71: =COUNTIFS(Daten!$G$2:$G$281,"absolut",Daten!$A$2:$A$281,"BMW",Daten!$U$2:$U$281,">=0") -> 0 | D71: =IFERROR(AVERAGEIFS(Daten!$Y$2:$Y$281,Daten!$A$2:$A$281,"BMW"),"") -> 0.0154 | E71: =COUNTIFS(Daten!$A$2:$A$281,"BMW",Daten!$Y$2:$Y$281,">=0") -> 5 | F71: =IFERROR(AVERAGEIFS(Daten!$V$2:$V$281,Daten!$A$2:$A$281,"BMW"),"") -> 0.6 | G71: =COUNTIFS(Daten!$A$2:$A$281,"BMW",Daten!$F$2:$F$281,"qualitativ")+COUNTIFS(Daten!$A$2:$A$281,"BMW",Daten!$F$2:$F$281,"fehlend") -> 5
A72: CON | B72: =IFERROR(AVERAGEIFS(Daten!$U$2:$U$281,Daten!$G$2:$G$281,"absolut",Daten!$A$2:$A$281,"CON"),"") -> 0.10261254 | C72: =COUNTIFS(Daten!$G$2:$G$281,"absolut",Daten!$A$2:$A$281,"CON",Daten!$U$2:$U$281,">=0") -> 5 | D72: =IFERROR(AVERAGEIFS(Daten!$Y$2:$Y$281,Daten!$A$2:$A$281,"CON"),"") -> 0.008 | E72: =COUNTIFS(Daten!$A$2:$A$281,"CON",Daten!$Y$2:$Y$281,">=0") -> 5 | F72: =IFERROR(AVERAGEIFS(Daten!$V$2:$V$281,Daten!$A$2:$A$281,"CON"),"") -> 0.4 | G72: =COUNTIFS(Daten!$A$2:$A$281,"CON",Daten!$F$2:$F$281,"qualitativ")+COUNTIFS(Daten!$A$2:$A$281,"CON",Daten!$F$2:$F$281,"fehlend") -> 0
A73: 1COV | B73: =IFERROR(AVERAGEIFS(Daten!$U$2:$U$281,Daten!$G$2:$G$281,"absolut",Daten!$A$2:$A$281,"1COV"),"") -> 0.45724957 | C73: =COUNTIFS(Daten!$G$2:$G$281,"absolut",Daten!$A$2:$A$281,"1COV",Daten!$U$2:$U$281,">=0") -> 2 | D73: =IFERROR(AVERAGEIFS(Daten!$Y$2:$Y$281,Daten!$A$2:$A$281,"1COV"),"") | E73: =COUNTIFS(Daten!$A$2:$A$281,"1COV",Daten!$Y$2:$Y$281,">=0") -> 0 | F73: =IFERROR(AVERAGEIFS(Daten!$V$2:$V$281,Daten!$A$2:$A$281,"1COV"),"") -> 0.5 | G73: =COUNTIFS(Daten!$A$2:$A$281,"1COV",Daten!$F$2:$F$281,"qualitativ")+COUNTIFS(Daten!$A$2:$A$281,"1COV",Daten!$F$2:$F$281,"fehlend") -> 8
A74: DAI | B74: =IFERROR(AVERAGEIFS(Daten!$U$2:$U$281,Daten!$G$2:$G$281,"absolut",Daten!$A$2:$A$281,"DAI"),"") | C74: =COUNTIFS(Daten!$G$2:$G$281,"absolut",Daten!$A$2:$A$281,"DAI",Daten!$U$2:$U$281,">=0") -> 0 | D74: =IFERROR(AVERAGEIFS(Daten!$Y$2:$Y$281,Daten!$A$2:$A$281,"DAI"),"") -> 0.0235 | E74: =COUNTIFS(Daten!$A$2:$A$281,"DAI",Daten!$Y$2:$Y$281,">=0") -> 5 | F74: =IFERROR(AVERAGEIFS(Daten!$V$2:$V$281,Daten!$A$2:$A$281,"DAI"),"") -> 0.2 | G74: =COUNTIFS(Daten!$A$2:$A$281,"DAI",Daten!$F$2:$F$281,"qualitativ")+COUNTIFS(Daten!$A$2:$A$281,"DAI",Daten!$F$2:$F$281,"fehlend") -> 5
A75: DBK | B75: =IFERROR(AVERAGEIFS(Daten!$U$2:$U$281,Daten!$G$2:$G$281,"absolut",Daten!$A$2:$A$281,"DBK"),"") -> 0.014091454 | C75: =COUNTIFS(Daten!$G$2:$G$281,"absolut",Daten!$A$2:$A$281,"DBK",Daten!$U$2:$U$281,">=0") -> 3 | D75: =IFERROR(AVERAGEIFS(Daten!$Y$2:$Y$281,Daten!$A$2:$A$281,"DBK"),"") -> 0.014 | E75: =COUNTIFS(Daten!$A$2:$A$281,"DBK",Daten!$Y$2:$Y$281,">=0") -> 1 | F75: =IFERROR(AVERAGEIFS(Daten!$V$2:$V$281,Daten!$A$2:$A$281,"DBK"),"") -> 0.5 | G75: =COUNTIFS(Daten!$A$2:$A$281,"DBK",Daten!$F$2:$F$281,"qualitativ")+COUNTIFS(Daten!$A$2:$A$281,"DBK",Daten!$F$2:$F$281,"fehlend") -> 6
A76: DB1 | B76: =IFERROR(AVERAGEIFS(Daten!$U$2:$U$281,Daten!$G$2:$G$281,"absolut",Daten!$A$2:$A$281,"DB1"),"") -> 0.06577644 | C76: =COUNTIFS(Daten!$G$2:$G$281,"absolut",Daten!$A$2:$A$281,"DB1",Daten!$U$2:$U$281,">=0") -> 9 | D76: =IFERROR(AVERAGEIFS(Daten!$Y$2:$Y$281,Daten!$A$2:$A$281,"DB1"),"") | E76: =COUNTIFS(Daten!$A$2:$A$281,"DB1",Daten!$Y$2:$Y$281,">=0") -> 0 | F76: =IFERROR(AVERAGEIFS(Daten!$V$2:$V$281,Daten!$A$2:$A$281,"DB1"),"") -> 0 | G76: =COUNTIFS(Daten!$A$2:$A$281,"DB1",Daten!$F$2:$F$281,"qualitativ")+COUNTIFS(Daten!$A$2:$A$281,"DB1",Daten!$F$2:$F$281,"fehlend") -> 1
A77: DPW | B77: =IFERROR(AVERAGEIFS(Daten!$U$2:$U$281,Daten!$G$2:$G$281,"absolut",Daten!$A$2:$A$281,"DPW"),"") -> 0.097765671 | C77: =COUNTIFS(Daten!$G$2:$G$281,"absolut",Daten!$A$2:$A$281,"DPW",Daten!$U$2:$U$281,">=0") -> 5 | D77: =IFERROR(AVERAGEIFS(Daten!$Y$2:$Y$281,Daten!$A$2:$A$281,"DPW"),"") | E77: =COUNTIFS(Daten!$A$2:$A$281,"DPW",Daten!$Y$2:$Y$281,">=0") -> 0 | F77: =IFERROR(AVERAGEIFS(Daten!$V$2:$V$281,Daten!$A$2:$A$281,"DPW"),"") -> 0.66666667 | G77: =COUNTIFS(Daten!$A$2:$A$281,"DPW",Daten!$F$2:$F$281,"qualitativ")+COUNTIFS(Daten!$A$2:$A$281,"DPW",Daten!$F$2:$F$281,"fehlend") -> 5
A78: DTE | B78: =IFERROR(AVERAGEIFS(Daten!$U$2:$U$281,Daten!$G$2:$G$281,"absolut",Daten!$A$2:$A$281,"DTE"),"") -> 0.076248851 | C78: =COUNTIFS(Daten!$G$2:$G$281,"absolut",Daten!$A$2:$A$281,"DTE",Daten!$U$2:$U$281,">=0") -> 5 | D78: =IFERROR(AVERAGEIFS(Daten!$Y$2:$Y$281,Daten!$A$2:$A$281,"DTE"),"") | E78: =COUNTIFS(Daten!$A$2:$A$281,"DTE",Daten!$Y$2:$Y$281,">=0") -> 0 | F78: =IFERROR(AVERAGEIFS(Daten!$V$2:$V$281,Daten!$A$2:$A$281,"DTE"),"") | G78: =COUNTIFS(Daten!$A$2:$A$281,"DTE",Daten!$F$2:$F$281,"qualitativ")+COUNTIFS(Daten!$A$2:$A$281,"DTE",Daten!$F$2:$F$281,"fehlend") -> 5
A79: EOAN | B79: =IFERROR(AVERAGEIFS(Daten!$U$2:$U$281,Daten!$G$2:$G$281,"absolut",Daten!$A$2:$A$281,"EOAN"),"") -> 0.088582528 | C79: =COUNTIFS(Daten!$G$2:$G$281,"absolut",Daten!$A$2:$A$281,"EOAN",Daten!$U$2:$U$281,">=0") -> 5 | D79: =IFERROR(AVERAGEIFS(Daten!$Y$2:$Y$281,Daten!$A$2:$A$281,"EOAN"),"") | E79: =COUNTIFS(Daten!$A$2:$A$281,"EOAN",Daten!$Y$2:$Y$281,">=0") -> 0 | F79: =IFERROR(AVERAGEIFS(Daten!$V$2:$V$281,Daten!$A$2:$A$281,"EOAN"),"") -> 0.2 | G79: =COUNTIFS(Daten!$A$2:$A$281,"EOAN",Daten!$F$2:$F$281,"qualitativ")+COUNTIFS(Daten!$A$2:$A$281,"EOAN",Daten!$F$2:$F$281,"fehlend") -> 5
A80: FRE | B80: =IFERROR(AVERAGEIFS(Daten!$U$2:$U$281,Daten!$G$2:$G$281,"absolut",Daten!$A$2:$A$281,"FRE"),"") -> 0.04110919 | C80: =COUNTIFS(Daten!$G$2:$G$281,"absolut",Daten!$A$2:$A$281,"FRE",Daten!$U$2:$U$281,">=0") -> 9 | D80: =IFERROR(AVERAGEIFS(Daten!$Y$2:$Y$281,Daten!$A$2:$A$281,"FRE"),"") | E80: =COUNTIFS(Daten!$A$2:$A$281,"FRE",Daten!$Y$2:$Y$281,">=0") -> 0 | F80: =IFERROR(AVERAGEIFS(Daten!$V$2:$V$281,Daten!$A$2:$A$281,"FRE"),"") -> 0.22222222 | G80: =COUNTIFS(Daten!$A$2:$A$281,"FRE",Daten!$F$2:$F$281,"qualitativ")+COUNTIFS(Daten!$A$2:$A$281,"FRE",Daten!$F$2:$F$281,"fehlend") -> 1
A81: FME | B81: =IFERROR(AVERAGEIFS(Daten!$U$2:$U$281,Daten!$G$2:$G$281,"absolut",Daten!$A$2:$A$281,"FME"),"") -> 0.081170369 | C81: =COUNTIFS(Daten!$G$2:$G$281,"absolut",Daten!$A$2:$A$281,"FME",Daten!$U$2:$U$281,">=0") -> 10 | D81: =IFERROR(AVERAGEIFS(Daten!$Y$2:$Y$281,Daten!$A$2:$A$281,"FME"),"") | E81: =COUNTIFS(Daten!$A$2:$A$281,"FME",Daten!$Y$2:$Y$281,">=0") -> 0 | F81: =IFERROR(AVERAGEIFS(Daten!$V$2:$V$281,Daten!$A$2:$A$281,"FME"),"") -> 0.2 | G81: =COUNTIFS(Daten!$A$2:$A$281,"FME",Daten!$F$2:$F$281,"qualitativ")+COUNTIFS(Daten!$A$2:$A$281,"FME",Daten!$F$2:$F$281,"fehlend") -> 0
A82: HEI | B82: =IFERROR(AVERAGEIFS(Daten!$U$2:$U$281,Daten!$G$2:$G$281,"absolut",Daten!$A$2:$A$281,"HEI"),"") -> 0.094877379 | C82: =COUNTIFS(Daten!$G$2:$G$281,"absolut",Daten!$A$2:$A$281,"HEI",Daten!$U$2:$U$281,">=0") -> 2 | D82: =IFERROR(AVERAGEIFS(Daten!$Y$2:$Y$281,Daten!$A$2:$A$281,"HEI"),"") | E82: =COUNTIFS(Daten!$A$2:$A$281,"HEI",Daten!$Y$2:$Y$281,">=0") -> 0 | F82: =IFERROR(AVERAGEIFS(Daten!$V$2:$V$281,Daten!$A$2:$A$281,"HEI"),"") -> 0.5 | G82: =COUNTIFS(Daten!$A$2:$A$281,"HEI",Daten!$F$2:$F$281,"qualitativ")+COUNTIFS(Daten!$A$2:$A$281,"HEI",Daten!$F$2:$F$281,"fehlend") -> 8
A83: HEN3 | B83: =IFERROR(AVERAGEIFS(Daten!$U$2:$U$281,Daten!$G$2:$G$281,"absolut",Daten!$A$2:$A$281,"HEN3"),"") | C83: =COUNTIFS(Daten!$G$2:$G$281,"absolut",Daten!$A$2:$A$281,"HEN3",Daten!$U$2:$U$281,">=0") -> 0 | D83: =IFERROR(AVERAGEIFS(Daten!$Y$2:$Y$281,Daten!$A$2:$A$281,"HEN3"),"") -> 0.02115 | E83: =COUNTIFS(Daten!$A$2:$A$281,"HEN3",Daten!$Y$2:$Y$281,">=0") -> 10 | F83: =IFERROR(AVERAGEIFS(Daten!$V$2:$V$281,Daten!$A$2:$A$281,"HEN3"),"") -> 0.22222222 | G83: =COUNTIFS(Daten!$A$2:$A$281,"HEN3",Daten!$F$2:$F$281,"qualitativ")+COUNTIFS(Daten!$A$2:$A$281,"HEN3",Daten!$F$2:$F$281,"fehlend") -> 0
A84: IFX | B84: =IFERROR(AVERAGEIFS(Daten!$U$2:$U$281,Daten!$G$2:$G$281,"absolut",Daten!$A$2:$A$281,"IFX"),"") -> 0.085936765 | C84: =COUNTIFS(Daten!$G$2:$G$281,"absolut",Daten!$A$2:$A$281,"IFX",Daten!$U$2:$U$281,">=0") -> 4 | D84: =IFERROR(AVERAGEIFS(Daten!$Y$2:$Y$281,Daten!$A$2:$A$281,"IFX"),"") -> 0.028 | E84: =COUNTIFS(Daten!$A$2:$A$281,"IFX",Daten!$Y$2:$Y$281,">=0") -> 4 | F84: =IFERROR(AVERAGEIFS(Daten!$V$2:$V$281,Daten!$A$2:$A$281,"IFX"),"") -> 0 | G84: =COUNTIFS(Daten!$A$2:$A$281,"IFX",Daten!$F$2:$F$281,"qualitativ")+COUNTIFS(Daten!$A$2:$A$281,"IFX",Daten!$F$2:$F$281,"fehlend") -> 2
A85: LHA | B85: =IFERROR(AVERAGEIFS(Daten!$U$2:$U$281,Daten!$G$2:$G$281,"absolut",Daten!$A$2:$A$281,"LHA"),"") | C85: =COUNTIFS(Daten!$G$2:$G$281,"absolut",Daten!$A$2:$A$281,"LHA",Daten!$U$2:$U$281,">=0") -> 0 | D85: =IFERROR(AVERAGEIFS(Daten!$Y$2:$Y$281,Daten!$A$2:$A$281,"LHA"),"") | E85: =COUNTIFS(Daten!$A$2:$A$281,"LHA",Daten!$Y$2:$Y$281,">=0") -> 0 | F85: =IFERROR(AVERAGEIFS(Daten!$V$2:$V$281,Daten!$A$2:$A$281,"LHA"),"") | G85: =COUNTIFS(Daten!$A$2:$A$281,"LHA",Daten!$F$2:$F$281,"qualitativ")+COUNTIFS(Daten!$A$2:$A$281,"LHA",Daten!$F$2:$F$281,"fehlend") -> 10
A86: MRK | B86: =IFERROR(AVERAGEIFS(Daten!$U$2:$U$281,Daten!$G$2:$G$281,"absolut",Daten!$A$2:$A$281,"MRK"),"") | C86: =COUNTIFS(Daten!$G$2:$G$281,"absolut",Daten!$A$2:$A$281,"MRK",Daten!$U$2:$U$281,">=0") -> 0 | D86: =IFERROR(AVERAGEIFS(Daten!$Y$2:$Y$281,Daten!$A$2:$A$281,"MRK"),"") | E86: =COUNTIFS(Daten!$A$2:$A$281,"MRK",Daten!$Y$2:$Y$281,">=0") -> 0 | F86: =IFERROR(AVERAGEIFS(Daten!$V$2:$V$281,Daten!$A$2:$A$281,"MRK"),"") | G86: =COUNTIFS(Daten!$A$2:$A$281,"MRK",Daten!$F$2:$F$281,"qualitativ")+COUNTIFS(Daten!$A$2:$A$281,"MRK",Daten!$F$2:$F$281,"fehlend") -> 10
A87: MTX | B87: =IFERROR(AVERAGEIFS(Daten!$U$2:$U$281,Daten!$G$2:$G$281,"absolut",Daten!$A$2:$A$281,"MTX"),"") -> 0.060482466 | C87: =COUNTIFS(Daten!$G$2:$G$281,"absolut",Daten!$A$2:$A$281,"MTX",Daten!$U$2:$U$281,">=0") -> 4 | D87: =IFERROR(AVERAGEIFS(Daten!$Y$2:$Y$281,Daten!$A$2:$A$281,"MTX"),"") -> 0.0135 | E87: =COUNTIFS(Daten!$A$2:$A$281,"MTX",Daten!$Y$2:$Y$281,">=0") -> 2 | F87: =IFERROR(AVERAGEIFS(Daten!$V$2:$V$281,Daten!$A$2:$A$281,"MTX"),"") -> 0.33333333 | G87: =COUNTIFS(Daten!$A$2:$A$281,"MTX",Daten!$F$2:$F$281,"qualitativ")+COUNTIFS(Daten!$A$2:$A$281,"MTX",Daten!$F$2:$F$281,"fehlend") -> 4
A88: MUV2 | B88: =IFERROR(AVERAGEIFS(Daten!$U$2:$U$281,Daten!$G$2:$G$281,"absolut",Daten!$A$2:$A$281,"MUV2"),"") -> 0.27848483 | C88: =COUNTIFS(Daten!$G$2:$G$281,"absolut",Daten!$A$2:$A$281,"MUV2",Daten!$U$2:$U$281,">=0") -> 5 | D88: =IFERROR(AVERAGEIFS(Daten!$Y$2:$Y$281,Daten!$A$2:$A$281,"MUV2"),"") | E88: =COUNTIFS(Daten!$A$2:$A$281,"MUV2",Daten!$Y$2:$Y$281,">=0") -> 0 | F88: =IFERROR(AVERAGEIFS(Daten!$V$2:$V$281,Daten!$A$2:$A$281,"MUV2"),"") | G88: =COUNTIFS(Daten!$A$2:$A$281,"MUV2",Daten!$F$2:$F$281,"qualitativ")+COUNTIFS(Daten!$A$2:$A$281,"MUV2",Daten!$F$2:$F$281,"fehlend") -> 5
A89: RWE | B89: =IFERROR(AVERAGEIFS(Daten!$U$2:$U$281,Daten!$G$2:$G$281,"absolut",Daten!$A$2:$A$281,"RWE"),"") -> 0.20791259 | C89: =COUNTIFS(Daten!$G$2:$G$281,"absolut",Daten!$A$2:$A$281,"RWE",Daten!$U$2:$U$281,">=0") -> 5 | D89: =IFERROR(AVERAGEIFS(Daten!$Y$2:$Y$281,Daten!$A$2:$A$281,"RWE"),"") | E89: =COUNTIFS(Daten!$A$2:$A$281,"RWE",Daten!$Y$2:$Y$281,">=0") -> 0 | F89: =IFERROR(AVERAGEIFS(Daten!$V$2:$V$281,Daten!$A$2:$A$281,"RWE"),"") -> 0.2 | G89: =COUNTIFS(Daten!$A$2:$A$281,"RWE",Daten!$F$2:$F$281,"qualitativ")+COUNTIFS(Daten!$A$2:$A$281,"RWE",Daten!$F$2:$F$281,"fehlend") -> 5
A90: SAP | B90: =IFERROR(AVERAGEIFS(Daten!$U$2:$U$281,Daten!$G$2:$G$281,"absolut",Daten!$A$2:$A$281,"SAP"),"") -> 0.037874676 | C90: =COUNTIFS(Daten!$G$2:$G$281,"absolut",Daten!$A$2:$A$281,"SAP",Daten!$U$2:$U$281,">=0") -> 10 | D90: =IFERROR(AVERAGEIFS(Daten!$Y$2:$Y$281,Daten!$A$2:$A$281,"SAP"),"") | E90: =COUNTIFS(Daten!$A$2:$A$281,"SAP",Daten!$Y$2:$Y$281,">=0") -> 0 | F90: =IFERROR(AVERAGEIFS(Daten!$V$2:$V$281,Daten!$A$2:$A$281,"SAP"),"") -> 0.2 | G90: =COUNTIFS(Daten!$A$2:$A$281,"SAP",Daten!$F$2:$F$281,"qualitativ")+COUNTIFS(Daten!$A$2:$A$281,"SAP",Daten!$F$2:$F$281,"fehlend") -> 0
A91: SIE | B91: =IFERROR(AVERAGEIFS(Daten!$U$2:$U$281,Daten!$G$2:$G$281,"absolut",Daten!$A$2:$A$281,"SIE"),"") -> 0.24697592 | C91: =COUNTIFS(Daten!$G$2:$G$281,"absolut",Daten!$A$2:$A$281,"SIE",Daten!$U$2:$U$281,">=0") -> 3 | D91: =IFERROR(AVERAGEIFS(Daten!$Y$2:$Y$281,Daten!$A$2:$A$281,"SIE"),"") -> 0.032333333 | E91: =COUNTIFS(Daten!$A$2:$A$281,"SIE",Daten!$Y$2:$Y$281,">=0") -> 3 | F91: =IFERROR(AVERAGEIFS(Daten!$V$2:$V$281,Daten!$A$2:$A$281,"SIE"),"") -> 0.16666667 | G91: =COUNTIFS(Daten!$A$2:$A$281,"SIE",Daten!$F$2:$F$281,"qualitativ")+COUNTIFS(Daten!$A$2:$A$281,"SIE",Daten!$F$2:$F$281,"fehlend") -> 4
A92: VOW3 | B92: =IFERROR(AVERAGEIFS(Daten!$U$2:$U$281,Daten!$G$2:$G$281,"absolut",Daten!$A$2:$A$281,"VOW3"),"") | C92: =COUNTIFS(Daten!$G$2:$G$281,"absolut",Daten!$A$2:$A$281,"VOW3",Daten!$U$2:$U$281,">=0") -> 0 | D92: =IFERROR(AVERAGEIFS(Daten!$Y$2:$Y$281,Daten!$A$2:$A$281,"VOW3"),"") -> 0.0143 | E92: =COUNTIFS(Daten!$A$2:$A$281,"VOW3",Daten!$Y$2:$Y$281,">=0") -> 5 | F92: =IFERROR(AVERAGEIFS(Daten!$V$2:$V$281,Daten!$A$2:$A$281,"VOW3"),"") -> 0.2 | G92: =COUNTIFS(Daten!$A$2:$A$281,"VOW3",Daten!$F$2:$F$281,"qualitativ")+COUNTIFS(Daten!$A$2:$A$281,"VOW3",Daten!$F$2:$F$281,"fehlend") -> 1
A93: VNA | B93: =IFERROR(AVERAGEIFS(Daten!$U$2:$U$281,Daten!$G$2:$G$281,"absolut",Daten!$A$2:$A$281,"VNA"),"") -> 0.02108812 | C93: =COUNTIFS(Daten!$G$2:$G$281,"absolut",Daten!$A$2:$A$281,"VNA",Daten!$U$2:$U$281,">=0") -> 9 | D93: =IFERROR(AVERAGEIFS(Daten!$Y$2:$Y$281,Daten!$A$2:$A$281,"VNA"),"") | E93: =COUNTIFS(Daten!$A$2:$A$281,"VNA",Daten!$Y$2:$Y$281,">=0") -> 0 | F93: =IFERROR(AVERAGEIFS(Daten!$V$2:$V$281,Daten!$A$2:$A$281,"VNA"),"") -> 0.77777778 | G93: =COUNTIFS(Daten!$A$2:$A$281,"VNA",Daten!$F$2:$F$281,"qualitativ")+COUNTIFS(Daten!$A$2:$A$281,"VNA",Daten!$F$2:$F$281,"fehlend") -> 1
A95: Hinweis: Alle Werte sind Formeln und aktualisieren sich automatisch, wenn im Blatt 'Daten' etwas geaendert wird.
A97: 8. Ausreisser (|rel. Fehler| > 50 %) - fuer Robustheitsrechnung pruefen
A98: Zeile | B98: Firma | C98: Jahr | D98: rel. Fehler | E98: Hinweis
A99: 9 | B99: ADS | C99: 2023 | D99: =Daten!T9 -> -3.6119403 | E99: Vorzeichenwechsel: Prognose Verlust, Ist Gewinn -> Kennzahl nicht interpretierbar
A100: 11 | B100: ADS | C100: 2024 | D100: =Daten!T11 -> -0.62602842 | E100: sehr niedrige Prognosebasis
A101: 77 | B101: 1COV | C101: 2022 | D101: =Daten!T77 -> 0.70068027 | E101: Ergebniseinbruch Energiekrise
A102: 223 | B102: MUV2 | C102: 2020 | D102: =Daten!T223 -> 1.0644096 | E102: Corona-Schadenbelastung
A103: 257 | B103: SIE | C103: 2022 | D103: =Daten!T257 -> 0.62705667 | E103: Wertminderung Siemens-Energy-Beteiligung (-3,37 EUR je Aktie)
A107: MAPE ohne ADS 2023 | B107: =(SUMIFS(Daten!$U$2:$U$281,Daten!$G$2:$G$281,"absolut")-Daten!U9)/(COUNTIFS(Daten!$G$2:$G$281,"absolut",Daten!$U$2:$U$281,">=0")-1) -> 0.10412563

Sheet Codebook
A1: Thema | B1: Regel
A2: Fehler | B2: Fehler = Prognose_final - Ist_Wert. Positiv = Ueberschaetzung, negativ = Unterschaetzung. Einheit = Einheit der Zeile (EUR bzw. Prozentpunkte).
A3: Prognose_final | B3: Bandbreite / Punkt mit Korridor / verbal-quantifiziert -> Mittelwert aus Unter- und Obergrenze; Punkt -> Punktwert; qualitativ und fehlend -> leer.
A4: Rel_Fehler / APE | B4: Nur fuer Angabetyp 'absolut' (EUR). Bei Margen und Wachstumsraten ist ein relativer Fehler nicht sinnvoll interpretierbar (Nulldurchgang, Vorzeichenwechsel); diese Beobachtungen werden ueber die Abweichung in Prozentpunkten ausgewertet.
A5: Zwei Teilstichproben | B5: Auswertung getrennt: (1) absolute KPIs in EUR -> MAPE; (2) Margen-/Wachstumsraten-KPIs -> mittlere absolute Abweichung in Prozentpunkten. Beide Kennzahlen sind nicht ineinander umrechenbar und werden getrennt ausgewiesen.
A6: Trefferkategorie | B6: innerhalb / oberhalb / unterhalb der Prognosebandbreite; 'Punktprognose' und 'nicht auswertbar' bleiben ausserhalb der Trefferquote. Bei Punktprognosen ist eine punktgenaue Uebereinstimmung praktisch ausgeschlossen.
A7: Prognoseform | B7: Punkt | Bandbreite | Punkt mit Korridor ('X +/- y') | verbal-quantifiziert (Wortlaut in Zahlen uebersetzt) | qualitativ (nur Richtungsaussage, kein Fehlerwert) | fehlend (kein Prognosewert im GB) | zurueckgezogen.
A8: Konvention verbale Angaben | B8: niedrig einstellig = 1-3 %, mittel einstellig = 4-6 %, hoch einstellig = 7-9 %, niedrig bis mittel = 1-6 %, mittel bis hoch = 4-9 %. Diese Uebersetzung ist eine methodische Setzung und in Kap. 3.2 offenzulegen.
A9: Konvention 'auf Vorjahresniveau' | B9: Bei qualitativen Prognosen mit Richtung 'stabil' gilt eine Ist-Abweichung bis +/- 3 % als Richtung getroffen.
A10: Prognose_Wortlaut | B10: Originalformulierung aus dem Geschaeftsbericht. Die Spalten Prog_Untergrenze/-Obergrenze enthalten ausschliesslich Zahlen.
A11: Qualitative Zeilen | B11: Kein Fehlerwert. Basiswert und Ist dienen nur der Richtungspruefung; das Urteil steht in 'Rahmensprengung'.
A12: Einheiten | B12: Innerhalb einer Firma und eines KPI durchgaengig dieselbe Einheit. Prozentangaben als Dezimalwert (0,08 = 8 %) mit Prozentformat.
A13: Stichprobe | B13: DAX30 zum 01.01.2020 (Stand nach Indexanpassung 09/2019); ausgeschlossen: Wirecard (Insolvenz) und Linde plc (keine DRS-20-Prognoseberichtspflicht) -> 28 Unternehmen, Ist-Jahre 2020-2024.
